Workbook

Sheet Assumptions
A1: Local Loyalty — Assumptions (CAD)
A2: Legend: blue = input you can change; black = formula; blue on yellow = scenario override of Base. Non-Base columns follow Base unless overridden. Source/notes in column I. Mirrors model.py ASSUMPTIONS.
A4: Key | B4: Assumption | C4: Base | D4: Bear | E4: Base + reco gates | F4: Lean plan | G4: Bull | H4: Unit | I4: Source / note
A6: Scalar assumptions
A7: months | B7: Months | C7: 36 | D7: =$C$7 -> 36 | E7: =$C$7 -> 36 | F7: =$C$7 -> 36 | G7: =$C$7 -> 36 | H7: months | I7: Projection horizon (CSV + workbook)
A8: extended_months | B8: Extended months | C8: 60 | D8: =$C$8 -> 60 | E8: =$C$8 -> 60 | F8: =$C$8 -> 60 | G8: =$C$8 -> 60 | H8: months | I8: Extended run used ONLY to find break-even if it falls after month 36; keeps launching at the last quarter's pace
A9: starting_cash | B9: Starting cash | C9: 0 | D9: =$C$9 -> 0 | E9: =$C$9 -> 0 | F9: =$C$9 -> 0 | G9: =$C$9 -> 0 | H9: CAD | I9: Founder starts at $0; peak cash need = money required to bootstrap
A10: strip_potential_merchants | B10: Strip potential merchants | C10: 32 | D10: 24 | E10: =$C$10 -> 32 | F10: =$C$10 -> 32 | G10: 38 | H10: merchants/strip | I10: Assumption: 80+ storefronts (PRD strip criterion) x ~55% repeat-visit verticals x ~70% eventually sign
A11: activation_rate | B11: Activation rate | C11: 0.6 | D11: 0.5 | E11: =$C$11 -> 0.6 | F11: =$C$11 -> 0.6 | G11: 0.7 | H11: share of signed | I11: PRD success metric: 60% of signed reach 25 active members
A12: free_merchant_churn | B12: Free merchant churn | C12: 0.015 | D12: 0.025 | E12: =$C$12 -> 0.015 | F12: =$C$12 -> 0.015 | G12: 0.01 | H12: per month | I12: Assumption: business closures + drop-outs; free plan has no switching cost
A13: members_per_active_merchant | B13: Members per active merchant | C13: 75 | D13: 50 | E13: =$C$13 -> 75 | F13: =$C$13 -> 75 | G13: 100 | H13: active members | I13: PRD success metric (month 6 target)
A14: membership_fill_speed | B14: Membership fill speed | C14: 0.35 | D14: =$C$14 -> 0.35 | E14: =$C$14 -> 0.35 | F14: =$C$14 -> 0.35 | G14: =$C$14 -> 0.35 | H14: share of gap closed/month | I14: Assumption: ~6 months to reach target
A15: shops_per_customer | B15: Shops per customer | C15: 1.4 | D15: =$C$15 -> 1.4 | E15: =$C$15 -> 1.4 | F15: =$C$15 -> 1.4 | G15: =$C$15 -> 1.4 | H15: shops per active customer | I15: Assumption from PRD target: 30% of customers hold 2+ shops
A16: customer_churn | B16: Customer churn | C16: 0.04 | D16: =$C$16 -> 0.04 | E16: =$C$16 -> 0.04 | F16: =$C$16 -> 0.04 | G16: =$C$16 -> 0.04 | H16: per month | I16: Assumption: active customers lapsing (drives re-acquisition SMS)
A17: app_user_share | B17: App user share | C17: 0.35 | D17: =$C$17 -> 0.35 | E17: =$C$17 -> 0.35 | F17: =$C$17 -> 0.35 | G17: =$C$17 -> 0.35 | H17: share of active customers | I17: Assumption: most join via wallet pass/phone number and never open the app
A18: unlock_plus_active_merchants | B18: Unlock plus active merchants | C18: 150 | D18: =$C$18 -> 150 | E18: 100 | F18: 100 | G18: =$C$18 -> 150 | H18: active merchants | I18: plans.ts unlockAtMerchants for Plus features
A19: plus_features_ready_month | B19: Plus features ready month | C19: 10 | D19: =$C$19 -> 10 | E19: =$C$19 -> 10 | F19: =$C$19 -> 10 | G19: =$C$19 -> 10 | H19: model month | I19: Assumption: Phase 2 build done Aug 2027 (PRD months 7-12)
A20: unlock_pro_active_merchants | B20: Unlock pro active merchants | C20: 150 | D20: =$C$20 -> 150 | E20: 40 | F20: 40 | G20: =$C$20 -> 150 | H20: active merchants | I20: plans.ts unlockAtMerchants for Pro features
A21: pro_features_ready_month | B21: Pro features ready month | C21: 10 | D21: =$C$21 -> 10 | E21: 8 | F21: 8 | G21: =$C$21 -> 10 | H21: model month | I21: Assumption: Phase 2 build done Aug 2027 (PRD months 7-12)
A22: unlock_bia_active_merchants | B22: Unlock bia active merchants | C22: 100 | D22: =$C$22 -> 100 | E22: =$C$22 -> 100 | F22: =$C$22 -> 100 | G22: =$C$22 -> 100 | H22: active merchants | I22: plans.ts campaigns.neighbourhood unlockAtMerchants
A23: unlock_ads_active_merchants | B23: Unlock ads active merchants | C23: 400 | D23: =$C$23 -> 400 | E23: 300 | F23: 300 | G23: =$C$23 -> 400 | H23: active merchants | I23: plans.ts ads.* unlockAtMerchants
A24: ads_ready_month | B24: Ads ready month | C24: 18 | D24: =$C$24 -> 18 | E24: =$C$24 -> 18 | F24: =$C$24 -> 18 | G24: =$C$24 -> 18 | H24: model month | I24: Assumption: ad tooling built by Apr 2028
A25: mix_food_bev | B25: Mix food bev | C25: 0.35 | D25: =$C$25 -> 0.35 | E25: =$C$25 -> 0.35 | F25: =$C$25 -> 0.35 | G25: =$C$25 -> 0.35 | H25: share of merchants | I25: Assumption: daily-visit anchors of a strip
A26: mix_retail | B26: Mix retail | C26: 0.25 | D26: =$C$26 -> 0.25 | E26: =$C$26 -> 0.25 | F26: =$C$26 -> 0.25 | G26: =$C$26 -> 0.25 | H26: share of merchants | I26: Assumption
A27: mix_repair_auto | B27: Mix repair auto | C27: 0.2 | D27: =$C$27 -> 0.2 | E27: =$C$27 -> 0.2 | F27: =$C$27 -> 0.2 | G27: =$C$27 -> 0.2 | H27: share of merchants | I27: Assumption: PRD says lead with repair/auto for revenue
A28: mix_personal_services | B28: Mix personal services | C28: 0.12 | D28: =$C$28 -> 0.12 | E28: =$C$28 -> 0.12 | F28: =$C$28 -> 0.12 | G28: =$C$28 -> 0.12 | H28: share of merchants | I28: Assumption
A29: mix_pharmacy | B29: Mix pharmacy | C29: 0.08 | D29: =$C$29 -> 0.08 | E29: =$C$29 -> 0.08 | F29: =$C$29 -> 0.08 | G29: =$C$29 -> 0.08 | H29: share of merchants | I29: Assumption
A30: conv12_food_bev | B30: Conv12 food bev | C30: 0.2 | D30: =$C$30 -> 0.2 | E30: =$C$30 -> 0.2 | F30: =$C$30 -> 0.2 | G30: =$C$30 -> 0.2 | H30: 12-month conversion | I30: Assumption: order-ahead/pickup pain is moderate
A31: conv12_retail | B31: Conv12 retail | C31: 0.12 | D31: =$C$31 -> 0.12 | E31: =$C$31 -> 0.12 | F31: =$C$31 -> 0.12 | G31: =$C$31 -> 0.12 | H31: 12-month conversion | I31: Assumption: SMS + push promos only
A32: conv12_repair_auto | B32: Conv12 repair auto | C32: 0.4 | D32: =$C$32 -> 0.4 | E32: =$C$32 -> 0.4 | F32: =$C$32 -> 0.4 | G32: =$C$32 -> 0.4 | H32: 12-month conversion | I32: Assumption: quote approval/deposits replace phone tag (validate with $100 pilot deposits, PRD)
A33: conv12_personal_services | B33: Conv12 personal services | C33: 0.15 | D33: =$C$33 -> 0.15 | E33: =$C$33 -> 0.15 | F33: =$C$33 -> 0.15 | G33: =$C$33 -> 0.15 | H33: 12-month conversion | I33: Assumption
A34: conv12_pharmacy | B34: Conv12 pharmacy | C34: 0.05 | D34: =$C$34 -> 0.05 | E34: =$C$34 -> 0.05 | F34: =$C$34 -> 0.05 | G34: =$C$34 -> 0.05 | H34: 12-month conversion | I34: Assumption: limited by OCP inducement rules
A35: pro_share_food_bev | B35: Pro share food bev | C35: 0.05 | D35: =$C$35 -> 0.05 | E35: =$C$35 -> 0.05 | F35: =$C$35 -> 0.05 | G35: =$C$35 -> 0.05 | H35: share Pro | I35: Assumption
A36: pro_share_retail | B36: Pro share retail | C36: 0.05 | D36: =$C$36 -> 0.05 | E36: =$C$36 -> 0.05 | F36: =$C$36 -> 0.05 | G36: =$C$36 -> 0.05 | H36: share Pro | I36: Assumption
A37: pro_share_repair_auto | B37: Pro share repair auto | C37: 0.85 | D37: =$C$37 -> 0.85 | E37: =$C$37 -> 0.85 | F37: =$C$37 -> 0.85 | G37: =$C$37 -> 0.85 | H37: share Pro | I37: Assumption: service tickets, quotes, invoices are Pro
A38: pro_share_personal_services | B38: Pro share personal services | C38: 0.3 | D38: =$C$38 -> 0.3 | E38: =$C$38 -> 0.3 | F38: =$C$38 -> 0.3 | G38: =$C$38 -> 0.3 | H38: share Pro | I38: Assumption: drop-off scheduling/permissions
A39: pro_share_pharmacy | B39: Pro share pharmacy | C39: 0 | D39: =$C$39 -> 0 | E39: =$C$39 -> 0 | F39: =$C$39 -> 0 | G39: =$C$39 -> 0 | H39: share Pro | I39: Assumption
A40: conversion_multiplier | B40: Conversion multiplier | C40: 1 | D40: 0.6 | E40: =$C$40 -> 1 | F40: =$C$40 -> 1 | G40: 1.3 | H40: x | I40: Scenario/sensitivity lever on all conversion rates
A41: paid_churn | B41: Paid churn | C41: 0.03 | D41: 0.045 | E41: =$C$41 -> 0.03 | F41: =$C$41 -> 0.03 | G41: 0.0225 | H41: per month | I41: PRD assumption (~33-month life); churned payers drop back to Free
A42: price_plus | B42: Price plus | C42: 39 | D42: =$C$42 -> 39 | E42: =$C$42 -> 39 | F42: =$C$42 -> 39 | G42: =$C$42 -> 39 | H42: CAD/month | I42: plans.ts PLANS.plus.priceCents = 3900
A43: price_pro | B43: Price pro | C43: 79 | D43: =$C$43 -> 79 | E43: =$C$43 -> 79 | F43: =$C$43 -> 79 | G43: =$C$43 -> 79 | H43: CAD/month | I43: plans.ts PLANS.pro.priceCents = 7900
A44: platform_fee | B44: Platform fee | C44: 0.0075 | D44: =$C$44 -> 0.0075 | E44: =$C$44 -> 0.0075 | F44: =$C$44 -> 0.0075 | G44: =$C$44 -> 0.0075 | H44: of in-app GMV | I44: plans.ts PLATFORM_PAYMENT_FEE_BPS = 75
A45: payments_adoption | B45: Payments adoption | C45: 0.6 | D45: 0.4 | E45: =$C$45 -> 0.6 | F45: =$C$45 -> 0.6 | G45: 0.75 | H45: share of payers | I45: Assumption: share of paying merchants using in-app payments
A46: gmv_plus | B46: Gmv plus | C46: 2500 | D46: =$C$46 -> 2500 | E46: =$C$46 -> 2500 | F46: =$C$46 -> 2500 | G46: =$C$46 -> 2500 | H46: CAD/month | I46: Assumption: order-ahead volume per Plus merchant using payments
A47: gmv_pro | B47: Gmv pro | C47: 6000 | D47: =$C$47 -> 6000 | E47: =$C$47 -> 6000 | F47: =$C$47 -> 6000 | G47: =$C$47 -> 6000 | H47: CAD/month | I47: Assumption: deposits + invoices per Pro merchant (PRD used $4,000 blended)
A48: avg_ticket | B48: Avg ticket | C48: 35 | D48: =$C$48 -> 35 | E48: =$C$48 -> 35 | F48: =$C$48 -> 35 | G48: =$C$48 -> 35 | H48: CAD | I48: Assumption: average in-app payment (for merchant fee comparison only)
A49: stripe_pct | B49: Stripe pct | C49: 0.029 | D49: =$C$49 -> 0.029 | E49: =$C$49 -> 0.029 | F49: =$C$49 -> 0.029 | G49: =$C$49 -> 0.029 | H49: of GMV | I49: Stripe CA domestic online card rate 2.9% (PRD, via Xero) — paid by merchant
A50: stripe_fixed | B50: Stripe fixed | C50: 0.3 | D50: =$C$50 -> 0.3 | E50: =$C$50 -> 0.3 | F50: =$C$50 -> 0.3 | G50: =$C$50 -> 0.3 | H50: CAD/txn | I50: Stripe CA C$0.30 per txn (PRD) — paid by merchant
A51: connect_pct | B51: Connect pct | C51: 0.0025 | D51: =$C$51 -> 0.0025 | E51: =$C$51 -> 0.0025 | F51: =$C$51 -> 0.0025 | G51: =$C$51 -> 0.0025 | H51: of GMV | I51: Assumption: Stripe Connect platform cost if we pick platform-paid pricing (US list 0.25% + payout fees); VERIFY CAD pricing
A52: connect_account_fee | B52: Connect account fee | C52: 2 | D52: =$C$52 -> 2 | E52: =$C$52 -> 2 | F52: =$C$52 -> 2 | G52: =$C$52 -> 2 | H52: CAD/active account/month | I52: Assumption: Stripe Connect active-account fee; VERIFY
A53: billing_pct | B53: Billing pct | C53: 0.034 | D53: =$C$53 -> 0.034 | E53: =$C$53 -> 0.034 | F53: =$C$53 -> 0.034 | G53: =$C$53 -> 0.034 | H53: of subscription revenue | I53: Assumption: 2.9% card + ~0.5% Stripe Billing; VERIFY
A54: billing_fixed | B54: Billing fixed | C54: 0.3 | D54: =$C$54 -> 0.3 | E54: =$C$54 -> 0.3 | F54: =$C$54 -> 0.3 | G54: =$C$54 -> 0.3 | H54: CAD/invoice | I54: Stripe CA C$0.30 per card txn (PRD)
A55: sms_rate | B55: Sms rate | C55: 0.022 | D55: =$C$55 -> 0.022 | E55: =$C$55 -> 0.022 | F55: =$C$55 -> 0.022 | G55: =$C$55 -> 0.022 | H55: CAD/segment | I55: Twilio CA outbound US$0.0079-0.0083/segment (twilio.com/en-us/sms/pricing/ca, Oct 2026) + carrier fees ~US$0.0064-0.0087 (third-party estimate) = ~US$0.016 x FX 1.38 (assumption); VERIFY before launch
A56: sms_used_plus | B56: Sms used plus | C56: 300 | D56: =$C$56 -> 300 | E56: =$C$56 -> 300 | F56: =$C$56 -> 300 | G56: =$C$56 -> 300 | H56: SMS/month | I56: Assumption: 60% of Plus allowance (plans.ts smsPerMonth = 500)
A57: sms_used_pro | B57: Sms used pro | C57: 900 | D57: =$C$57 -> 900 | E57: =$C$57 -> 900 | F57: =$C$57 -> 900 | G57: =$C$57 -> 900 | H57: SMS/month | I57: Assumption: 60% of Pro allowance (plans.ts smsPerMonth = 1500)
A58: otp_sms_per_new_customer | B58: Otp sms per new customer | C58: 1.5 | D58: =$C$58 -> 1.5 | E58: =$C$58 -> 1.5 | F58: =$C$58 -> 1.5 | G58: =$C$58 -> 1.5 | H58: SMS | I58: Assumption: phone-number join verification + welcome
A59: txn_sms_per_customer | B59: Txn sms per customer | C59: 0.3 | D59: =$C$59 -> 0.3 | E59: =$C$59 -> 0.3 | F59: =$C$59 -> 0.3 | G59: =$C$59 -> 0.3 | H59: SMS/month | I59: Assumption: reward-ready / receipt texts on Free
A60: infra_per_merchant | B60: Infra per merchant | C60: 1 | D60: =$C$60 -> 1 | E60: =$C$60 -> 1 | F60: =$C$60 -> 1 | G60: =$C$60 -> 1 | H60: CAD/month | I60: Assumption: DB, storage, wallet pass updates, email
A61: infra_per_customer | B61: Infra per customer | C61: 0.01 | D61: =$C$61 -> 0.01 | E61: =$C$61 -> 0.01 | F61: =$C$61 -> 0.01 | G61: =$C$61 -> 0.01 | H61: CAD/month | I61: Assumption: per active customer hosting + push
A62: support_hourly | B62: Support hourly | C62: 25 | D62: =$C$62 -> 25 | E62: =$C$62 -> 25 | F62: =$C$62 -> 25 | G62: =$C$62 -> 25 | H62: CAD/hr | I62: Assumption: blended support cost (founder time is free, see fixed costs)
A63: support_min_free | B63: Support min free | C63: 5 | D63: =$C$63 -> 5 | E63: =$C$63 -> 5 | F63: =$C$63 -> 5 | G63: =$C$63 -> 5 | H63: min/merchant/month | I63: Assumption
A64: support_min_paid | B64: Support min paid | C64: 15 | D64: =$C$64 -> 15 | E64: =$C$64 -> 15 | F64: =$C$64 -> 15 | G64: =$C$64 -> 15 | H64: min/merchant/month | I64: Assumption: extra support for ops features
A65: perk_qualify_rate | B65: Perk qualify rate | C65: 0.15 | D65: =$C$65 -> 0.15 | E65: =$C$65 -> 0.15 | F65: =$C$65 -> 0.15 | G65: =$C$65 -> 0.15 | H65: of new customers | I65: Assumption: share hitting 'visit 3 shops on the strip'
A66: perk_value | B66: Perk value | C66: 3 | D66: =$C$66 -> 3 | E66: =$C$66 -> 3 | F66: =$C$66 -> 3 | G66: =$C$66 -> 3 | H66: CAD | I66: Assumption: platform-funded bonus value
A67: perk_redeem_rate | B67: Perk redeem rate | C67: 0.6 | D67: =$C$67 -> 0.6 | E67: =$C$67 -> 0.6 | F67: =$C$67 -> 0.6 | G67: =$C$67 -> 0.6 | H67: share redeemed | I67: Assumption (cost booked when earned x expected redemption)
A68: sessions_per_app_user | B68: Sessions per app user | C68: 6 | D68: =$C$68 -> 6 | E68: =$C$68 -> 6 | F68: =$C$68 -> 6 | G68: =$C$68 -> 6 | H68: sessions/month | I68: Assumption
A69: ad_slots_per_session | B69: Ad slots per session | C69: 2 | D69: =$C$69 -> 2 | E69: =$C$69 -> 2 | F69: =$C$69 -> 2 | G69: =$C$69 -> 2 | H69: slots | I69: Assumption: 1 feed slot + 1 search/map slot
A70: ad_fill_rate | B70: Ad fill rate | C70: 0.2 | D70: 0.1 | E70: =$C$70 -> 0.2 | F70: =$C$70 -> 0.2 | G70: 0.3 | H70: share of slots sold | I70: Assumption: small local inventory, self-serve
A71: ad_cpm | B71: Ad cpm | C71: 12 | D71: 8 | E71: =$C$71 -> 12 | F71: =$C$71 -> 12 | G71: 15 | H71: CAD per 1,000 impressions | I71: Assumption: hyper-local intent; see unit-economics.md rate card
A72: pin_adoption | B72: Pin adoption | C72: 0.03 | D72: =$C$72 -> 0.03 | E72: =$C$72 -> 0.03 | F72: =$C$72 -> 0.03 | G72: =$C$72 -> 0.03 | H72: share of active merchants | I72: Assumption: featured map pin buyers each month
A73: pin_price_month | B73: Pin price month | C73: 75 | D73: =$C$73 -> 75 | E73: =$C$73 -> 75 | F73: =$C$73 -> 75 | G73: =$C$73 -> 75 | H73: CAD/month | I73: Assumption: ~$2.50/day rate card
A74: boost_adoption | B74: Boost adoption | C74: 0.04 | D74: =$C$74 -> 0.04 | E74: =$C$74 -> 0.04 | F74: =$C$74 -> 0.04 | G74: =$C$74 -> 0.04 | H74: share of active merchants | I74: Assumption: nearby push boost buyers each month
A75: boosts_per_buyer | B75: Boosts per buyer | C75: 2 | D75: =$C$75 -> 2 | E75: =$C$75 -> 2 | F75: =$C$75 -> 2 | G75: =$C$75 -> 2 | H75: boosts/month | I75: Assumption
A76: boost_price | B76: Boost price | C76: 25 | D76: =$C$76 -> 25 | E76: =$C$76 -> 25 | F76: =$C$76 -> 25 | G76: =$C$76 -> 25 | H76: CAD/boost | I76: Assumption
A77: ads_ramp_months | B77: Ads ramp months | C77: 6 | D77: =$C$77 -> 6 | E77: =$C$77 -> 6 | F77: =$C$77 -> 6 | G77: =$C$77 -> 6 | H77: months | I77: Assumption: linear ramp to full demand after ads unlock
A78: ads_ops_pct | B78: Ads ops pct | C78: 0.1 | D78: =$C$78 -> 0.1 | E78: =$C$78 -> 0.1 | F78: =$C$78 -> 0.1 | G78: =$C$78 -> 0.1 | H78: of ad revenue | I78: Assumption: creative help, moderation, ad serving
A79: strip_maturity_months | B79: Strip maturity months | C79: 6 | D79: =$C$79 -> 6 | E79: =$C$79 -> 6 | F79: =$C$79 -> 6 | G79: =$C$79 -> 6 | H79: months | I79: Assumption: a strip can sell a campaign 6 months after launch
A80: bia_campaigns_per_strip_year | B80: Bia campaigns per strip year | C80: 1 | D80: 0.5 | E80: =$C$80 -> 1 | F80: 2 | G80: 1.5 | H80: campaigns/mature strip/year | I80: Assumption
A81: bia_price | B81: Bia price | C81: 2250 | D81: =$C$81 -> 2250 | E81: =$C$81 -> 2250 | F81: =$C$81 -> 2250 | G81: =$C$81 -> 2250 | H81: CAD/campaign | I81: Midpoint of founder's $1,500-3,000 range
A82: bia_cost_pct | B82: Bia cost pct | C82: 0.3 | D82: =$C$82 -> 0.3 | E82: =$C$82 -> 0.3 | F82: =$C$82 -> 0.3 | G82: =$C$82 -> 0.3 | H82: of campaign revenue | I82: Assumption: prize basket, print, rep hours
A83: rep_wage | B83: Rep wage | C83: 17.95 | D83: =$C$83 -> 17.95 | E83: =$C$83 -> 17.95 | F83: =$C$83 -> 17.95 | G83: =$C$83 -> 17.95 | H83: CAD/hr | I83: Ontario general minimum wage from Oct 1, 2026 (Hicks Morley, cited in PRD)
A84: wage_indexation | B84: Wage indexation | C84: 0.025 | D84: =$C$84 -> 0.025 | E84: =$C$84 -> 0.025 | F84: =$C$84 -> 0.025 | G84: =$C$84 -> 0.025 | H84: per year (each Oct 1) | I84: Assumption: Ontario indexes min wage to CPI every Oct 1
A85: payroll_burden | B85: Payroll burden | C85: 0.13 | D85: =$C$85 -> 0.13 | E85: =$C$85 -> 0.13 | F85: =$C$85 -> 0.13 | G85: =$C$85 -> 0.13 | H85: of wages | I85: Assumption: 4% vacation pay + CPP ~5.95% + EI ~2.3% + WSIB ~1%; VERIFY
A86: rep_hours_per_signup | B86: Rep hours per signup | C86: 2.5 | D86: 3.5 | E86: =$C$86 -> 2.5 | F86: =$C$86 -> 2.5 | G86: 2 | H86: paid hours/signed merchant | I86: PRD: ~3 activations per 6-hour shift (2h) + 0.5h prospecting and day-7/30 calls
A87: activation_bonus | B87: Activation bonus | C87: 25 | D87: =$C$87 -> 25 | E87: =$C$87 -> 25 | F87: =$C$87 -> 25 | G87: =$C$87 -> 25 | H87: CAD/activated merchant | I87: PRD: bonus at 25 active members (paid on top of wage)
A88: kit_cost | B88: Kit cost | C88: 15 | D88: =$C$88 -> 15 | E88: =$C$88 -> 15 | F88: =$C$88 -> 15 | G88: =$C$88 -> 15 | H88: CAD/signed merchant | I88: PRD: QR counter stand + print
A89: strip_launch_cost | B89: Strip launch cost | C89: 750 | D89: =$C$89 -> 750 | E89: =$C$89 -> 750 | F89: =$C$89 -> 750 | G89: =$C$89 -> 750 | H89: CAD/strip | I89: Assumption: passport week prizes, flyers, launch event
A90: upsell_cost | B90: Upsell cost | C90: 50 | D90: =$C$90 -> 50 | E90: =$C$90 -> 50 | F90: =$C$90 -> 50 | G90: =$C$90 -> 50 | H90: CAD/conversion | I90: PRD: upsell bonus / onboarding of paid features
A91: cac_multiplier | B91: Cac multiplier | C91: 1 | D91: =$C$91 -> 1 | E91: =$C$91 -> 1 | F91: =$C$91 -> 1 | G91: =$C$91 -> 1 | H91: x | I91: Scenario/sensitivity lever on all acquisition spend
A92: fixed_hosting_base | B92: Fixed hosting base | C92: 250 | D92: =$C$92 -> 250 | E92: =$C$92 -> 250 | F92: =$C$92 -> 250 | G92: =$C$92 -> 250 | H92: CAD/month | I92: Assumption: managed DB, hosting, monitoring (Canadian region)
A93: fixed_saas_tools | B93: Fixed saas tools | C93: 250 | D93: =$C$93 -> 250 | E93: =$C$93 -> 250 | F93: =$C$93 -> 250 | G93: =$C$93 -> 250 | H93: CAD/month | I93: Assumption: email, design, CRM, Google Workspace
A94: fixed_insurance | B94: Fixed insurance | C94: 150 | D94: =$C$94 -> 150 | E94: =$C$94 -> 150 | F94: =$C$94 -> 150 | G94: =$C$94 -> 150 | H94: CAD/month | I94: Assumption: CGL + cyber/privacy liability
A95: fixed_accounting | B95: Fixed accounting | C95: 250 | D95: =$C$95 -> 250 | E95: =$C$95 -> 250 | F95: =$C$95 -> 250 | G95: =$C$95 -> 250 | H95: CAD/month | I95: Assumption: bookkeeping + year-end
A96: fixed_app_stores | B96: Fixed app stores | C96: 15 | D96: =$C$96 -> 15 | E96: =$C$96 -> 15 | F96: =$C$96 -> 15 | G96: =$C$96 -> 15 | H96: CAD/month | I96: Apple Developer US$99/yr + Google Play one-time US$25, amortised
A97: fixed_phone_misc | B97: Fixed phone misc | C97: 100 | D97: =$C$97 -> 100 | E97: =$C$97 -> 100 | F97: =$C$97 -> 100 | G97: =$C$97 -> 100 | H97: CAD/month | I97: Assumption
A98: fixed_marketing | B98: Fixed marketing | C98: 300 | D98: =$C$98 -> 300 | E98: =$C$98 -> 300 | F98: =$C$98 -> 300 | G98: =$C$98 -> 300 | H98: CAD/month | I98: Assumption: baseline brand, social, local press
A99: fixed_legal_reserve | B99: Fixed legal reserve | C99: 150 | D99: =$C$99 -> 150 | E99: =$C$99 -> 150 | F99: =$C$99 -> 150 | G99: =$C$99 -> 150 | H99: CAD/month | I99: Assumption: ongoing legal/compliance reserve
A100: dev_monthly_y1 | B100: Dev monthly y1 | C100: 4000 | D100: =$C$100 -> 4000 | E100: =$C$100 -> 4000 | F100: 2000 | G100: =$C$100 -> 4000 | H100: CAD/month | I100: PRD: part-time contract developer ~$4,000/mo
A101: dev_monthly_y2 | B101: Dev monthly y2 | C101: 5000 | D101: =$C$101 -> 5000 | E101: =$C$101 -> 5000 | F101: 2500 | G101: =$C$101 -> 5000 | H101: CAD/month | I101: Assumption: more hours for Phase 2 (ops features)
A102: dev_monthly_y3 | B102: Dev monthly y3 | C102: 6000 | D102: =$C$102 -> 6000 | E102: =$C$102 -> 6000 | F102: 3000 | G102: =$C$102 -> 6000 | H102: CAD/month | I102: Assumption: Phase 3 (ads, campaigns)
...

Sheet Scenarios
A1: Scenarios — live KPIs from each monthly sheet (CAD)
A2: Scenario inputs are the columns of the Assumptions sheet; overrides are highlighted there.
A4: Metric | B4: Base | C4: Bear | D4: Base + reco gates | E4: Lean plan | F4: Bull
A5: Break-even month (36m) | B5: =Monthly!$C$85 -> none | C5: =Monthly_Bear!$C$85 -> none | D5: =Monthly_RecoGates!$C$85 -> none | E5: =Monthly_Lean!$C$85 -> none | F5: =Monthly_Bull!$C$85 -> none
A6: Break-even month (60m run) | B6: =Monthly!$C$86 -> 60 | C6: =Monthly_Bear!$C$86 -> none | D6: =Monthly_RecoGates!$C$86 -> 60 | E6: =Monthly_Lean!$C$86 -> 39 | F6: =Monthly_Bull!$C$86 -> 46
A7: First EBITDA-positive month | B7: =Monthly!$C$87 -> none | C7: =Monthly_Bear!$C$87 -> none | D7: =Monthly_RecoGates!$C$87 -> none | E7: =Monthly_Lean!$C$87 -> none | F7: =Monthly_Bull!$C$87 -> none
A8: Peak cash need, months 1-36 | B8: =Monthly!$C$88 -> 322991.1 | C8: =Monthly_Bear!$C$88 -> 305899.55 | D8: =Monthly_RecoGates!$C$88 -> 310918.03 | E8: =Monthly_Lean!$C$88 -> 197411.15 | F8: =Monthly_Bull!$C$88 -> 297222.86
A9: Cash needed to reach break-even (60m) | B9: =Monthly!$C$90 -> 420715.24 | C9: =Monthly_Bear!$C$90 -> 545418.1 | D9: =Monthly_RecoGates!$C$90 -> 401426.7 | E9: =Monthly_Lean!$C$90 -> 199397.64 | F9: =Monthly_Bull!$C$90 -> 315810.81
A10: Cash trough month (36m) | B10: =Monthly!$C$89 -> 36 | C10: =Monthly_Bear!$C$89 -> 36 | D10: =Monthly_RecoGates!$C$89 -> 36 | E10: =Monthly_Lean!$C$89 -> 36 | F10: =Monthly_Bull!$C$89 -> 36
A11: Plus unlock month | B11: =Monthly!$C$91 -> 22 | C11: =Monthly_Bear!$C$91 -> 36 | D11: =Monthly_RecoGates!$C$91 -> 18 | E11: =Monthly_Lean!$C$91 -> 16 | F11: =Monthly_Bull!$C$91 -> 16
A12: Pro unlock month | B12: =Monthly!$C$92 -> 22 | C12: =Monthly_Bear!$C$92 -> 36 | D12: =Monthly_RecoGates!$C$92 -> 12 | E12: =Monthly_Lean!$C$92 -> 11 | F12: =Monthly_Bull!$C$92 -> 16
A13: BIA unlock month | B13: =Monthly!$C$93 -> 18 | C13: =Monthly_Bear!$C$93 -> 29 | D13: =Monthly_RecoGates!$C$93 -> 18 | E13: =Monthly_Lean!$C$93 -> 16 | F13: =Monthly_Bull!$C$93 -> 14
A14: Ads unlock month | B14: =Monthly!$C$94 -> none | C14: =Monthly_Bear!$C$94 -> none | D14: =Monthly_RecoGates!$C$94 -> 31 | E14: =Monthly_Lean!$C$94 -> 27 | F14: =Monthly_Bull!$C$94 -> 26
A15: Month-36 active merchants | B15: =Monthly!$C$95 -> 398.76048 | C15: =Monthly_Bear!$C$95 -> 155.61935 | D15: =Monthly_RecoGates!$C$95 -> 398.76048 | E15: =Monthly_Lean!$C$95 -> 546.01289 | F15: =Monthly_Bull!$C$95 -> 797.3703
A16: Month-36 paying merchants | B16: =Monthly!$C$96 -> 58.104389 | C16: =Monthly_Bear!$C$96 -> 1.8102727 | D16: =Monthly_RecoGates!$C$96 -> 62.541469 | E16: =Monthly_Lean!$C$96 -> 86.712948 | F16: =Monthly_Bull!$C$96 -> 162.16383
A17: Month-36 active customers | B17: =Monthly!$C$97 -> 19474.991 | C17: =Monthly_Bear!$C$97 -> 5041.5366 | D17: =Monthly_RecoGates!$C$97 -> 19474.991 | E17: =Monthly_Lean!$C$97 -> 26607.87 | F17: =Monthly_Bull!$C$97 -> 51684.321
A18: Month-36 revenue | B18: =Monthly!$C$98 -> 8117.5131 | C18: =Monthly_Bear!$C$98 -> 1434.5128 | D18: =Monthly_RecoGates!$C$98 -> 10333.828 | E18: =Monthly_Lean!$C$98 -> 19693.578 | F18: =Monthly_Bull!$C$98 -> 24766.787
A19: Month-36 EBITDA | B19: =Monthly!$C$99 -> -9622.449 | C19: =Monthly_Bear!$C$99 -> -10902.903 | D19: =Monthly_RecoGates!$C$99 -> -7711.5074 | E19: =Monthly_Lean!$C$99 -> -1648.6465 | F19: =Monthly_Bull!$C$99 -> -3785.9249
A20: Year-1 revenue | B20: =Monthly!$C$100 -> 0 | C20: =Monthly_Bear!$C$100 -> 0 | D20: =Monthly_RecoGates!$C$100 -> 35.16651 | E20: =Monthly_Lean!$C$100 -> 116.79014 | F20: =Monthly_Bull!$C$100 -> 0
A21: Year-2 revenue | B21: =Monthly!$C$101 -> 8877.7828 | C21: =Monthly_Bear!$C$101 -> 0 | D21: =Monthly_RecoGates!$C$101 -> 14442.006 | E21: =Monthly_Lean!$C$101 -> 34541.848 | F21: =Monthly_Bull!$C$101 -> 36148.209
A22: Year-3 revenue | B22: =Monthly!$C$102 -> 62747.457 | C22: =Monthly_Bear!$C$102 -> 8184.5128 | D22: =Monthly_RecoGates!$C$102 -> 74485.46 | E22: =Monthly_Lean!$C$102 -> 156099.47 | F22: =Monthly_Bull!$C$102 -> 193437.7
A23: Year-1 EBITDA | B23: =Monthly!$C$103 -> -84348.511 | C23: =Monthly_Bear!$C$103 -> -78847.286 | D23: =Monthly_RecoGates!$C$103 -> -84344.415 | E23: =Monthly_Lean!$C$103 -> -63351.367 | F23: =Monthly_Bull!$C$103 -> -88986.255
A24: Year-2 EBITDA | B24: =Monthly!$C$104 -> -113012.32 | C24: =Monthly_Bear!$C$104 -> -99702.923 | D24: =Monthly_RecoGates!$C$104 -> -110057.24 | E24: =Monthly_Lean!$C$104 -> -82521.603 | F24: =Monthly_Bull!$C$104 -> -122340.52
A25: Year-3 EBITDA | B25: =Monthly!$C$105 -> -125630.27 | C25: =Monthly_Bear!$C$105 -> -127349.34 | D25: =Monthly_RecoGates!$C$105 -> -116516.37 | E25: =Monthly_Lean!$C$105 -> -51538.178 | F25: =Monthly_Bull!$C$105 -> -85896.087
A27: LTV/CAC (from Unit Economics) | B27: ='Unit Economics'!B22 -> 2.6460144 | C27: ='Unit Economics'!C22 -> 0.78088083 | D27: ='Unit Economics'!D22 -> 2.6460144 | E27: ='Unit Economics'!E22 -> 2.6460144 | F27: ='Unit Economics'!F22 -> 5.5152978
A28: Payback months (from Unit Economics) | B28: ='Unit Economics'!B23 -> 12.597563 | C28: ='Unit Economics'!C23 -> 28.457892 | D28: ='Unit Economics'!D23 -> 12.597563 | E28: ='Unit Economics'!E23 -> 12.597563 | F28: ='Unit Economics'!F23 -> 8.0583943

Sheet Unit Economics
A1: Unit economics — steady state, per merchant per month (CAD)
A2: Live formulas on the Assumptions sheet. CAC per paying merchant loads all acquisition spend on free merchants onto the ones that convert within 24 months.
A4: Metric | B4: Base | C4: Bear | D4: Base + reco gates | E4: Lean plan | F4: Bull
A5: Unique customers per active merchant | B5: =Assumptions!$C$13/Assumptions!$C$15 -> 53.571429 | C5: =Assumptions!$D$13/Assumptions!$D$15 -> 35.714286 | D5: =Assumptions!$E$13/Assumptions!$E$15 -> 53.571429 | E5: =Assumptions!$F$13/Assumptions!$F$15 -> 53.571429 | F5: =Assumptions!$G$13/Assumptions!$G$15 -> 71.428571
A6: Free merchant: infra + support | B6: =Assumptions!$C$60+Assumptions!$C$63/60*Assumptions!$C$62 -> 3.0833333 | C6: =Assumptions!$D$60+Assumptions!$D$63/60*Assumptions!$D$62 -> 3.0833333 | D6: =Assumptions!$E$60+Assumptions!$E$63/60*Assumptions!$E$62 -> 3.0833333 | E6: =Assumptions!$F$60+Assumptions!$F$63/60*Assumptions!$F$62 -> 3.0833333 | F6: =Assumptions!$G$60+Assumptions!$G$63/60*Assumptions!$G$62 -> 3.0833333
A7: Free merchant: its customers (infra, SMS, perks) | B7: =B5*(Assumptions!$C$61+Assumptions!$C$59*Assumptions!$C$55+Assumptions!$C$16*(Assumptions!$C$58*Assumptions!$C$55+Assumptions!$C$65*Assumptions!$C$66*Assumptions!$C$67)) -> 1.5385714 | C7: =C5*(Assumptions!$D$61+Assumptions!$D$59*Assumptions!$D$55+Assumptions!$D$16*(Assumptions!$D$58*Assumptions!$D$55+Assumptions!$D$65*Assumptions!$D$66*Assumptions!$D$67)) -> 1.0257143 | D7: =D5*(Assumptions!$E$61+Assumptions!$E$59*Assumptions!$E$55+Assumptions!$E$16*(Assumptions!$E$58*Assumptions!$E$55+Assumptions!$E$65*Assumptions!$E$66*Assumptions!$E$67)) -> 1.5385714 | E7: =E5*(Assumptions!$F$61+Assumptions!$F$59*Assumptions!$F$55+Assumptions!$F$16*(Assumptions!$F$58*Assumptions!$F$55+Assumptions!$F$65*Assumptions!$F$66*Assumptions!$F$67)) -> 1.5385714 | F7: =F5*(Assumptions!$G$61+Assumptions!$G$59*Assumptions!$G$55+Assumptions!$G$16*(Assumptions!$G$58*Assumptions!$G$55+Assumptions!$G$65*Assumptions!$G$66*Assumptions!$G$67)) -> 2.0514286
A8: Cost of a free active merchant / month | B8: =B6+B7 -> 4.6219048 | C8: =C6+C7 -> 4.1090476 | D8: =D6+D7 -> 4.6219048 | E8: =E6+E7 -> 4.6219048 | F8: =F6+F7 -> 5.1347619
A9: Free→paid within 24 months (mix-weighted) | B9: =Assumptions!$C$25*(1-(1-((1-(1-Assumptions!$C$30)^(1/12))*Assumptions!$C$40))^24)+Assumptions!$C$26*(1-(1-((1-(1-Assumptions!$C$31)^(1/12))*Assumptions!$C$40))^24)+Assumptions!$C$27*(1-(1-((1-(1-Assumptions!$C$32)^(1/12))*Assumptions!$C$40))^24)+Assumptions!$C$28*(1-(1-((1-(1-Assumptions!$C$33)^(1/12))*Assumptions!$C$40))^24)+Assumptions!$C$29*(1-(1-((1-(1-Assumptions!$C$34)^(1/12))*Assumptions!$C$40))^24) -> 0.3515 | C9: =Assumptions!$D$25*(1-(1-((1-(1-Assumptions!$D$30)^(1/12))*Assumptions!$D$40))^24)+Assumptions!$D$26*(1-(1-((1-(1-Assumptions!$D$31)^(1/12))*Assumptions!$D$40))^24)+Assumptions!$D$27*(1-(1-((1-(1-Assumptions!$D$32)^(1/12))*Assumptions!$D$40))^24)+Assumptions!$D$28*(1-(1-((1-(1-Assumptions!$D$33)^(1/12))*Assumptions!$D$40))^24)+Assumptions!$D$29*(1-(1-((1-(1-Assumptions!$D$34)^(1/12))*Assumptions!$D$40))^24) -> 0.23450483 | D9: =Assumptions!$E$25*(1-(1-((1-(1-Assumptions!$E$30)^(1/12))*Assumptions!$E$40))^24)+Assumptions!$E$26*(1-(1-((1-(1-Assumptions!$E$31)^(1/12))*Assumptions!$E$40))^24)+Assumptions!$E$27*(1-(1-((1-(1-Assumptions!$E$32)^(1/12))*Assumptions!$E$40))^24)+Assumptions!$E$28*(1-(1-((1-(1-Assumptions!$E$33)^(1/12))*Assumptions!$E$40))^24)+Assumptions!$E$29*(1-(1-((1-(1-Assumptions!$E$34)^(1/12))*Assumptions!$E$40))^24) -> 0.3515 | E9: =Assumptions!$F$25*(1-(1-((1-(1-Assumptions!$F$30)^(1/12))*Assumptions!$F$40))^24)+Assumptions!$F$26*(1-(1-((1-(1-Assumptions!$F$31)^(1/12))*Assumptions!$F$40))^24)+Assumptions!$F$27*(1-(1-((1-(1-Assumptions!$F$32)^(1/12))*Assumptions!$F$40))^24)+Assumptions!$F$28*(1-(1-((1-(1-Assumptions!$F$33)^(1/12))*Assumptions!$F$40))^24)+Assumptions!$F$29*(1-(1-((1-(1-Assumptions!$F$34)^(1/12))*Assumptions!$F$40))^24) -> 0.3515 | F9: =Assumptions!$G$25*(1-(1-((1-(1-Assumptions!$G$30)^(1/12))*Assumptions!$G$40))^24)+Assumptions!$G$26*(1-(1-((1-(1-Assumptions!$G$31)^(1/12))*Assumptions!$G$40))^24)+Assumptions!$G$27*(1-(1-((1-(1-Assumptions!$G$32)^(1/12))*Assumptions!$G$40))^24)+Assumptions!$G$28*(1-(1-((1-(1-Assumptions!$G$33)^(1/12))*Assumptions!$G$40))^24)+Assumptions!$G$29*(1-(1-((1-(1-Assumptions!$G$34)^(1/12))*Assumptions!$G$40))^24) -> 0.42406075
A10: Share of payers on Pro | B10: =(Assumptions!$C$25*(1-(1-((1-(1-Assumptions!$C$30)^(1/12))*Assumptions!$C$40))^24)*Assumptions!$C$35+Assumptions!$C$26*(1-(1-((1-(1-Assumptions!$C$31)^(1/12))*Assumptions!$C$40))^24)*Assumptions!$C$36+Assumptions!$C$27*(1-(1-((1-(1-Assumptions!$C$32)^(1/12))*Assumptions!$C$40))^24)*Assumptions!$C$37+Assumptions!$C$28*(1-(1-((1-(1-Assumptions!$C$33)^(1/12))*Assumptions!$C$40))^24)*Assumptions!$C$38+Assumptions!$C$29*(1-(1-((1-(1-Assumptions!$C$34)^(1/12))*Assumptions!$C$40))^24)*Assumptions!$C$39)/B9 -> 0.36389758 | C10: =(Assumptions!$D$25*(1-(1-((1-(1-Assumptions!$D$30)^(1/12))*Assumptions!$D$40))^24)*Assumptions!$D$35+Assumptions!$D$26*(1-(1-((1-(1-Assumptions!$D$31)^(1/12))*Assumptions!$D$40))^24)*Assumptions!$D$36+Assumptions!$D$27*(1-(1-((1-(1-Assumptions!$D$32)^(1/12))*Assumptions!$D$40))^24)*Assumptions!$D$37+Assumptions!$D$28*(1-(1-((1-(1-Assumptions!$D$33)^(1/12))*Assumptions!$D$40))^24)*Assumptions!$D$38+Assumptions!$D$29*(1-(1-((1-(1-Assumptions!$D$34)^(1/12))*Assumptions!$D$40))^24)*Assumptions!$D$39)/C9 -> 0.38232818 | D10: =(Assumptions!$E$25*(1-(1-((1-(1-Assumptions!$E$30)^(1/12))*Assumptions!$E$40))^24)*Assumptions!$E$35+Assumptions!$E$26*(1-(1-((1-(1-Assumptions!$E$31)^(1/12))*Assumptions!$E$40))^24)*Assumptions!$E$36+Assumptions!$E$27*(1-(1-((1-(1-Assumptions!$E$32)^(1/12))*Assumptions!$E$40))^24)*Assumptions!$E$37+Assumptions!$E$28*(1-(1-((1-(1-Assumptions!$E$33)^(1/12))*Assumptions!$E$40))^24)*Assumptions!$E$38+Assumptions!$E$29*(1-(1-((1-(1-Assumptions!$E$34)^(1/12))*Assumptions!$E$40))^24)*Assumptions!$E$39)/D9 -> 0.36389758 | E10: =(Assumptions!$F$25*(1-(1-((1-(1-Assumptions!$F$30)^(1/12))*Assumptions!$F$40))^24)*Assumptions!$F$35+Assumptions!$F$26*(1-(1-((1-(1-Assumptions!$F$31)^(1/12))*Assumptions!$F$40))^24)*Assumptions!$F$36+Assumptions!$F$27*(1-(1-((1-(1-Assumptions!$F$32)^(1/12))*Assumptions!$F$40))^24)*Assumptions!$F$37+Assumptions!$F$28*(1-(1-((1-(1-Assumptions!$F$33)^(1/12))*Assumptions!$F$40))^24)*Assumptions!$F$38+Assumptions!$F$29*(1-(1-((1-(1-Assumptions!$F$34)^(1/12))*Assumptions!$F$40))^24)*Assumptions!$F$39)/E9 -> 0.36389758 | F10: =(Assumptions!$G$25*(1-(1-((1-(1-Assumptions!$G$30)^(1/12))*Assumptions!$G$40))^24)*Assumptions!$G$35+Assumptions!$G$26*(1-(1-((1-(1-Assumptions!$G$31)^(1/12))*Assumptions!$G$40))^24)*Assumptions!$G$36+Assumptions!$G$27*(1-(1-((1-(1-Assumptions!$G$32)^(1/12))*Assumptions!$G$40))^24)*Assumptions!$G$37+Assumptions!$G$28*(1-(1-((1-(1-Assumptions!$G$33)^(1/12))*Assumptions!$G$40))^24)*Assumptions!$G$38+Assumptions!$G$29*(1-(1-((1-(1-Assumptions!$G$34)^(1/12))*Assumptions!$G$40))^24)*Assumptions!$G$39)/F9 -> 0.35143675
A11: Subscription ARPU (blended Plus/Pro) | B11: =Assumptions!$C$42*(1-B10)+Assumptions!$C$43*B10 -> 53.555903 | C11: =Assumptions!$D$42*(1-C10)+Assumptions!$D$43*C10 -> 54.293127 | D11: =Assumptions!$E$42*(1-D10)+Assumptions!$E$43*D10 -> 53.555903 | E11: =Assumptions!$F$42*(1-E10)+Assumptions!$F$43*E10 -> 53.555903 | F11: =Assumptions!$G$42*(1-F10)+Assumptions!$G$43*F10 -> 53.05747
A12: Payments margin net of Stripe Connect | B12: =Assumptions!$C$45*((Assumptions!$C$46*(1-B10)+Assumptions!$C$47*B10)*(Assumptions!$C$44-Assumptions!$C$51)-Assumptions!$C$52) -> 10.120925 | C12: =Assumptions!$D$45*((Assumptions!$D$46*(1-C10)+Assumptions!$D$47*C10)*(Assumptions!$D$44-Assumptions!$D$51)-Assumptions!$D$52) -> 6.8762973 | D12: =Assumptions!$E$45*((Assumptions!$E$46*(1-D10)+Assumptions!$E$47*D10)*(Assumptions!$E$44-Assumptions!$E$51)-Assumptions!$E$52) -> 10.120925 | E12: =Assumptions!$F$45*((Assumptions!$F$46*(1-E10)+Assumptions!$F$47*E10)*(Assumptions!$F$44-Assumptions!$F$51)-Assumptions!$F$52) -> 10.120925 | F12: =Assumptions!$G$45*((Assumptions!$G$46*(1-F10)+Assumptions!$G$47*F10)*(Assumptions!$G$44-Assumptions!$G$51)-Assumptions!$G$52) -> 12.487607
A13: SMS cost (included allowance used) | B13: =(Assumptions!$C$56*(1-B10)+Assumptions!$C$57*B10)*Assumptions!$C$55 -> 11.403448 | C13: =(Assumptions!$D$56*(1-C10)+Assumptions!$D$57*C10)*Assumptions!$D$55 -> 11.646732 | D13: =(Assumptions!$E$56*(1-D10)+Assumptions!$E$57*D10)*Assumptions!$E$55 -> 11.403448 | E13: =(Assumptions!$F$56*(1-E10)+Assumptions!$F$57*E10)*Assumptions!$F$55 -> 11.403448 | F13: =(Assumptions!$G$56*(1-F10)+Assumptions!$G$57*F10)*Assumptions!$G$55 -> 11.238965
A14: Subscription billing fees | B14: =B11*Assumptions!$C$53+Assumptions!$C$54 -> 2.1209007 | C14: =C11*Assumptions!$D$53+Assumptions!$D$54 -> 2.1459663 | D14: =D11*Assumptions!$E$53+Assumptions!$E$54 -> 2.1209007 | E14: =E11*Assumptions!$F$53+Assumptions!$F$54 -> 2.1209007 | F14: =F11*Assumptions!$G$53+Assumptions!$G$54 -> 2.103954
A15: Extra support for paid features | B15: =Assumptions!$C$64/60*Assumptions!$C$62 -> 6.25 | C15: =Assumptions!$D$64/60*Assumptions!$D$62 -> 6.25 | D15: =Assumptions!$E$64/60*Assumptions!$E$62 -> 6.25 | E15: =Assumptions!$F$64/60*Assumptions!$F$62 -> 6.25 | F15: =Assumptions!$G$64/60*Assumptions!$G$62 -> 6.25
A16: Contribution per paying merchant / month | B16: =B11+B12-B13-B14-B15 -> 43.902479 | C16: =C11+C12-C13-C14-C15 -> 41.126726 | D16: =D11+D12-D13-D14-D15 -> 43.902479 | E16: =E11+E12-E13-E14-E15 -> 43.902479 | F16: =F11+F12-F13-F14-F15 -> 45.952158
A17: CAC per signed merchant | B17: =Assumptions!$C$91*(Assumptions!$C$86*Assumptions!$C$83*(1+Assumptions!$C$85)+Assumptions!$C$11*Assumptions!$C$87*(1+Assumptions!$C$85)+Assumptions!$C$88+Assumptions!$C$89/Assumptions!$C$10) -> 106.09625 | C17: =Assumptions!$D$91*(Assumptions!$D$86*Assumptions!$D$83*(1+Assumptions!$D$85)+Assumptions!$D$11*Assumptions!$D$87*(1+Assumptions!$D$85)+Assumptions!$D$88+Assumptions!$D$89/Assumptions!$D$10) -> 131.36725 | D17: =Assumptions!$E$91*(Assumptions!$E$86*Assumptions!$E$83*(1+Assumptions!$E$85)+Assumptions!$E$11*Assumptions!$E$87*(1+Assumptions!$E$85)+Assumptions!$E$88+Assumptions!$E$89/Assumptions!$E$10) -> 106.09625 | E17: =Assumptions!$F$91*(Assumptions!$F$86*Assumptions!$F$83*(1+Assumptions!$F$85)+Assumptions!$F$11*Assumptions!$F$87*(1+Assumptions!$F$85)+Assumptions!$F$88+Assumptions!$F$89/Assumptions!$F$10) -> 106.09625 | F17: =Assumptions!$G$91*(Assumptions!$G$86*Assumptions!$G$83*(1+Assumptions!$G$85)+Assumptions!$G$11*Assumptions!$G$87*(1+Assumptions!$G$85)+Assumptions!$G$88+Assumptions!$G$89/Assumptions!$G$10) -> 95.078842
A18: CAC per activated merchant | B18: =B17/Assumptions!$C$11 -> 176.82708 | C18: =C17/Assumptions!$D$11 -> 262.7345 | D18: =D17/Assumptions!$E$11 -> 176.82708 | E18: =E17/Assumptions!$F$11 -> 176.82708 | F18: =F17/Assumptions!$G$11 -> 135.82692
A19: CAC per paying merchant | B19: =B17/(Assumptions!$C$11*B9)+Assumptions!$C$90*Assumptions!$C$91 -> 553.06425 | C19: =C17/(Assumptions!$D$11*C9)+Assumptions!$D$90*Assumptions!$D$91 -> 1170.3799 | D19: =D17/(Assumptions!$E$11*D9)+Assumptions!$E$90*Assumptions!$E$91 -> 553.06425 | E19: =E17/(Assumptions!$F$11*E9)+Assumptions!$F$90*Assumptions!$F$91 -> 553.06425 | F19: =F17/(Assumptions!$G$11*F9)+Assumptions!$G$90*Assumptions!$G$91 -> 370.30061
A20: Average paid life (months) | B20: =1/Assumptions!$C$41 -> 33.333333 | C20: =1/Assumptions!$D$41 -> 22.222222 | D20: =1/Assumptions!$E$41 -> 33.333333 | E20: =1/Assumptions!$F$41 -> 33.333333 | F20: =1/Assumptions!$G$41 -> 44.444444
A21: LTV per paying merchant (undiscounted contribution) | B21: =B16*B20 -> 1463.416 | C21: =C16*C20 -> 913.92725 | D21: =D16*D20 -> 1463.416 | E21: =E16*E20 -> 1463.416 | F21: =F16*F20 -> 2042.3181
A22: LTV / CAC | B22: =B21/B19 -> 2.6460144 | C22: =C21/C19 -> 0.78088083 | D22: =D21/D19 -> 2.6460144 | E22: =E21/E19 -> 2.6460144 | F22: =F21/F19 -> 5.5152978
A23: CAC payback (months) | B23: =B19/B16 -> 12.597563 | C23: =C19/C16 -> 28.457892 | D23: =D19/D16 -> 12.597563 | E23: =E19/E16 -> 12.597563 | F23: =F19/F16 -> 8.0583943
A24: Free-tier carry cost per paying merchant (24 months) | B24: =(1-B9)/B9*B8*24 -> 204.65242 | C24: =(1-C9)/C9*C8*24 -> 321.91639 | D24: =(1-D9)/D9*D8*24 -> 204.65242 | E24: =(1-E9)/E9*E8*24 -> 204.65242 | F24: =(1-F9)/F9*F8*24 -> 167.37098
A25: LTV / (CAC + free carry), fully loaded | B25: =B21/(B19+B24) -> 1.9313498 | C25: =C21/(C19+C24) -> 0.61243015 | D25: =D21/(D19+D24) -> 1.9313498 | E25: =E21/(E19+E24) -> 1.9313498 | F25: =F21/(F19+F24) -> 3.7984491
A26: Merchant all-in cost of an in-app payment (Stripe + 0.75%) | B26: =Assumptions!$C$49+Assumptions!$C$50/Assumptions!$C$48+Assumptions!$C$44 -> 0.045071429 | C26: =Assumptions!$D$49+Assumptions!$D$50/Assumptions!$D$48+Assumptions!$D$44 -> 0.045071429 | D26: =Assumptions!$E$49+Assumptions!$E$50/Assumptions!$E$48+Assumptions!$E$44 -> 0.045071429 | E26: =Assumptions!$F$49+Assumptions!$F$50/Assumptions!$F$48+Assumptions!$F$44 -> 0.045071429 | F26: =Assumptions!$G$49+Assumptions!$G$50/Assumptions!$G$48+Assumptions!$G$44 -> 0.045071429

Sheet Monthly
A1: Local Loyalty — monthly model: Base scenario (CAD)
A2: Every cell is a formula driven by the Assumptions sheet (column C). Months 1-36 = projection; grey months 37-60 = extension used only to locate break-even.
B4: Model month | C4: 0 | D4: 1 | E4: 2 | F4: 3 | G4: 4 | H4: 5 | I4: 6 | J4: 7 | K4: 8 | L4: 9 | M4: 10 | N4: 11 | O4: 12 | P4: 13 | Q4: 14 | R4: 15 | S4: 16 | T4: 17 | U4: 18 | V4: 19 | W4: 20 | X4: 21 | Y4: 22 | Z4: 23 | AA4: 24 | AB4: 25 | AC4: 26 | AD4: 27 | AE4: 28 | AF4: 29 | AG4: 30 | AH4: 31 | AI4: 32 | AJ4: 33 | AK4: 34 | AL4: 35 | AM4: 36 | AN4: 37 | AO4: 38 | AP4: 39 | AQ4: 40 | AR4: 41 | AS4: 42 | AT4: 43 | AU4: 44 | AV4: 45 | AW4: 46 | AX4: 47 | AY4: 48 | AZ4: 49 | BA4: 50 | BB4: 51 | BC4: 52 | BD4: 53 | BE4: 54 | BF4: 55 | BG4: 56 | BH4: 57 | BI4: 58 | BJ4: 59 | BK4: 60
B5: Calendar month | C5: start | D5: 2026-11 | E5: 2026-12 | F5: 2027-01 | G5: 2027-02 | H5: 2027-03 | I5: 2027-04 | J5: 2027-05 | K5: 2027-06 | L5: 2027-07 | M5: 2027-08 | N5: 2027-09 | O5: 2027-10 | P5: 2027-11 | Q5: 2027-12 | R5: 2028-01 | S5: 2028-02 | T5: 2028-03 | U5: 2028-04 | V5: 2028-05 | W5: 2028-06 | X5: 2028-07 | Y5: 2028-08 | Z5: 2028-09 | AA5: 2028-10 | AB5: 2028-11 | AC5: 2028-12 | AD5: 2029-01 | AE5: 2029-02 | AF5: 2029-03 | AG5: 2029-04 | AH5: 2029-05 | AI5: 2029-06 | AJ5: 2029-07 | AK5: 2029-08 | AL5: 2029-09 | AM5: 2029-10 | AN5: 2029-11 | AO5: 2029-12 | AP5: 2030-01 | AQ5: 2030-02 | AR5: 2030-03 | AS5: 2030-04 | AT5: 2030-05 | AU5: 2030-06 | AV5: 2030-07 | AW5: 2030-08 | AX5: 2030-09 | AY5: 2030-10 | AZ5: 2030-11 | BA5: 2030-12 | BB5: 2031-01 | BC5: 2031-02 | BD5: 2031-03 | BE5: 2031-04 | BF5: 2031-05 | BG5: 2031-06 | BH5: 2031-07 | BI5: 2031-08 | BJ5: 2031-09 | BK5: 2031-10
B6: Strips & merchants
A7: month | B7: Model month | C7: 0 | D7: 1 | E7: 2 | F7: 3 | G7: 4 | H7: 5 | I7: 6 | J7: 7 | K7: 8 | L7: 9 | M7: 10 | N7: 11 | O7: 12 | P7: 13 | Q7: 14 | R7: 15 | S7: 16 | T7: 17 | U7: 18 | V7: 19 | W7: 20 | X7: 21 | Y7: 22 | Z7: 23 | AA7: 24 | AB7: 25 | AC7: 26 | AD7: 27 | AE7: 28 | AF7: 29 | AG7: 30 | AH7: 31 | AI7: 32 | AJ7: 33 | AK7: 34 | AL7: 35 | AM7: 36 | AN7: 37 | AO7: 38 | AP7: 39 | AQ7: 40 | AR7: 41 | AS7: 42 | AT7: 43 | AU7: 44 | AV7: 45 | AW7: 46 | AX7: 47 | AY7: 48 | AZ7: 49 | BA7: 50 | BB7: 51 | BC7: 52 | BD7: 53 | BE7: 54 | BF7: 55 | BG7: 56 | BH7: 57 | BI7: 58 | BJ7: 59 | BK7: 60
A8: strips_launched | B8: Strips launched | C8: 0 | D8: =Assumptions!C$139 -> 0 | E8: =Assumptions!D$139 -> 0 | F8: =Assumptions!E$139 -> 0 | G8: =Assumptions!F$139 -> 0 | H8: =Assumptions!G$139 -> 1 | I8: =Assumptions!H$139 -> 0 | J8: =Assumptions!I$139 -> 0 | K8: =Assumptions!J$139 -> 1 | ... BK8: =Assumptions!BJ$139 -> 1
A9: strips_cum | B9: Strips live (cumulative) | C9: 0 | D9: =C9+D8 -> 0 | E9: =D9+E8 -> 0 | F9: =E9+F8 -> 0 | G9: =F9+G8 -> 0 | H9: =G9+H8 -> 1 | I9: =H9+I8 -> 1 | J9: =I9+J8 -> 1 | K9: =J9+K8 -> 2 | ... BK9: =BJ9+BK8 -> 61
A10: strips_mature | B10: Mature strips (launched >= maturity months ago) | C10: 0 | D10: =IF(D7>Assumptions!$C$79,INDEX($D$9:$BK$9,D7-Assumptions!$C$79),0) -> 0 | E10: =IF(E7>Assumptions!$C$79,INDEX($D$9:$BK$9,E7-Assumptions!$C$79),0) -> 0 | F10: =IF(F7>Assumptions!$C$79,INDEX($D$9:$BK$9,F7-Assumptions!$C$79),0) -> 0 | G10: =IF(G7>Assumptions!$C$79,INDEX($D$9:$BK$9,G7-Assumptions!$C$79),0) -> 0 | H10: =IF(H7>Assumptions!$C$79,INDEX($D$9:$BK$9,H7-Assumptions!$C$79),0) -> 0 | I10: =IF(I7>Assumptions!$C$79,INDEX($D$9:$BK$9,I7-Assumptions!$C$79),0) -> 0 | J10: =IF(J7>Assumptions!$C$79,INDEX($D$9:$BK$9,J7-Assumptions!$C$79),0) -> 0 | K10: =IF(K7>Assumptions!$C$79,INDEX($D$9:$BK$9,K7-Assumptions!$C$79),0) -> 0 | ... BK10: =IF(BK7>Assumptions!$C$79,INDEX($D$9:$BK$9,BK7-Assumptions!$C$79),0) -> 53
A11: signups | B11: New merchant sign-ups | C11: 0 | D11: =Assumptions!$C$10*(D8*Assumptions!$C$111) -> 0 | E11: =Assumptions!$C$10*(E8*Assumptions!$C$111+D8*Assumptions!$C$112) -> 0 | F11: =Assumptions!$C$10*(F8*Assumptions!$C$111+E8*Assumptions!$C$112+D8*Assumptions!$C$113) -> 0 | G11: =Assumptions!$C$10*(G8*Assumptions!$C$111+F8*Assumptions!$C$112+E8*Assumptions!$C$113+D8*Assumptions!$C$114) -> 0 | H11: =Assumptions!$C$10*(H8*Assumptions!$C$111+G8*Assumptions!$C$112+F8*Assumptions!$C$113+E8*Assumptions!$C$114+D8*Assumptions!$C$115) -> 8 | I11: =Assumptions!$C$10*(I8*Assumptions!$C$111+H8*Assumptions!$C$112+G8*Assumptions!$C$113+F8*Assumptions!$C$114+E8*Assumptions!$C$115+D8*Assumptions!$C$116) -> 7.04 | J11: =Assumptions!$C$10*(J8*Assumptions!$C$111+I8*Assumptions!$C$112+H8*Assumptions!$C$113+G8*Assumptions!$C$114+F8*Assumptions!$C$115+E8*Assumptions!$C$116+D8*Assumptions!$C$117) -> 4.8 | K11: =Assumptions!$C$10*(K8*Assumptions!$C$111+J8*Assumptions!$C$112+I8*Assumptions!$C$113+H8*Assumptions!$C$114+G8*Assumptions!$C$115+F8*Assumptions!$C$116+E8*Assumptions!$C$117+D8*Assumptions!$C$118) -> 11.2 | L11: =Assumptions!$C$10*(L8*Assumptions!$C$111+K8*Assumptions!$C$112+J8*Assumptions!$C$113+I8*Assumptions!$C$114+H8*Assumptions!$C$115+G8*Assumptions!$C$116+F8*Assumptions!$C$117+E8*Assumptions!$C$118+D8*Assumptions!$C$119) -> 8.96 | M11: =Assumptions!$C$10*(M8*Assumptions!$C$111+L8*Assumptions!$C$112+K8*Assumptions!$C$113+J8*Assumptions!$C$114+I8*Assumptions!$C$115+H8*Assumptions!$C$116+G8*Assumptions!$C$117+F8*Assumptions!$C$118+E8*Assumptions!$C$119+D8*Assumptions!$C$120) -> 6.4 | N11: =Assumptions!$C$10*(N8*Assumptions!$C$111+M8*Assumptions!$C$112+L8*Assumptions!$C$113+K8*Assumptions!$C$114+J8*Assumptions!$C$115+I8*Assumptions!$C$116+H8*Assumptions!$C$117+G8*Assumptions!$C$118+F8*Assumptions!$C$119+E8*Assumptions!$C$120+D8*Assumptions!$C$121) -> 11.52 | O11: =Assumptions!$C$10*(O8*Assumptions!$C$111+N8*Assumptions!$C$112+M8*Assumptions!$C$113+L8*Assumptions!$C$114+K8*Assumptions!$C$115+J8*Assumptions!$C$116+I8*Assumptions!$C$117+H8*Assumptions!$C$118+G8*Assumptions!$C$119+F8*Assumptions!$C$120+E8*Assumptions!$C$121+D8*Assumptions!$C$122) -> 17.28 | P11: =Assumptions!$C$10*(P8*Assumptions!$C$111+O8*Assumptions!$C$112+N8*Assumptions!$C$113+M8*Assumptions!$C$114+L8*Assumptions!$C$115+K8*Assumptions!$C$116+J8*Assumptions!$C$117+I8*Assumptions!$C$118+H8*Assumptions!$C$119+G8*Assumptions!$C$120+F8*Assumptions!$C$121+E8*Assumptions!$C$122+D8*Assumptions!$C$123) -> 13.76 | Q11: =Assumptions!$C$10*(Q8*Assumptions!$C$111+P8*Assumptions!$C$112+O8*Assumptions!$C$113+N8*Assumptions!$C$114+M8*Assumptions!$C$115+L8*Assumptions!$C$116+K8*Assumptions!$C$117+J8*Assumptions!$C$118+I8*Assumptions!$C$119+H8*Assumptions!$C$120+G8*Assumptions!$C$121+F8*Assumptions!$C$122+E8*Assumptions!$C$123+D8*Assumptions!$C$124) -> 16.64 | R11: =Assumptions!$C$10*(R8*Assumptions!$C$111+Q8*Assumptions!$C$112+P8*Assumptions!$C$113+O8*Assumptions!$C$114+N8*Assumptions!$C$115+M8*Assumptions!$C$116+L8*Assumptions!$C$117+K8*Assumptions!$C$118+J8*Assumptions!$C$119+I8*Assumptions!$C$120+H8*Assumptions!$C$121+G8*Assumptions!$C$122+F8*Assumptions!$C$123+E8*Assumptions!$C$124+D8*Assumptions!$C$125) -> 20.8 | S11: =Assumptions!$C$10*(S8*Assumptions!$C$111+R8*Assumptions!$C$112+Q8*Assumptions!$C$113+P8*Assumptions!$C$114+O8*Assumptions!$C$115+N8*Assumptions!$C$116+M8*Assumptions!$C$117+L8*Assumptions!$C$118+K8*Assumptions!$C$119+J8*Assumptions!$C$120+I8*Assumptions!$C$121+H8*Assumptions!$C$122+G8*Assumptions!$C$123+F8*Assumptions!$C$124+E8*Assumptions!$C$125+D8*Assumptions!$C$126) -> 16 | T11: =Assumptions!$C$10*(T8*Assumptions!$C$111+S8*Assumptions!$C$112+R8*Assumptions!$C$113+Q8*Assumptions!$C$114+P8*Assumptions!$C$115+O8*Assumptions!$C$116+N8*Assumptions!$C$117+M8*Assumptions!$C$118+L8*Assumptions!$C$119+K8*Assumptions!$C$120+J8*Assumptions!$C$121+I8*Assumptions!$C$122+H8*Assumptions!$C$123+G8*Assumptions!$C$124+F8*Assumptions!$C$125+E8*Assumptions!$C$126+D8*Assumptions!$C$127) -> 18.56 | U11: =Assumptions!$C$10*(U8*Assumptions!$C$111+T8*Assumptions!$C$112+S8*Assumptions!$C$113+R8*Assumptions!$C$114+Q8*Assumptions!$C$115+P8*Assumptions!$C$116+O8*Assumptions!$C$117+N8*Assumptions!$C$118+M8*Assumptions!$C$119+L8*Assumptions!$C$120+K8*Assumptions!$C$121+J8*Assumptions!$C$122+I8*Assumptions!$C$123+H8*Assumptions!$C$124+G8*Assumptions!$C$125+F8*Assumptions!$C$126+E8*Assumptions!$C$127+D8*Assumptions!$C$128) -> 21.44 | V11: =Assumptions!$C$10*(V8*Assumptions!$C$111+U8*Assumptions!$C$112+T8*Assumptions!$C$113+S8*Assumptions!$C$114+R8*Assumptions!$C$115+Q8*Assumptions!$C$116+P8*Assumptions!$C$117+O8*Assumptions!$C$118+N8*Assumptions!$C$119+M8*Assumptions!$C$120+L8*Assumptions!$C$121+K8*Assumptions!$C$122+J8*Assumptions!$C$123+I8*Assumptions!$C$124+H8*Assumptions!$C$125+G8*Assumptions!$C$126+F8*Assumptions!$C$127+E8*Assumptions!$C$128+D8*Assumptions!$C$129) -> 24.64 | W11: =Assumptions!$C$10*(W8*Assumptions!$C$111+V8*Assumptions!$C$112+U8*Assumptions!$C$113+T8*Assumptions!$C$114+S8*Assumptions!$C$115+R8*Assumptions!$C$116+Q8*Assumptions!$C$117+P8*Assumptions!$C$118+O8*Assumptions!$C$119+N8*Assumptions!$C$120+M8*Assumptions!$C$121+L8*Assumptions!$C$122+K8*Assumptions!$C$123+J8*Assumptions!$C$124+I8*Assumptions!$C$125+H8*Assumptions!$C$126+G8*Assumptions!$C$127+F8*Assumptions!$C$128+E8*Assumptions!$C$129+D8*Assumptions!$C$130) -> 26.24 | X11: =Assumptions!$C$10*(X8*Assumptions!$C$111+W8*Assumptions!$C$112+V8*Assumptions!$C$113+U8*Assumptions!$C$114+T8*Assumptions!$C$115+S8*Assumptions!$C$116+R8*Assumptions!$C$117+Q8*Assumptions!$C$118+P8*Assumptions!$C$119+O8*Assumptions!$C$120+N8*Assumptions!$C$121+M8*Assumptions!$C$122+L8*Assumptions!$C$123+K8*Assumptions!$C$124+J8*Assumptions!$C$125+I8*Assumptions!$C$126+H8*Assumptions!$C$127+G8*Assumptions!$C$128+F8*Assumptions!$C$129+E8*Assumptions!$C$130+D8*Assumptions!$C$131) -> 26.88 | Y11: =Assumptions!$C$10*(Y8*Assumptions!$C$111+X8*Assumptions!$C$112+W8*Assumptions!$C$113+V8*Assumptions!$C$114+U8*Assumptions!$C$115+T8*Assumptions!$C$116+S8*Assumptions!$C$117+R8*Assumptions!$C$118+Q8*Assumptions!$C$119+P8*Assumptions!$C$120+O8*Assumptions!$C$121+N8*Assumptions!$C$122+M8*Assumptions!$C$123+L8*Assumptions!$C$124+K8*Assumptions!$C$125+J8*Assumptions!$C$126+I8*Assumptions!$C$127+H8*Assumptions!$C$128+G8*Assumptions!$C$129+F8*Assumptions!$C$130+E8*Assumptions!$C$131+D8*Assumptions!$C$132) -> 28.48 | Z11: =Assumptions!$C$10*(Z8*Assumptions!$C$111+Y8*Assumptions!$C$112+X8*Assumptions!$C$113+W8*Assumptions!$C$114+V8*Assumptions!$C$115+U8*Assumptions!$C$116+T8*Assumptions!$C$117+S8*Assumptions!$C$118+R8*Assumptions!$C$119+Q8*Assumptions!$C$120+P8*Assumptions!$C$121+O8*Assumptions!$C$122+N8*Assumptions!$C$123+M8*Assumptions!$C$124+L8*Assumptions!$C$125+K8*Assumptions!$C$126+J8*Assumptions!$C$127+I8*Assumptions!$C$128+H8*Assumptions!$C$129+G8*Assumptions!$C$130+F8*Assumptions!$C$131+E8*Assumptions!$C$132+D8*Assumptions!$C$133) -> 28.8 | AA11: =Assumptions!$C$10*(AA8*Assumptions!$C$111+Z8*Assumptions!$C$112+Y8*Assumptions!$C$113+X8*Assumptions!$C$114+W8*Assumptions!$C$115+V8*Assumptions!$C$116+U8*Assumptions!$C$117+T8*Assumptions!$C$118+S8*Assumptions!$C$119+R8*Assumptions!$C$120+Q8*Assumptions!$C$121+P8*Assumptions!$C$122+O8*Assumptions!$C$123+N8*Assumptions!$C$124+M8*Assumptions!$C$125+L8*Assumptions!$C$126+K8*Assumptions!$C$127+J8*Assumptions!$C$128+I8*Assumptions!$C$129+H8*Assumptions!$C$130+G8*Assumptions!$C$131+F8*Assumptions!$C$132+E8*Assumptions!$C$133) -> 29.12 | AB11: =Assumptions!$C$10*(AB8*Assumptions!$C$111+AA8*Assumptions!$C$112+Z8*Assumptions!$C$113+Y8*Assumptions!$C$114+X8*Assumptions!$C$115+W8*Assumptions!$C$116+V8*Assumptions!$C$117+U8*Assumptions!$C$118+T8*Assumptions!$C$119+S8*Assumptions!$C$120+R8*Assumptions!$C$121+Q8*Assumptions!$C$122+P8*Assumptions!$C$123+O8*Assumptions!$C$124+N8*Assumptions!$C$125+M8*Assumptions!$C$126+L8*Assumptions!$C$127+K8*Assumptions!$C$128+J8*Assumptions!$C$129+I8*Assumptions!$C$130+H8*Assumptions!$C$131+G8*Assumptions!$C$132+F8*Assumptions!$C$133) -> 29.44 | AC11: =Assumptions!$C$10*(AC8*Assumptions!$C$111+AB8*Assumptions!$C$112+AA8*Assumptions!$C$113+Z8*Assumptions!$C$114+Y8*Assumptions!$C$115+X8*Assumptions!$C$116+W8*Assumptions!$C$117+V8*Assumptions!$C$118+U8*Assumptions!$C$119+T8*Assumptions!$C$120+S8*Assumptions!$C$121+R8*Assumptions!$C$122+Q8*Assumptions!$C$123+P8*Assumptions!$C$124+O8*Assumptions!$C$125+N8*Assumptions!$C$126+M8*Assumptions!$C$127+L8*Assumptions!$C$128+K8*Assumptions!$C$129+J8*Assumptions!$C$130+I8*Assumptions!$C$131+H8*Assumptions!$C$132+G8*Assumptions!$C$133) -> 29.76 | AD11: =Assumptions!$C$10*(AD8*Assumptions!$C$111+AC8*Assumptions!$C$112+AB8*Assumptions!$C$113+AA8*Assumptions!$C$114+Z8*Assumptions!$C$115+Y8*Assumptions!$C$116+X8*Assumptions!$C$117+W8*Assumptions!$C$118+V8*Assumptions!$C$119+U8*Assumptions!$C$120+T8*Assumptions!$C$121+S8*Assumptions!$C$122+R8*Assumptions!$C$123+Q8*Assumptions!$C$124+P8*Assumptions!$C$125+O8*Assumptions!$C$126+N8*Assumptions!$C$127+M8*Assumptions!$C$128+L8*Assumptions!$C$129+K8*Assumptions!$C$130+J8*Assumptions!$C$131+I8*Assumptions!$C$132+H8*Assumptions!$C$133) -> 30.08 | AE11: =Assumptions!$C$10*(AE8*Assumptions!$C$111+AD8*Assumptions!$C$112+AC8*Assumptions!$C$113+AB8*Assumptions!$C$114+AA8*Assumptions!$C$115+Z8*Assumptions!$C$116+Y8*Assumptions!$C$117+X8*Assumptions!$C$118+W8*Assumptions!$C$119+V8*Assumptions!$C$120+U8*Assumptions!$C$121+T8*Assumptions!$C$122+S8*Assumptions!$C$123+R8*Assumptions!$C$124+Q8*Assumptions!$C$125+P8*Assumptions!$C$126+O8*Assumptions!$C$127+N8*Assumptions!$C$128+M8*Assumptions!$C$129+L8*Assumptions!$C$130+K8*Assumptions!$C$131+J8*Assumptions!$C$132+I8*Assumptions!$C$133) -> 30.08 | AF11: =Assumptions!$C$10*(AF8*Assumptions!$C$111+AE8*Assumptions!$C$112+AD8*Assumptions!$C$113+AC8*Assumptions!$C$114+AB8*Assumptions!$C$115+AA8*Assumptions!$C$116+Z8*Assumptions!$C$117+Y8*Assumptions!$C$118+X8*Assumptions!$C$119+W8*Assumptions!$C$120+V8*Assumptions!$C$121+U8*Assumptions!$C$122+T8*Assumptions!$C$123+S8*Assumptions!$C$124+R8*Assumptions!$C$125+Q8*Assumptions!$C$126+P8*Assumptions!$C$127+O8*Assumptions!$C$128+N8*Assumptions!$C$129+M8*Assumptions!$C$130+L8*Assumptions!$C$131+K8*Assumptions!$C$132+J8*Assumptions!$C$133) -> 38.4 | AG11: =Assumptions!$C$10*(AG8*Assumptions!$C$111+AF8*Assumptions!$C$112+AE8*Assumptions!$C$113+AD8*Assumptions!$C$114+AC8*Assumptions!$C$115+AB8*Assumptions!$C$116+AA8*Assumptions!$C$117+Z8*Assumptions!$C$118+Y8*Assumptions!$C$119+X8*Assumptions!$C$120+W8*Assumptions!$C$121+V8*Assumptions!$C$122+U8*Assumptions!$C$123+T8*Assumptions!$C$124+S8*Assumptions!$C$125+R8*Assumptions!$C$126+Q8*Assumptions!$C$127+P8*Assumptions!$C$128+O8*Assumptions!$C$129+N8*Assumptions!$C$130+M8*Assumptions!$C$131+L8*Assumptions!$C$132+K8*Assumptions!$C$133) -> 37.76 | ... BK11: =Assumptions!$C$10*(BK8*Assumptions!$C$111+BJ8*Assumptions!$C$112+BI8*Assumptions!$C$113+BH8*Assumptions!$C$114+BG8*Assumptions!$C$115+BF8*Assumptions!$C$116+BE8*Assumptions!$C$117+BD8*Assumptions!$C$118+BC8*Assumptions!$C$119+BB8*Assumptions!$C$120+BA8*Assumptions!$C$121+AZ8*Assumptions!$C$122+AY8*Assumptions!$C$123+AX8*Assumptions!$C$124+AW8*Assumptions!$C$125+AV8*Assumptions!$C$126+AU8*Assumptions!$C$127+AT8*Assumptions!$C$128+AS8*Assumptions!$C$129+AR8*Assumptions!$C$130+AQ8*Assumptions!$C$131+AP8*Assumptions!$C$132+AO8*Assumptions!$C$133) -> 42.88
A12: network_merchants | B12: Network merchants (signed, net of churn) | C12: 0 | D12: =C12*(1-Assumptions!$C$12)+D11 -> 0 | E12: =D12*(1-Assumptions!$C$12)+E11 -> 0 | F12: =E12*(1-Assumptions!$C$12)+F11 -> 0 | G12: =F12*(1-Assumptions!$C$12)+G11 -> 0 | H12: =G12*(1-Assumptions!$C$12)+H11 -> 8 | I12: =H12*(1-Assumptions!$C$12)+I11 -> 14.92 | J12: =I12*(1-Assumptions!$C$12)+J11 -> 19.4962 | K12: =J12*(1-Assumptions!$C$12)+K11 -> 30.403757 | ... BK12: =BJ12*(1-Assumptions!$C$12)+BK11 -> 1320.3863
A13: active_merchants | B13: Active merchants (>= 25 active members) | C13: 0 | D13: =D12*Assumptions!$C$11 -> 0 | E13: =E12*Assumptions!$C$11 -> 0 | F13: =F12*Assumptions!$C$11 -> 0 | G13: =G12*Assumptions!$C$11 -> 0 | H13: =H12*Assumptions!$C$11 -> 4.8 | I13: =I12*Assumptions!$C$11 -> 8.952 | J13: =J12*Assumptions!$C$11 -> 11.69772 | K13: =K12*Assumptions!$C$11 -> 18.242254 | ... BK13: =BK12*Assumptions!$C$11 -> 792.23178
A14: activated_new | B14: Newly activated merchants | C14: 0 | D14: =D11*Assumptions!$C$11 -> 0 | E14: =E11*Assumptions!$C$11 -> 0 | F14: =F11*Assumptions!$C$11 -> 0 | G14: =G11*Assumptions!$C$11 -> 0 | H14: =H11*Assumptions!$C$11 -> 4.8 | I14: =I11*Assumptions!$C$11 -> 4.224 | J14: =J11*Assumptions!$C$11 -> 2.88 | K14: =K11*Assumptions!$C$11 -> 6.72 | ... BK14: =BK11*Assumptions!$C$11 -> 25.728
B15: Rollout gates (1 = unlocked; plans.ts unlockAtMerchants)
A16: plus_unlocked | B16: Plus features GA | C16: 0 | D16: =IF(OR(C16=1,AND(D13>=Assumptions!$C$18,D7>=Assumptions!$C$19)),1,0) -> 0 | E16: =IF(OR(D16=1,AND(E13>=Assumptions!$C$18,E7>=Assumptions!$C$19)),1,0) -> 0 | F16: =IF(OR(E16=1,AND(F13>=Assumptions!$C$18,F7>=Assumptions!$C$19)),1,0) -> 0 | G16: =IF(OR(F16=1,AND(G13>=Assumptions!$C$18,G7>=Assumptions!$C$19)),1,0) -> 0 | H16: =IF(OR(G16=1,AND(H13>=Assumptions!$C$18,H7>=Assumptions!$C$19)),1,0) -> 0 | I16: =IF(OR(H16=1,AND(I13>=Assumptions!$C$18,I7>=Assumptions!$C$19)),1,0) -> 0 | J16: =IF(OR(I16=1,AND(J13>=Assumptions!$C$18,J7>=Assumptions!$C$19)),1,0) -> 0 | K16: =IF(OR(J16=1,AND(K13>=Assumptions!$C$18,K7>=Assumptions!$C$19)),1,0) -> 0 | ... BK16: =IF(OR(BJ16=1,AND(BK13>=Assumptions!$C$18,BK7>=Assumptions!$C$19)),1,0) -> 1
A17: pro_unlocked | B17: Pro features GA | C17: 0 | D17: =IF(OR(C17=1,AND(D13>=Assumptions!$C$20,D7>=Assumptions!$C$21)),1,0) -> 0 | E17: =IF(OR(D17=1,AND(E13>=Assumptions!$C$20,E7>=Assumptions!$C$21)),1,0) -> 0 | F17: =IF(OR(E17=1,AND(F13>=Assumptions!$C$20,F7>=Assumptions!$C$21)),1,0) -> 0 | G17: =IF(OR(F17=1,AND(G13>=Assumptions!$C$20,G7>=Assumptions!$C$21)),1,0) -> 0 | H17: =IF(OR(G17=1,AND(H13>=Assumptions!$C$20,H7>=Assumptions!$C$21)),1,0) -> 0 | I17: =IF(OR(H17=1,AND(I13>=Assumptions!$C$20,I7>=Assumptions!$C$21)),1,0) -> 0 | J17: =IF(OR(I17=1,AND(J13>=Assumptions!$C$20,J7>=Assumptions!$C$21)),1,0) -> 0 | K17: =IF(OR(J17=1,AND(K13>=Assumptions!$C$20,K7>=Assumptions!$C$21)),1,0) -> 0 | ... BK17: =IF(OR(BJ17=1,AND(BK13>=Assumptions!$C$20,BK7>=Assumptions!$C$21)),1,0) -> 1
A18: bia_unlocked | B18: BIA campaigns available | C18: 0 | D18: =IF(OR(C18=1,D13>=Assumptions!$C$22),1,0) -> 0 | E18: =IF(OR(D18=1,E13>=Assumptions!$C$22),1,0) -> 0 | F18: =IF(OR(E18=1,F13>=Assumptions!$C$22),1,0) -> 0 | G18: =IF(OR(F18=1,G13>=Assumptions!$C$22),1,0) -> 0 | H18: =IF(OR(G18=1,H13>=Assumptions!$C$22),1,0) -> 0 | I18: =IF(OR(H18=1,I13>=Assumptions!$C$22),1,0) -> 0 | J18: =IF(OR(I18=1,J13>=Assumptions!$C$22),1,0) -> 0 | K18: =IF(OR(J18=1,K13>=Assumptions!$C$22),1,0) -> 0 | ... BK18: =IF(OR(BJ18=1,BK13>=Assumptions!$C$22),1,0) -> 1
A19: ads_unlocked | B19: Ads available | C19: 0 | D19: =IF(OR(C19=1,AND(D13>=Assumptions!$C$23,D7>=Assumptions!$C$24)),1,0) -> 0 | E19: =IF(OR(D19=1,AND(E13>=Assumptions!$C$23,E7>=Assumptions!$C$24)),1,0) -> 0 | F19: =IF(OR(E19=1,AND(F13>=Assumptions!$C$23,F7>=Assumptions!$C$24)),1,0) -> 0 | G19: =IF(OR(F19=1,AND(G13>=Assumptions!$C$23,G7>=Assumptions!$C$24)),1,0) -> 0 | H19: =IF(OR(G19=1,AND(H13>=Assumptions!$C$23,H7>=Assumptions!$C$24)),1,0) -> 0 | I19: =IF(OR(H19=1,AND(I13>=Assumptions!$C$23,I7>=Assumptions!$C$24)),1,0) -> 0 | J19: =IF(OR(I19=1,AND(J13>=Assumptions!$C$23,J7>=Assumptions!$C$24)),1,0) -> 0 | K19: =IF(OR(J19=1,AND(K13>=Assumptions!$C$23,K7>=Assumptions!$C$24)),1,0) -> 0 | ... BK19: =IF(OR(BJ19=1,AND(BK13>=Assumptions!$C$23,BK7>=Assumptions!$C$24)),1,0) -> 1
A20: ads_months | B20: Months since ads unlocked | C20: 0 | D20: =IF(D19=1,C20+1,0) -> 0 | E20: =IF(E19=1,D20+1,0) -> 0 | F20: =IF(F19=1,E20+1,0) -> 0 | G20: =IF(G19=1,F20+1,0) -> 0 | H20: =IF(H19=1,G20+1,0) -> 0 | I20: =IF(I19=1,H20+1,0) -> 0 | J20: =IF(J19=1,I20+1,0) -> 0 | K20: =IF(K19=1,J20+1,0) -> 0 | ... BK20: =IF(BK19=1,BJ20+1,0) -> 24
A21: ads_ramp | B21: Ad demand ramp | C21: 0 | D21: =MIN(1,D20/Assumptions!$C$77) -> 0 | E21: =MIN(1,E20/Assumptions!$C$77) -> 0 | F21: =MIN(1,F20/Assumptions!$C$77) -> 0 | G21: =MIN(1,G20/Assumptions!$C$77) -> 0 | H21: =MIN(1,H20/Assumptions!$C$77) -> 0 | I21: =MIN(1,I20/Assumptions!$C$77) -> 0 | J21: =MIN(1,J20/Assumptions!$C$77) -> 0 | K21: =MIN(1,K20/Assumptions!$C$77) -> 0 | ... BK21: =MIN(1,BK20/Assumptions!$C$77) -> 1
B22: Customers
A23: memberships | B23: Memberships (customer-shop pairs) | C23: 0 | D23: =C23+(D13*Assumptions!$C$13-C23)*Assumptions!$C$14 -> 0 | E23: =D23+(E13*Assumptions!$C$13-D23)*Assumptions!$C$14 -> 0 | F23: =E23+(F13*Assumptions!$C$13-E23)*Assumptions!$C$14 -> 0 | G23: =F23+(G13*Assumptions!$C$13-F23)*Assumptions!$C$14 -> 0 | H23: =G23+(H13*Assumptions!$C$13-G23)*Assumptions!$C$14 -> 126 | I23: =H23+(I13*Assumptions!$C$13-H23)*Assumptions!$C$14 -> 316.89 | J23: =I23+(J13*Assumptions!$C$13-I23)*Assumptions!$C$14 -> 513.04365 | K23: =J23+(K13*Assumptions!$C$13-J23)*Assumptions!$C$14 -> 812.33755 | ... BK23: =BJ23+(BK13*Assumptions!$C$13-BJ23)*Assumptions!$C$14 -> 57392.841
A24: active_customers | B24: Active customers (unique) | C24: 0 | D24: =D23/Assumptions!$C$15 -> 0 | E24: =E23/Assumptions!$C$15 -> 0 | F24: =F23/Assumptions!$C$15 -> 0 | G24: =G23/Assumptions!$C$15 -> 0 | H24: =H23/Assumptions!$C$15 -> 90 | I24: =I23/Assumptions!$C$15 -> 226.35 | J24: =J23/Assumptions!$C$15 -> 366.45975 | K24: =K23/Assumptions!$C$15 -> 580.2411 | ... BK24: =BK23/Assumptions!$C$15 -> 40994.887
A25: new_customers | B25: New / re-acquired customers | C25: 0 | D25: =MAX(0,D24-C24)+C24*Assumptions!$C$16 -> 0 | E25: =MAX(0,E24-D24)+D24*Assumptions!$C$16 -> 0 | F25: =MAX(0,F24-E24)+E24*Assumptions!$C$16 -> 0 | G25: =MAX(0,G24-F24)+F24*Assumptions!$C$16 -> 0 | H25: =MAX(0,H24-G24)+G24*Assumptions!$C$16 -> 90 | I25: =MAX(0,I24-H24)+H24*Assumptions!$C$16 -> 139.95 | J25: =MAX(0,J24-I24)+I24*Assumptions!$C$16 -> 149.16375 | K25: =MAX(0,K24-J24)+J24*Assumptions!$C$16 -> 228.43974 | ... BK25: =MAX(0,BK24-BJ24)+BJ24*Assumptions!$C$16 -> 2387.3187
B26: Paying merchants by vertical (repair/auto gated by Pro, others by Plus)
A27: paid_food_bev | B27: Paying — Cafes, restaurants, bakeries | C27: 0 | D27: =C27*(1-Assumptions!$C$41)+D16*((1-(1-Assumptions!$C$30)^(1/12))*Assumptions!$C$40)*MAX(0,D13*Assumptions!$C$25-C27) -> 0 | E27: =D27*(1-Assumptions!$C$41)+E16*((1-(1-Assumptions!$C$30)^(1/12))*Assumptions!$C$40)*MAX(0,E13*Assumptions!$C$25-D27) -> 0 | F27: =E27*(1-Assumptions!$C$41)+F16*((1-(1-Assumptions!$C$30)^(1/12))*Assumptions!$C$40)*MAX(0,F13*Assumptions!$C$25-E27) -> 0 | G27: =F27*(1-Assumptions!$C$41)+G16*((1-(1-Assumptions!$C$30)^(1/12))*Assumptions!$C$40)*MAX(0,G13*Assumptions!$C$25-F27) -> 0 | H27: =G27*(1-Assumptions!$C$41)+H16*((1-(1-Assumptions!$C$30)^(1/12))*Assumptions!$C$40)*MAX(0,H13*Assumptions!$C$25-G27) -> 0 | I27: =H27*(1-Assumptions!$C$41)+I16*((1-(1-Assumptions!$C$30)^(1/12))*Assumptions!$C$40)*MAX(0,I13*Assumptions!$C$25-H27) -> 0 | J27: =I27*(1-Assumptions!$C$41)+J16*((1-(1-Assumptions!$C$30)^(1/12))*Assumptions!$C$40)*MAX(0,J13*Assumptions!$C$25-I27) -> 0 | K27: =J27*(1-Assumptions!$C$41)+K16*((1-(1-Assumptions!$C$30)^(1/12))*Assumptions!$C$40)*MAX(0,K13*Assumptions!$C$25-J27) -> 0 | ... BK27: =BJ27*(1-Assumptions!$C$41)+BK16*((1-(1-Assumptions!$C$30)^(1/12))*Assumptions!$C$40)*MAX(0,BK13*Assumptions!$C$25-BJ27) -> 66.433033
A28: paid_retail | B28: Paying — Independent retail | C28: 0 | D28: =C28*(1-Assumptions!$C$41)+D16*((1-(1-Assumptions!$C$31)^(1/12))*Assumptions!$C$40)*MAX(0,D13*Assumptions!$C$26-C28) -> 0 | E28: =D28*(1-Assumptions!$C$41)+E16*((1-(1-Assumptions!$C$31)^(1/12))*Assumptions!$C$40)*MAX(0,E13*Assumptions!$C$26-D28) -> 0 | F28: =E28*(1-Assumptions!$C$41)+F16*((1-(1-Assumptions!$C$31)^(1/12))*Assumptions!$C$40)*MAX(0,F13*Assumptions!$C$26-E28) -> 0 | G28: =F28*(1-Assumptions!$C$41)+G16*((1-(1-Assumptions!$C$31)^(1/12))*Assumptions!$C$40)*MAX(0,G13*Assumptions!$C$26-F28) -> 0 | H28: =G28*(1-Assumptions!$C$41)+H16*((1-(1-Assumptions!$C$31)^(1/12))*Assumptions!$C$40)*MAX(0,H13*Assumptions!$C$26-G28) -> 0 | I28: =H28*(1-Assumptions!$C$41)+I16*((1-(1-Assumptions!$C$31)^(1/12))*Assumptions!$C$40)*MAX(0,I13*Assumptions!$C$26-H28) -> 0 | J28: =I28*(1-Assumptions!$C$41)+J16*((1-(1-Assumptions!$C$31)^(1/12))*Assumptions!$C$40)*MAX(0,J13*Assumptions!$C$26-I28) -> 0 | K28: =J28*(1-Assumptions!$C$41)+K16*((1-(1-Assumptions!$C$31)^(1/12))*Assumptions!$C$40)*MAX(0,K13*Assumptions!$C$26-J28) -> 0 | ... BK28: =BJ28*(1-Assumptions!$C$41)+BK16*((1-(1-Assumptions!$C$31)^(1/12))*Assumptions!$C$40)*MAX(0,BK13*Assumptions!$C$26-BJ28) -> 29.695505
A29: paid_repair_auto | B29: Paying — Repair, auto, alterations, print | C29: 0 | D29: =C29*(1-Assumptions!$C$41)+D17*((1-(1-Assumptions!$C$32)^(1/12))*Assumptions!$C$40)*MAX(0,D13*Assumptions!$C$27-C29) -> 0 | E29: =D29*(1-Assumptions!$C$41)+E17*((1-(1-Assumptions!$C$32)^(1/12))*Assumptions!$C$40)*MAX(0,E13*Assumptions!$C$27-D29) -> 0 | F29: =E29*(1-Assumptions!$C$41)+F17*((1-(1-Assumptions!$C$32)^(1/12))*Assumptions!$C$40)*MAX(0,F13*Assumptions!$C$27-E29) -> 0 | G29: =F29*(1-Assumptions!$C$41)+G17*((1-(1-Assumptions!$C$32)^(1/12))*Assumptions!$C$40)*MAX(0,G13*Assumptions!$C$27-F29) -> 0 | H29: =G29*(1-Assumptions!$C$41)+H17*((1-(1-Assumptions!$C$32)^(1/12))*Assumptions!$C$40)*MAX(0,H13*Assumptions!$C$27-G29) -> 0 | I29: =H29*(1-Assumptions!$C$41)+I17*((1-(1-Assumptions!$C$32)^(1/12))*Assumptions!$C$40)*MAX(0,I13*Assumptions!$C$27-H29) -> 0 | J29: =I29*(1-Assumptions!$C$41)+J17*((1-(1-Assumptions!$C$32)^(1/12))*Assumptions!$C$40)*MAX(0,J13*Assumptions!$C$27-I29) -> 0 | K29: =J29*(1-Assumptions!$C$41)+K17*((1-(1-Assumptions!$C$32)^(1/12))*Assumptions!$C$40)*MAX(0,K13*Assumptions!$C$27-J29) -> 0 | ... BK29: =BJ29*(1-Assumptions!$C$41)+BK17*((1-(1-Assumptions!$C$32)^(1/12))*Assumptions!$C$40)*MAX(0,BK13*Assumptions!$C$27-BJ29) -> 68.504829
A30: paid_personal_services | B30: Paying — Salons, barbers, fitness, pets | C30: 0 | D30: =C30*(1-Assumptions!$C$41)+D16*((1-(1-Assumptions!$C$33)^(1/12))*Assumptions!$C$40)*MAX(0,D13*Assumptions!$C$28-C30) -> 0 | E30: =D30*(1-Assumptions!$C$41)+E16*((1-(1-Assumptions!$C$33)^(1/12))*Assumptions!$C$40)*MAX(0,E13*Assumptions!$C$28-D30) -> 0 | F30: =E30*(1-Assumptions!$C$41)+F16*((1-(1-Assumptions!$C$33)^(1/12))*Assumptions!$C$40)*MAX(0,F13*Assumptions!$C$28-E30) -> 0 | G30: =F30*(1-Assumptions!$C$41)+G16*((1-(1-Assumptions!$C$33)^(1/12))*Assumptions!$C$40)*MAX(0,G13*Assumptions!$C$28-F30) -> 0 | H30: =G30*(1-Assumptions!$C$41)+H16*((1-(1-Assumptions!$C$33)^(1/12))*Assumptions!$C$40)*MAX(0,H13*Assumptions!$C$28-G30) -> 0 | I30: =H30*(1-Assumptions!$C$41)+I16*((1-(1-Assumptions!$C$33)^(1/12))*Assumptions!$C$40)*MAX(0,I13*Assumptions!$C$28-H30) -> 0 | J30: =I30*(1-Assumptions!$C$41)+J16*((1-(1-Assumptions!$C$33)^(1/12))*Assumptions!$C$40)*MAX(0,J13*Assumptions!$C$28-I30) -> 0 | K30: =J30*(1-Assumptions!$C$41)+K16*((1-(1-Assumptions!$C$33)^(1/12))*Assumptions!$C$40)*MAX(0,K13*Assumptions!$C$28-J30) -> 0 | ... BK30: =BJ30*(1-Assumptions!$C$41)+BK16*((1-(1-Assumptions!$C$33)^(1/12))*Assumptions!$C$40)*MAX(0,BK13*Assumptions!$C$28-BJ30) -> 17.537441
A31: paid_pharmacy | B31: Paying — Independent pharmacies (front store only) | C31: 0 | D31: =C31*(1-Assumptions!$C$41)+D16*((1-(1-Assumptions!$C$34)^(1/12))*Assumptions!$C$40)*MAX(0,D13*Assumptions!$C$29-C31) -> 0 | E31: =D31*(1-Assumptions!$C$41)+E16*((1-(1-Assumptions!$C$34)^(1/12))*Assumptions!$C$40)*MAX(0,E13*Assumptions!$C$29-D31) -> 0 | F31: =E31*(1-Assumptions!$C$41)+F16*((1-(1-Assumptions!$C$34)^(1/12))*Assumptions!$C$40)*MAX(0,F13*Assumptions!$C$29-E31) -> 0 | G31: =F31*(1-Assumptions!$C$41)+G16*((1-(1-Assumptions!$C$34)^(1/12))*Assumptions!$C$40)*MAX(0,G13*Assumptions!$C$29-F31) -> 0 | H31: =G31*(1-Assumptions!$C$41)+H16*((1-(1-Assumptions!$C$34)^(1/12))*Assumptions!$C$40)*MAX(0,H13*Assumptions!$C$29-G31) -> 0 | I31: =H31*(1-Assumptions!$C$41)+I16*((1-(1-Assumptions!$C$34)^(1/12))*Assumptions!$C$40)*MAX(0,I13*Assumptions!$C$29-H31) -> 0 | J31: =I31*(1-Assumptions!$C$41)+J16*((1-(1-Assumptions!$C$34)^(1/12))*Assumptions!$C$40)*MAX(0,J13*Assumptions!$C$29-I31) -> 0 | K31: =J31*(1-Assumptions!$C$41)+K16*((1-(1-Assumptions!$C$34)^(1/12))*Assumptions!$C$40)*MAX(0,K13*Assumptions!$C$29-J31) -> 0 | ... BK31: =BJ31*(1-Assumptions!$C$41)+BK16*((1-(1-Assumptions!$C$34)^(1/12))*Assumptions!$C$40)*MAX(0,BK13*Assumptions!$C$29-BJ31) -> 4.109074
A32: paid_total | B32: Paying merchants (total) | C32: 0 | D32: =D27+D28+D29+D30+D31 -> 0 | E32: =E27+E28+E29+E30+E31 -> 0 | F32: =F27+F28+F29+F30+F31 -> 0 | G32: =G27+G28+G29+G30+G31 -> 0 | H32: =H27+H28+H29+H30+H31 -> 0 | I32: =I27+I28+I29+I30+I31 -> 0 | J32: =J27+J28+J29+J30+J31 -> 0 | K32: =K27+K28+K29+K30+K31 -> 0 | ... BK32: =BK27+BK28+BK29+BK30+BK31 -> 186.27988
A33: plus_merchants | B33: Plus merchants | D33: =D27*(1-Assumptions!$C$35)+D28*(1-Assumptions!$C$36)+D29*(1-Assumptions!$C$37)+D30*(1-Assumptions!$C$38)+D31*(1-Assumptions!$C$39) -> 0 | E33: =E27*(1-Assumptions!$C$35)+E28*(1-Assumptions!$C$36)+E29*(1-Assumptions!$C$37)+E30*(1-Assumptions!$C$38)+E31*(1-Assumptions!$C$39) -> 0 | F33: =F27*(1-Assumptions!$C$35)+F28*(1-Assumptions!$C$36)+F29*(1-Assumptions!$C$37)+F30*(1-Assumptions!$C$38)+F31*(1-Assumptions!$C$39) -> 0 | G33: =G27*(1-Assumptions!$C$35)+G28*(1-Assumptions!$C$36)+G29*(1-Assumptions!$C$37)+G30*(1-Assumptions!$C$38)+G31*(1-Assumptions!$C$39) -> 0 | H33: =H27*(1-Assumptions!$C$35)+H28*(1-Assumptions!$C$36)+H29*(1-Assumptions!$C$37)+H30*(1-Assumptions!$C$38)+H31*(1-Assumptions!$C$39) -> 0 | I33: =I27*(1-Assumptions!$C$35)+I28*(1-Assumptions!$C$36)+I29*(1-Assumptions!$C$37)+I30*(1-Assumptions!$C$38)+I31*(1-Assumptions!$C$39) -> 0 | J33: =J27*(1-Assumptions!$C$35)+J28*(1-Assumptions!$C$36)+J29*(1-Assumptions!$C$37)+J30*(1-Assumptions!$C$38)+J31*(1-Assumptions!$C$39) -> 0 | K33: =K27*(1-Assumptions!$C$35)+K28*(1-Assumptions!$C$36)+K29*(1-Assumptions!$C$37)+K30*(1-Assumptions!$C$38)+K31*(1-Assumptions!$C$39) -> 0 | ... BK33: =BK27*(1-Assumptions!$C$35)+BK28*(1-Assumptions!$C$36)+BK29*(1-Assumptions!$C$37)+BK30*(1-Assumptions!$C$38)+BK31*(1-Assumptions!$C$39) -> 117.98312
A34: pro_merchants | B34: Pro merchants | D34: =D27*Assumptions!$C$35+D28*Assumptions!$C$36+D29*Assumptions!$C$37+D30*Assumptions!$C$38+D31*Assumptions!$C$39 -> 0 | E34: =E27*Assumptions!$C$35+E28*Assumptions!$C$36+E29*Assumptions!$C$37+E30*Assumptions!$C$38+E31*Assumptions!$C$39 -> 0 | F34: =F27*Assumptions!$C$35+F28*Assumptions!$C$36+F29*Assumptions!$C$37+F30*Assumptions!$C$38+F31*Assumptions!$C$39 -> 0 | G34: =G27*Assumptions!$C$35+G28*Assumptions!$C$36+G29*Assumptions!$C$37+G30*Assumptions!$C$38+G31*Assumptions!$C$39 -> 0 | H34: =H27*Assumptions!$C$35+H28*Assumptions!$C$36+H29*Assumptions!$C$37+H30*Assumptions!$C$38+H31*Assumptions!$C$39 -> 0 | I34: =I27*Assumptions!$C$35+I28*Assumptions!$C$36+I29*Assumptions!$C$37+I30*Assumptions!$C$38+I31*Assumptions!$C$39 -> 0 | J34: =J27*Assumptions!$C$35+J28*Assumptions!$C$36+J29*Assumptions!$C$37+J30*Assumptions!$C$38+J31*Assumptions!$C$39 -> 0 | K34: =K27*Assumptions!$C$35+K28*Assumptions!$C$36+K29*Assumptions!$C$37+K30*Assumptions!$C$38+K31*Assumptions!$C$39 -> 0 | ... BK34: =BK27*Assumptions!$C$35+BK28*Assumptions!$C$36+BK29*Assumptions!$C$37+BK30*Assumptions!$C$38+BK31*Assumptions!$C$39 -> 68.296764
A35: new_conversions | B35: New paid conversions | D35: =MAX(0,D32-C32*(1-Assumptions!$C$41)) -> 0 | E35: =MAX(0,E32-D32*(1-Assumptions!$C$41)) -> 0 | F35: =MAX(0,F32-E32*(1-Assumptions!$C$41)) -> 0 | G35: =MAX(0,G32-F32*(1-Assumptions!$C$41)) -> 0 | H35: =MAX(0,H32-G32*(1-Assumptions!$C$41)) -> 0 | I35: =MAX(0,I32-H32*(1-Assumptions!$C$41)) -> 0 | J35: =MAX(0,J32-I32*(1-Assumptions!$C$41)) -> 0 | K35: =MAX(0,K32-J32*(1-Assumptions!$C$41)) -> 0 | ... BK35: =MAX(0,BK32-BJ32*(1-Assumptions!$C$41)) -> 10.842996
B36: Revenue (CAD)
A37: rev_plus | B37: Plus subscriptions | D37: =D33*Assumptions!$C$42 -> 0 | E37: =E33*Assumptions!$C$42 -> 0 | F37: =F33*Assumptions!$C$42 -> 0 | G37: =G33*Assumptions!$C$42 -> 0 | H37: =H33*Assumptions!$C$42 -> 0 | I37: =I33*Assumptions!$C$42 -> 0 | J37: =J33*Assumptions!$C$42 -> 0 | K37: =K33*Assumptions!$C$42 -> 0 | ... BK37: =BK33*Assumptions!$C$42 -> 4601.3416
A38: rev_pro | B38: Pro subscriptions | D38: =D34*Assumptions!$C$43 -> 0 | E38: =E34*Assumptions!$C$43 -> 0 | F38: =F34*Assumptions!$C$43 -> 0 | G38: =G34*Assumptions!$C$43 -> 0 | H38: =H34*Assumptions!$C$43 -> 0 | I38: =I34*Assumptions!$C$43 -> 0 | J38: =J34*Assumptions!$C$43 -> 0 | K38: =K34*Assumptions!$C$43 -> 0 | ... BK38: =BK34*Assumptions!$C$43 -> 5395.4443
A39: gmv_in_app | B39: In-app payment volume (GMV) | D39: =(D33*Assumptions!$C$46+D34*Assumptions!$C$47)*Assumptions!$C$45 -> 0 | E39: =(E33*Assumptions!$C$46+E34*Assumptions!$C$47)*Assumptions!$C$45 -> 0 | F39: =(F33*Assumptions!$C$46+F34*Assumptions!$C$47)*Assumptions!$C$45 -> 0 | G39: =(G33*Assumptions!$C$46+G34*Assumptions!$C$47)*Assumptions!$C$45 -> 0 | H39: =(H33*Assumptions!$C$46+H34*Assumptions!$C$47)*Assumptions!$C$45 -> 0 | I39: =(I33*Assumptions!$C$46+I34*Assumptions!$C$47)*Assumptions!$C$45 -> 0 | J39: =(J33*Assumptions!$C$46+J34*Assumptions!$C$47)*Assumptions!$C$45 -> 0 | K39: =(K33*Assumptions!$C$46+K34*Assumptions!$C$47)*Assumptions!$C$45 -> 0 | ... BK39: =(BK33*Assumptions!$C$46+BK34*Assumptions!$C$47)*Assumptions!$C$45 -> 422843.03
A40: rev_payments | B40: Platform fee on payments (0.75%) | D40: =D39*Assumptions!$C$44 -> 0 | E40: =E39*Assumptions!$C$44 -> 0 | F40: =F39*Assumptions!$C$44 -> 0 | G40: =G39*Assumptions!$C$44 -> 0 | H40: =H39*Assumptions!$C$44 -> 0 | I40: =I39*Assumptions!$C$44 -> 0 | J40: =J39*Assumptions!$C$44 -> 0 | K40: =K39*Assumptions!$C$44 -> 0 | ... BK40: =BK39*Assumptions!$C$44 -> 3171.3227
A41: rev_ads_impressions | B41: Sponsored listings/promos (CPM) | D41: =D24*Assumptions!$C$17*Assumptions!$C$68*Assumptions!$C$69*Assumptions!$C$70*Assumptions!$C$71/1000*D21 -> 0 | E41: =E24*Assumptions!$C$17*Assumptions!$C$68*Assumptions!$C$69*Assumptions!$C$70*Assumptions!$C$71/1000*E21 -> 0 | F41: =F24*Assumptions!$C$17*Assumptions!$C$68*Assumptions!$C$69*Assumptions!$C$70*Assumptions!$C$71/1000*F21 -> 0 | G41: =G24*Assumptions!$C$17*Assumptions!$C$68*Assumptions!$C$69*Assumptions!$C$70*Assumptions!$C$71/1000*G21 -> 0 | H41: =H24*Assumptions!$C$17*Assumptions!$C$68*Assumptions!$C$69*Assumptions!$C$70*Assumptions!$C$71/1000*H21 -> 0 | I41: =I24*Assumptions!$C$17*Assumptions!$C$68*Assumptions!$C$69*Assumptions!$C$70*Assumptions!$C$71/1000*I21 -> 0 | J41: =J24*Assumptions!$C$17*Assumptions!$C$68*Assumptions!$C$69*Assumptions!$C$70*Assumptions!$C$71/1000*J21 -> 0 | K41: =K24*Assumptions!$C$17*Assumptions!$C$68*Assumptions!$C$69*Assumptions!$C$70*Assumptions!$C$71/1000*K21 -> 0 | ... BK41: =BK24*Assumptions!$C$17*Assumptions!$C$68*Assumptions!$C$69*Assumptions!$C$70*Assumptions!$C$71/1000*BK21 -> 413.22846
A42: rev_map_pins | B42: Featured map pins | D42: =D13*Assumptions!$C$72*Assumptions!$C$73*D21 -> 0 | E42: =E13*Assumptions!$C$72*Assumptions!$C$73*E21 -> 0 | F42: =F13*Assumptions!$C$72*Assumptions!$C$73*F21 -> 0 | G42: =G13*Assumptions!$C$72*Assumptions!$C$73*G21 -> 0 | H42: =H13*Assumptions!$C$72*Assumptions!$C$73*H21 -> 0 | I42: =I13*Assumptions!$C$72*Assumptions!$C$73*I21 -> 0 | J42: =J13*Assumptions!$C$72*Assumptions!$C$73*J21 -> 0 | K42: =K13*Assumptions!$C$72*Assumptions!$C$73*K21 -> 0 | ... BK42: =BK13*Assumptions!$C$72*Assumptions!$C$73*BK21 -> 1782.5215
A43: rev_push_boosts | B43: Nearby push boosts | D43: =D13*Assumptions!$C$74*Assumptions!$C$75*Assumptions!$C$76*D21 -> 0 | E43: =E13*Assumptions!$C$74*Assumptions!$C$75*Assumptions!$C$76*E21 -> 0 | F43: =F13*Assumptions!$C$74*Assumptions!$C$75*Assumptions!$C$76*F21 -> 0 | G43: =G13*Assumptions!$C$74*Assumptions!$C$75*Assumptions!$C$76*G21 -> 0 | H43: =H13*Assumptions!$C$74*Assumptions!$C$75*Assumptions!$C$76*H21 -> 0 | I43: =I13*Assumptions!$C$74*Assumptions!$C$75*Assumptions!$C$76*I21 -> 0 | J43: =J13*Assumptions!$C$74*Assumptions!$C$75*Assumptions!$C$76*J21 -> 0 | K43: =K13*Assumptions!$C$74*Assumptions!$C$75*Assumptions!$C$76*K21 -> 0 | ... BK43: =BK13*Assumptions!$C$74*Assumptions!$C$75*Assumptions!$C$76*BK21 -> 1584.4636
A44: bia_campaigns | B44: BIA campaigns sold (expected) | D44: =D10*Assumptions!$C$80/12*D18 -> 0 | E44: =E10*Assumptions!$C$80/12*E18 -> 0 | F44: =F10*Assumptions!$C$80/12*F18 -> 0 | G44: =G10*Assumptions!$C$80/12*G18 -> 0 | H44: =H10*Assumptions!$C$80/12*H18 -> 0 | I44: =I10*Assumptions!$C$80/12*I18 -> 0 | J44: =J10*Assumptions!$C$80/12*J18 -> 0 | K44: =K10*Assumptions!$C$80/12*K18 -> 0 | ... BK44: =BK10*Assumptions!$C$80/12*BK18 -> 4.4166667
A45: rev_bia | B45: BIA neighbourhood campaigns | D45: =D44*Assumptions!$C$81 -> 0 | E45: =E44*Assumptions!$C$81 -> 0 | F45: =F44*Assumptions!$C$81 -> 0 | G45: =G44*Assumptions!$C$81 -> 0 | H45: =H44*Assumptions!$C$81 -> 0 | I45: =I44*Assumptions!$C$81 -> 0 | J45: =J44*Assumptions!$C$81 -> 0 | K45: =K44*Assumptions!$C$81 -> 0 | ... BK45: =BK44*Assumptions!$C$81 -> 9937.5
A46: rev_total | B46: Total revenue | D46: =D37+D38+D40+D41+D42+D43+D45 -> 0 | E46: =E37+E38+E40+E41+E42+E43+E45 -> 0 | F46: =F37+F38+F40+F41+F42+F43+F45 -> 0 | G46: =G37+G38+G40+G41+G42+G43+G45 -> 0 | H46: =H37+H38+H40+H41+H42+H43+H45 -> 0 | I46: =I37+I38+I40+I41+I42+I43+I45 -> 0 | J46: =J37+J38+J40+J41+J42+J43+J45 -> 0 | K46: =K37+K38+K40+K41+K42+K43+K45 -> 0 | ... BK46: =BK37+BK38+BK40+BK41+BK42+BK43+BK45 -> 26885.822
A47: mrr_subscriptions | B47: Subscription MRR | D47: =D37+D38 -> 0 | E47: =E37+E38 -> 0 | F47: =F37+F38 -> 0 | G47: =G37+G38 -> 0 | H47: =H37+H38 -> 0 | I47: =I37+I38 -> 0 | J47: =J37+J38 -> 0 | K47: =K37+K38 -> 0 | ... BK47: =BK37+BK38 -> 9996.7859
B48: Variable costs (CAD)
A49: cost_free_merchants | B49: Free-tier merchant cost (infra + support) | D49: =D12*(Assumptions!$C$60+Assumptions!$C$63/60*Assumptions!$C$62) -> 0 | E49: =E12*(Assumptions!$C$60+Assumptions!$C$63/60*Assumptions!$C$62) -> 0 | F49: =F12*(Assumptions!$C$60+Assumptions!$C$63/60*Assumptions!$C$62) -> 0 | G49: =G12*(Assumptions!$C$60+Assumptions!$C$63/60*Assumptions!$C$62) -> 0 | H49: =H12*(Assumptions!$C$60+Assumptions!$C$63/60*Assumptions!$C$62) -> 24.666667 | I49: =I12*(Assumptions!$C$60+Assumptions!$C$63/60*Assumptions!$C$62) -> 46.003333 | J49: =J12*(Assumptions!$C$60+Assumptions!$C$63/60*Assumptions!$C$62) -> 60.113283 | K49: =K12*(Assumptions!$C$60+Assumptions!$C$63/60*Assumptions!$C$62) -> 93.744917 | ... BK49: =BK12*(Assumptions!$C$60+Assumptions!$C$63/60*Assumptions!$C$62) -> 4071.1911
A50: cost_paid_support | B50: Extra support, paying merchants | D50: =D32*Assumptions!$C$64/60*Assumptions!$C$62 -> 0 | E50: =E32*Assumptions!$C$64/60*Assumptions!$C$62 -> 0 | F50: =F32*Assumptions!$C$64/60*Assumptions!$C$62 -> 0 | G50: =G32*Assumptions!$C$64/60*Assumptions!$C$62 -> 0 | H50: =H32*Assumptions!$C$64/60*Assumptions!$C$62 -> 0 | I50: =I32*Assumptions!$C$64/60*Assumptions!$C$62 -> 0 | J50: =J32*Assumptions!$C$64/60*Assumptions!$C$62 -> 0 | K50: =K32*Assumptions!$C$64/60*Assumptions!$C$62 -> 0 | ... BK50: =BK32*Assumptions!$C$64/60*Assumptions!$C$62 -> 1164.2493
A51: cost_customer_infra | B51: Customer infra | D51: =D24*Assumptions!$C$61 -> 0 | E51: =E24*Assumptions!$C$61 -> 0 | F51: =F24*Assumptions!$C$61 -> 0 | G51: =G24*Assumptions!$C$61 -> 0 | H51: =H24*Assumptions!$C$61 -> 0.9 | I51: =I24*Assumptions!$C$61 -> 2.2635 | J51: =J24*Assumptions!$C$61 -> 3.6645975 | K51: =K24*Assumptions!$C$61 -> 5.802411 | ... BK51: =BK24*Assumptions!$C$61 -> 409.94887
A52: cost_sms | B52: SMS (Twilio) | D52: =(D33*Assumptions!$C$56+D34*Assumptions!$C$57+D25*Assumptions!$C$58+D24*Assumptions!$C$59)*Assumptions!$C$55 -> 0 | E52: =(E33*Assumptions!$C$56+E34*Assumptions!$C$57+E25*Assumptions!$C$58+E24*Assumptions!$C$59)*Assumptions!$C$55 -> 0 | F52: =(F33*Assumptions!$C$56+F34*Assumptions!$C$57+F25*Assumptions!$C$58+F24*Assumptions!$C$59)*Assumptions!$C$55 -> 0 | G52: =(G33*Assumptions!$C$56+G34*Assumptions!$C$57+G25*Assumptions!$C$58+G24*Assumptions!$C$59)*Assumptions!$C$55 -> 0 | H52: =(H33*Assumptions!$C$56+H34*Assumptions!$C$57+H25*Assumptions!$C$58+H24*Assumptions!$C$59)*Assumptions!$C$55 -> 3.564 | I52: =(I33*Assumptions!$C$56+I34*Assumptions!$C$57+I25*Assumptions!$C$58+I24*Assumptions!$C$59)*Assumptions!$C$55 -> 6.11226 | J52: =(J33*Assumptions!$C$56+J34*Assumptions!$C$57+J25*Assumptions!$C$58+J24*Assumptions!$C$59)*Assumptions!$C$55 -> 7.3410381 | K52: =(K33*Assumptions!$C$56+K34*Assumptions!$C$57+K25*Assumptions!$C$58+K24*Assumptions!$C$59)*Assumptions!$C$55 -> 11.368103 | ... BK52: =(BK33*Assumptions!$C$56+BK34*Assumptions!$C$57+BK25*Assumptions!$C$58+BK24*Assumptions!$C$59)*Assumptions!$C$55 -> 2480.3123
A53: cost_payments | B53: Stripe Connect platform costs | D53: =D39*Assumptions!$C$51+D32*Assumptions!$C$45*Assumptions!$C$52 -> 0 | E53: =E39*Assumptions!$C$51+E32*Assumptions!$C$45*Assumptions!$C$52 -> 0 | F53: =F39*Assumptions!$C$51+F32*Assumptions!$C$45*Assumptions!$C$52 -> 0 | G53: =G39*Assumptions!$C$51+G32*Assumptions!$C$45*Assumptions!$C$52 -> 0 | H53: =H39*Assumptions!$C$51+H32*Assumptions!$C$45*Assumptions!$C$52 -> 0 | I53: =I39*Assumptions!$C$51+I32*Assumptions!$C$45*Assumptions!$C$52 -> 0 | J53: =J39*Assumptions!$C$51+J32*Assumptions!$C$45*Assumptions!$C$52 -> 0 | K53: =K39*Assumptions!$C$51+K32*Assumptions!$C$45*Assumptions!$C$52 -> 0 | ... BK53: =BK39*Assumptions!$C$51+BK32*Assumptions!$C$45*Assumptions!$C$52 -> 1280.6434
A54: cost_billing | B54: Subscription billing fees | D54: =(D37+D38)*Assumptions!$C$53+D32*Assumptions!$C$54 -> 0 | E54: =(E37+E38)*Assumptions!$C$53+E32*Assumptions!$C$54 -> 0 | F54: =(F37+F38)*Assumptions!$C$53+F32*Assumptions!$C$54 -> 0 | G54: =(G37+G38)*Assumptions!$C$53+G32*Assumptions!$C$54 -> 0 | H54: =(H37+H38)*Assumptions!$C$53+H32*Assumptions!$C$54 -> 0 | I54: =(I37+I38)*Assumptions!$C$53+I32*Assumptions!$C$54 -> 0 | J54: =(J37+J38)*Assumptions!$C$53+J32*Assumptions!$C$54 -> 0 | K54: =(K37+K38)*Assumptions!$C$53+K32*Assumptions!$C$54 -> 0 | ... BK54: =(BK37+BK38)*Assumptions!$C$53+BK32*Assumptions!$C$54 -> 395.77469
A55: cost_network_perks | B55: Platform-funded network perks | D55: =D25*Assumptions!$C$65*Assumptions!$C$66*Assumptions!$C$67 -> 0 | E55: =E25*Assumptions!$C$65*Assumptions!$C$66*Assumptions!$C$67 -> 0 | F55: =F25*Assumptions!$C$65*Assumptions!$C$66*Assumptions!$C$67 -> 0 | G55: =G25*Assumptions!$C$65*Assumptions!$C$66*Assumptions!$C$67 -> 0 | H55: =H25*Assumptions!$C$65*Assumptions!$C$66*Assumptions!$C$67 -> 24.3 | I55: =I25*Assumptions!$C$65*Assumptions!$C$66*Assumptions!$C$67 -> 37.7865 | J55: =J25*Assumptions!$C$65*Assumptions!$C$66*Assumptions!$C$67 -> 40.274212 | K55: =K25*Assumptions!$C$65*Assumptions!$C$66*Assumptions!$C$67 -> 61.678731 | ... BK55: =BK25*Assumptions!$C$65*Assumptions!$C$66*Assumptions!$C$67 -> 644.57606
A56: cost_ads_ops | B56: Ad operations | D56: =(D41+D42+D43)*Assumptions!$C$78 -> 0 | E56: =(E41+E42+E43)*Assumptions!$C$78 -> 0 | F56: =(F41+F42+F43)*Assumptions!$C$78 -> 0 | G56: =(G41+G42+G43)*Assumptions!$C$78 -> 0 | H56: =(H41+H42+H43)*Assumptions!$C$78 -> 0 | I56: =(I41+I42+I43)*Assumptions!$C$78 -> 0 | J56: =(J41+J42+J43)*Assumptions!$C$78 -> 0 | K56: =(K41+K42+K43)*Assumptions!$C$78 -> 0 | ... BK56: =(BK41+BK42+BK43)*Assumptions!$C$78 -> 378.02135
A57: cost_bia | B57: BIA campaign delivery | D57: =D45*Assumptions!$C$82 -> 0 | E57: =E45*Assumptions!$C$82 -> 0 | F57: =F45*Assumptions!$C$82 -> 0 | G57: =G45*Assumptions!$C$82 -> 0 | H57: =H45*Assumptions!$C$82 -> 0 | I57: =I45*Assumptions!$C$82 -> 0 | J57: =J45*Assumptions!$C$82 -> 0 | K57: =K45*Assumptions!$C$82 -> 0 | ... BK57: =BK45*Assumptions!$C$82 -> 2981.25
A58: variable_total | B58: Total variable costs | D58: =D49+D50+D51+D52+D53+D54+D55+D56+D57 -> 0 | E58: =E49+E50+E51+E52+E53+E54+E55+E56+E57 -> 0 | F58: =F49+F50+F51+F52+F53+F54+F55+F56+F57 -> 0 | G58: =G49+G50+G51+G52+G53+G54+G55+G56+G57 -> 0 | H58: =H49+H50+H51+H52+H53+H54+H55+H56+H57 -> 53.430667 | I58: =I49+I50+I51+I52+I53+I54+I55+I56+I57 -> 92.165593 | J58: =J49+J50+J51+J52+J53+J54+J55+J56+J57 -> 111.39313 | K58: =K49+K50+K51+K52+K53+K54+K55+K56+K57 -> 172.59416 | ... BK58: =BK49+BK50+BK51+BK52+BK53+BK54+BK55+BK56+BK57 -> 13805.967
A59: gross_profit | B59: Gross profit | D59: =D46-D58 -> 0 | E59: =E46-E58 -> 0 | F59: =F46-F58 -> 0 | G59: =G46-G58 -> 0 | H59: =H46-H58 -> -53.430667 | I59: =I46-I58 -> -92.165593 | J59: =J46-J58 -> -111.39313 | K59: =K46-K58 -> -172.59416 | ... BK59: =BK46-BK58 -> 13079.855
B60: Merchant acquisition (CAC) spend (CAD)
A61: rep_wage | B61: Rep hourly wage (indexed each Oct 1) | D61: =Assumptions!$C$83*(1+Assumptions!$C$84)^INT(D7/12) -> 17.95 | E61: =Assumptions!$C$83*(1+Assumptions!$C$84)^INT(E7/12) -> 17.95 | F61: =Assumptions!$C$83*(1+Assumptions!$C$84)^INT(F7/12) -> 17.95 | G61: =Assumptions!$C$83*(1+Assumptions!$C$84)^INT(G7/12) -> 17.95 | H61: =Assumptions!$C$83*(1+Assumptions!$C$84)^INT(H7/12) -> 17.95 | I61: =Assumptions!$C$83*(1+Assumptions!$C$84)^INT(I7/12) -> 17.95 | J61: =Assumptions!$C$83*(1+Assumptions!$C$84)^INT(J7/12) -> 17.95 | K61: =Assumptions!$C$83*(1+Assumptions!$C$84)^INT(K7/12) -> 17.95 | ... BK61: =Assumptions!$C$83*(1+Assumptions!$C$84)^INT(BK7/12) -> 20.308777
A62: cac_rep_wages | B62: Rep wages incl. payroll burden | D62: =D11*Assumptions!$C$86*D61*(1+Assumptions!$C$85)*Assumptions!$C$91 -> 0 | E62: =E11*Assumptions!$C$86*E61*(1+Assumptions!$C$85)*Assumptions!$C$91 -> 0 | F62: =F11*Assumptions!$C$86*F61*(1+Assumptions!$C$85)*Assumptions!$C$91 -> 0 | G62: =G11*Assumptions!$C$86*G61*(1+Assumptions!$C$85)*Assumptions!$C$91 -> 0 | H62: =H11*Assumptions!$C$86*H61*(1+Assumptions!$C$85)*Assumptions!$C$91 -> 405.67 | I62: =I11*Assumptions!$C$86*I61*(1+Assumptions!$C$85)*Assumptions!$C$91 -> 356.9896 | J62: =J11*Assumptions!$C$86*J61*(1+Assumptions!$C$85)*Assumptions!$C$91 -> 243.402 | K62: =K11*Assumptions!$C$86*K61*(1+Assumptions!$C$85)*Assumptions!$C$91 -> 567.938 | ... BK62: =BK11*Assumptions!$C$86*BK61*(1+Assumptions!$C$85)*Assumptions!$C$91 -> 2460.1241
A63: cac_activation_bonus | B63: Activation bonuses incl. burden | D63: =D14*Assumptions!$C$87*(1+Assumptions!$C$85)*Assumptions!$C$91 -> 0 | E63: =E14*Assumptions!$C$87*(1+Assumptions!$C$85)*Assumptions!$C$91 -> 0 | F63: =F14*Assumptions!$C$87*(1+Assumptions!$C$85)*Assumptions!$C$91 -> 0 | G63: =G14*Assumptions!$C$87*(1+Assumptions!$C$85)*Assumptions!$C$91 -> 0 | H63: =H14*Assumptions!$C$87*(1+Assumptions!$C$85)*Assumptions!$C$91 -> 135.6 | I63: =I14*Assumptions!$C$87*(1+Assumptions!$C$85)*Assumptions!$C$91 -> 119.328 | J63: =J14*Assumptions!$C$87*(1+Assumptions!$C$85)*Assumptions!$C$91 -> 81.36 | K63: =K14*Assumptions!$C$87*(1+Assumptions!$C$85)*Assumptions!$C$91 -> 189.84 | ... BK63: =BK14*Assumptions!$C$87*(1+Assumptions!$C$85)*Assumptions!$C$91 -> 726.816
A64: cac_kits | B64: Counter kits | D64: =D11*Assumptions!$C$88*Assumptions!$C$91 -> 0 | E64: =E11*Assumptions!$C$88*Assumptions!$C$91 -> 0 | F64: =F11*Assumptions!$C$88*Assumptions!$C$91 -> 0 | G64: =G11*Assumptions!$C$88*Assumptions!$C$91 -> 0 | H64: =H11*Assumptions!$C$88*Assumptions!$C$91 -> 120 | I64: =I11*Assumptions!$C$88*Assumptions!$C$91 -> 105.6 | J64: =J11*Assumptions!$C$88*Assumptions!$C$91 -> 72 | K64: =K11*Assumptions!$C$88*Assumptions!$C$91 -> 168 | ... BK64: =BK11*Assumptions!$C$88*Assumptions!$C$91 -> 643.2
A65: cac_strip_launch | B65: Strip launch events | D65: =D8*Assumptions!$C$89*Assumptions!$C$91 -> 0 | E65: =E8*Assumptions!$C$89*Assumptions!$C$91 -> 0 | F65: =F8*Assumptions!$C$89*Assumptions!$C$91 -> 0 | G65: =G8*Assumptions!$C$89*Assumptions!$C$91 -> 0 | H65: =H8*Assumptions!$C$89*Assumptions!$C$91 -> 750 | I65: =I8*Assumptions!$C$89*Assumptions!$C$91 -> 0 | J65: =J8*Assumptions!$C$89*Assumptions!$C$91 -> 0 | K65: =K8*Assumptions!$C$89*Assumptions!$C$91 -> 750 | ... BK65: =BK8*Assumptions!$C$89*Assumptions!$C$91 -> 750
A66: cac_upsell | B66: Paid upsell cost | D66: =D35*Assumptions!$C$90*Assumptions!$C$91 -> 0 | E66: =E35*Assumptions!$C$90*Assumptions!$C$91 -> 0 | F66: =F35*Assumptions!$C$90*Assumptions!$C$91 -> 0 | G66: =G35*Assumptions!$C$90*Assumptions!$C$91 -> 0 | H66: =H35*Assumptions!$C$90*Assumptions!$C$91 -> 0 | I66: =I35*Assumptions!$C$90*Assumptions!$C$91 -> 0 | J66: =J35*Assumptions!$C$90*Assumptions!$C$91 -> 0 | K66: =K35*Assumptions!$C$90*Assumptions!$C$91 -> 0 | ... BK66: =BK35*Assumptions!$C$90*Assumptions!$C$91 -> 542.14981
A67: cac_total | B67: Total acquisition spend | D67: =D62+D63+D64+D65+D66 -> 0 | E67: =E62+E63+E64+E65+E66 -> 0 | F67: =F62+F63+F64+F65+F66 -> 0 | G67: =G62+G63+G64+G65+G66 -> 0 | H67: =H62+H63+H64+H65+H66 -> 1411.27 | I67: =I62+I63+I64+I65+I66 -> 581.9176 | J67: =J62+J63+J64+J65+J66 -> 396.762 | K67: =K62+K63+K64+K65+K66 -> 1675.778 | ... BK67: =BK62+BK63+BK64+BK65+BK66 -> 5122.2899
B68: Fixed operating costs (CAD)
A69: opex_fixed_overhead | B69: Fixed overhead | D69: =Assumptions!$C$108 -> 1465 | E69: =Assumptions!$C$108 -> 1465 | F69: =Assumptions!$C$108 -> 1465 | G69: =Assumptions!$C$108 -> 1465 | H69: =Assumptions!$C$108 -> 1465 | I69: =Assumptions!$C$108 -> 1465 | J69: =Assumptions!$C$108 -> 1465 | K69: =Assumptions!$C$108 -> 1465 | ... BK69: =Assumptions!$C$108 -> 1465
A70: opex_developer | B70: Part-time developer | D70: =IF(D7<=12,Assumptions!$C$100,IF(D7<=24,Assumptions!$C$101,Assumptions!$C$102)) -> 4000 | E70: =IF(E7<=12,Assumptions!$C$100,IF(E7<=24,Assumptions!$C$101,Assumptions!$C$102)) -> 4000 | F70: =IF(F7<=12,Assumptions!$C$100,IF(F7<=24,Assumptions!$C$101,Assumptions!$C$102)) -> 4000 | G70: =IF(G7<=12,Assumptions!$C$100,IF(G7<=24,Assumptions!$C$101,Assumptions!$C$102)) -> 4000 | H70: =IF(H7<=12,Assumptions!$C$100,IF(H7<=24,Assumptions!$C$101,Assumptions!$C$102)) -> 4000 | I70: =IF(I7<=12,Assumptions!$C$100,IF(I7<=24,Assumptions!$C$101,Assumptions!$C$102)) -> 4000 | J70: =IF(J7<=12,Assumptions!$C$100,IF(J7<=24,Assumptions!$C$101,Assumptions!$C$102)) -> 4000 | K70: =IF(K7<=12,Assumptions!$C$100,IF(K7<=24,Assumptions!$C$101,Assumptions!$C$102)) -> 4000 | ... BK70: =IF(BK7<=12,Assumptions!$C$100,IF(BK7<=24,Assumptions!$C$101,Assumptions!$C$102)) -> 6000
A71: opex_customer_success | B71: Account / BIA manager | D71: =INT(D13/Assumptions!$C$103)*Assumptions!$C$104 -> 0 | E71: =INT(E13/Assumptions!$C$103)*Assumptions!$C$104 -> 0 | F71: =INT(F13/Assumptions!$C$103)*Assumptions!$C$104 -> 0 | G71: =INT(G13/Assumptions!$C$103)*Assumptions!$C$104 -> 0 | H71: =INT(H13/Assumptions!$C$103)*Assumptions!$C$104 -> 0 | I71: =INT(I13/Assumptions!$C$103)*Assumptions!$C$104 -> 0 | J71: =INT(J13/Assumptions!$C$103)*Assumptions!$C$104 -> 0 | K71: =INT(K13/Assumptions!$C$103)*Assumptions!$C$104 -> 0 | ... BK71: =INT(BK13/Assumptions!$C$103)*Assumptions!$C$104 -> 0
A72: opex_founder_salary | B72: Founder salary | D72: =IF(D7>=Assumptions!$C$106,Assumptions!$C$105,0) -> 0 | E72: =IF(E7>=Assumptions!$C$106,Assumptions!$C$105,0) -> 0 | F72: =IF(F7>=Assumptions!$C$106,Assumptions!$C$105,0) -> 0 | G72: =IF(G7>=Assumptions!$C$106,Assumptions!$C$105,0) -> 0 | H72: =IF(H7>=Assumptions!$C$106,Assumptions!$C$105,0) -> 0 | I72: =IF(I7>=Assumptions!$C$106,Assumptions!$C$105,0) -> 0 | J72: =IF(J7>=Assumptions!$C$106,Assumptions!$C$105,0) -> 0 | K72: =IF(K7>=Assumptions!$C$106,Assumptions!$C$105,0) -> 0 | ... BK72: =IF(BK7>=Assumptions!$C$106,Assumptions!$C$105,0) -> 0
A73: opex_one_time | B73: One-time costs | D73: =Assumptions!C$144 -> 3500 | E73: =Assumptions!D$144 -> 1500 | F73: =Assumptions!E$144 -> 3000 | G73: =Assumptions!F$144 -> 0 | H73: =Assumptions!G$144 -> 0 | I73: =Assumptions!H$144 -> 0 | J73: =Assumptions!I$144 -> 0 | K73: =Assumptions!J$144 -> 0 | ... BK73: =Assumptions!BJ$144 -> 0
A74: opex_total | B74: Total fixed opex | D74: =D69+D70+D71+D72+D73 -> 8965 | E74: =E69+E70+E71+E72+E73 -> 6965 | F74: =F69+F70+F71+F72+F73 -> 8465 | G74: =G69+G70+G71+G72+G73 -> 5465 | H74: =H69+H70+H71+H72+H73 -> 5465 | I74: =I69+I70+I71+I72+I73 -> 5465 | J74: =J69+J70+J71+J72+J73 -> 5465 | K74: =K69+K70+K71+K72+K73 -> 5465 | ... BK74: =BK69+BK70+BK71+BK72+BK73 -> 7465
B75: Bottom line (CAD)
A76: ebitda | B76: EBITDA / net cash flow | D76: =D59-D67-D74 -> -8965 | E76: =E59-E67-E74 -> -6965 | F76: =F59-F67-F74 -> -8465 | G76: =G59-G67-G74 -> -5465 | H76: =H59-H67-H74 -> -6929.7007 | I76: =I59-I67-I74 -> -6139.0832 | J76: =J59-J67-J74 -> -5973.1551 | K76: =K59-K67-K74 -> -7313.3722 | ... BK76: =BK59-BK67-BK74 -> 492.56526
A77: cum_cash | B77: Cumulative cash (from starting cash) | C77: =Assumptions!$C$9 -> 0 | D77: =C77+D76 -> -8965 | E77: =D77+E76 -> -15930 | F77: =E77+F76 -> -24395 | G77: =F77+G76 -> -29860 | H77: =G77+H76 -> -36789.701 | I77: =H77+I76 -> -42928.784 | J77: =I77+J76 -> -48901.939 | K77: =J77+K76 -> -56215.311 | ... BK77: =BJ77+BK76 -> -420222.68
A78: merchant_paid_stripe_fees | B78: Info: Stripe fees paid by merchants (not ours) | D78: =D39*Assumptions!$C$49+D39/Assumptions!$C$48*Assumptions!$C$50 -> 0 | E78: =E39*Assumptions!$C$49+E39/Assumptions!$C$48*Assumptions!$C$50 -> 0 | F78: =F39*Assumptions!$C$49+F39/Assumptions!$C$48*Assumptions!$C$50 -> 0 | G78: =G39*Assumptions!$C$49+G39/Assumptions!$C$48*Assumptions!$C$50 -> 0 | H78: =H39*Assumptions!$C$49+H39/Assumptions!$C$48*Assumptions!$C$50 -> 0 | I78: =I39*Assumptions!$C$49+I39/Assumptions!$C$48*Assumptions!$C$50 -> 0 | J78: =J39*Assumptions!$C$49+J39/Assumptions!$C$48*Assumptions!$C$50 -> 0 | K78: =K39*Assumptions!$C$49+K39/Assumptions!$C$48*Assumptions!$C$50 -> 0 | ... BK78: =BK39*Assumptions!$C$49+BK39/Assumptions!$C$48*Assumptions!$C$50 -> 15886.817
B79: Break-even helpers
A80: pos_flag | B80: EBITDA >= 0 | D80: =IF(D76>=0,1,0) -> 0 | E80: =IF(E76>=0,1,0) -> 0 | F80: =IF(F76>=0,1,0) -> 0 | G80: =IF(G76>=0,1,0) -> 0 | H80: =IF(H76>=0,1,0) -> 0 | I80: =IF(I76>=0,1,0) -> 0 | J80: =IF(J76>=0,1,0) -> 0 | K80: =IF(K76>=0,1,0) -> 0 | ... BK80: =IF(BK76>=0,1,0) -> 1
A81: stays36 | B81: EBITDA >= 0 from here to month 36 | D81: =IF(AND(D80=1,E81=1),1,0) -> 0 | E81: =IF(AND(E80=1,F81=1),1,0) -> 0 | F81: =IF(AND(F80=1,G81=1),1,0) -> 0 | G81: =IF(AND(G80=1,H81=1),1,0) -> 0 | H81: =IF(AND(H80=1,I81=1),1,0) -> 0 | I81: =IF(AND(I80=1,J81=1),1,0) -> 0 | J81: =IF(AND(J80=1,K81=1),1,0) -> 0 | K81: =IF(AND(K80=1,L81=1),1,0) -> 0 | ... AL81: =IF(AND(AL80=1,AM81=1),1,0) -> 0 | AM81: =AM80 -> 0
A82: stays60 | B82: EBITDA >= 0 from here to month 60 | D82: =IF(AND(D80=1,E82=1),1,0) -> 0 | E82: =IF(AND(E80=1,F82=1),1,0) -> 0 | F82: =IF(AND(F80=1,G82=1),1,0) -> 0 | G82: =IF(AND(G80=1,H82=1),1,0) -> 0 | H82: =IF(AND(H80=1,I82=1),1,0) -> 0 | I82: =IF(AND(I80=1,J82=1),1,0) -> 0 | J82: =IF(AND(J80=1,K82=1),1,0) -> 0 | K82: =IF(AND(K80=1,L82=1),1,0) -> 0 | ... BJ82: =IF(AND(BJ80=1,BK82=1),1,0) -> 0 | BK82: =BK80 -> 1
B84: Key outputs
B85: Break-even month (EBITDA >= 0 through month 36) | C85: =IFERROR(MATCH(1,D81:AM81,0),"none") -> none
B86: Break-even month, extended run (EBITDA >= 0 through month 60) | C86: =IFERROR(MATCH(1,D82:BK82,0),"none") -> 60
B87: First month with EBITDA >= 0 (36m) | C87: =IFERROR(MATCH(1,D80:AM80,0),"none") -> none
B88: Peak cash need, months 1-36 | C88: =-MIN(0,MIN(D77:AM77)) -> 322991.1
B89: Month of cash trough (36m) | C89: =MATCH(MIN(D77:AM77),D77:AM77,0) -> 36
B90: Peak cash need, months 1-60 (to break-even) | C90: =-MIN(0,MIN(D77:BK77)) -> 420715.24
B91: Plus unlock month | C91: =IFERROR(MATCH(1,D16:AM16,0),"none") -> 22
B92: Pro unlock month | C92: =IFERROR(MATCH(1,D17:AM17,0),"none") -> 22
B93: BIA campaigns unlock month | C93: =IFERROR(MATCH(1,D18:AM18,0),"none") -> 18
B94: Ads unlock month | C94: =IFERROR(MATCH(1,D19:AM19,0),"none") -> none
B95: Month-36 active merchants | C95: =AM13 -> 398.76048
B96: Month-36 paying merchants | C96: =AM32 -> 58.104389
B97: Month-36 active customers | C97: =AM24 -> 19474.991
B98: Month-36 revenue | C98: =AM46 -> 8117.5131
B99: Month-36 EBITDA | C99: =AM76 -> -9622.449
B100: Year-1 revenue | C100: =SUM(D46:O46) -> 0
B101: Year-2 revenue | C101: =SUM(P46:AA46) -> 8877.7828
B102: Year-3 revenue | C102: =SUM(AB46:AM46) -> 62747.457
...

Sheet Monthly_Bear
A1: Local Loyalty — monthly model: Bear scenario (CAD)
A2: Every cell is a formula driven by the Assumptions sheet (column D). Months 1-36 = projection; grey months 37-60 = extension used only to locate break-even.
B4: Model month | C4: 0 | D4: 1 | E4: 2 | F4: 3 | G4: 4 | H4: 5 | I4: 6 | J4: 7 | K4: 8 | L4: 9 | M4: 10 | N4: 11 | O4: 12 | P4: 13 | Q4: 14 | R4: 15 | S4: 16 | T4: 17 | U4: 18 | V4: 19 | W4: 20 | X4: 21 | Y4: 22 | Z4: 23 | AA4: 24 | AB4: 25 | AC4: 26 | AD4: 27 | AE4: 28 | AF4: 29 | AG4: 30 | AH4: 31 | AI4: 32 | AJ4: 33 | AK4: 34 | AL4: 35 | AM4: 36 | AN4: 37 | AO4: 38 | AP4: 39 | AQ4: 40 | AR4: 41 | AS4: 42 | AT4: 43 | AU4: 44 | AV4: 45 | AW4: 46 | AX4: 47 | AY4: 48 | AZ4: 49 | BA4: 50 | BB4: 51 | BC4: 52 | BD4: 53 | BE4: 54 | BF4: 55 | BG4: 56 | BH4: 57 | BI4: 58 | BJ4: 59 | BK4: 60
B5: Calendar month | C5: start | D5: 2026-11 | E5: 2026-12 | F5: 2027-01 | G5: 2027-02 | H5: 2027-03 | I5: 2027-04 | J5: 2027-05 | K5: 2027-06 | L5: 2027-07 | M5: 2027-08 | N5: 2027-09 | O5: 2027-10 | P5: 2027-11 | Q5: 2027-12 | R5: 2028-01 | S5: 2028-02 | T5: 2028-03 | U5: 2028-04 | V5: 2028-05 | W5: 2028-06 | X5: 2028-07 | Y5: 2028-08 | Z5: 2028-09 | AA5: 2028-10 | AB5: 2028-11 | AC5: 2028-12 | AD5: 2029-01 | AE5: 2029-02 | AF5: 2029-03 | AG5: 2029-04 | AH5: 2029-05 | AI5: 2029-06 | AJ5: 2029-07 | AK5: 2029-08 | AL5: 2029-09 | AM5: 2029-10 | AN5: 2029-11 | AO5: 2029-12 | AP5: 2030-01 | AQ5: 2030-02 | AR5: 2030-03 | AS5: 2030-04 | AT5: 2030-05 | AU5: 2030-06 | AV5: 2030-07 | AW5: 2030-08 | AX5: 2030-09 | AY5: 2030-10 | AZ5: 2030-11 | BA5: 2030-12 | BB5: 2031-01 | BC5: 2031-02 | BD5: 2031-03 | BE5: 2031-04 | BF5: 2031-05 | BG5: 2031-06 | BH5: 2031-07 | BI5: 2031-08 | BJ5: 2031-09 | BK5: 2031-10
B6: Strips & merchants
A7: month | B7: Model month | C7: 0 | D7: 1 | E7: 2 | F7: 3 | G7: 4 | H7: 5 | I7: 6 | J7: 7 | K7: 8 | L7: 9 | M7: 10 | N7: 11 | O7: 12 | P7: 13 | Q7: 14 | R7: 15 | S7: 16 | T7: 17 | U7: 18 | V7: 19 | W7: 20 | X7: 21 | Y7: 22 | Z7: 23 | AA7: 24 | AB7: 25 | AC7: 26 | AD7: 27 | AE7: 28 | AF7: 29 | AG7: 30 | AH7: 31 | AI7: 32 | AJ7: 33 | AK7: 34 | AL7: 35 | AM7: 36 | AN7: 37 | AO7: 38 | AP7: 39 | AQ7: 40 | AR7: 41 | AS7: 42 | AT7: 43 | AU7: 44 | AV7: 45 | AW7: 46 | AX7: 47 | AY7: 48 | AZ7: 49 | BA7: 50 | BB7: 51 | BC7: 52 | BD7: 53 | BE7: 54 | BF7: 55 | BG7: 56 | BH7: 57 | BI7: 58 | BJ7: 59 | BK7: 60
A8: strips_launched | B8: Strips launched | C8: 0 | D8: =Assumptions!C$140 -> 0 | E8: =Assumptions!D$140 -> 0 | F8: =Assumptions!E$140 -> 0 | G8: =Assumptions!F$140 -> 0 | H8: =Assumptions!G$140 -> 1 | I8: =Assumptions!H$140 -> 0 | J8: =Assumptions!I$140 -> 0 | K8: =Assumptions!J$140 -> 0 | ... BK8: =Assumptions!BJ$140 -> 1
A9: strips_cum | B9: Strips live (cumulative) | C9: 0 | D9: =C9+D8 -> 0 | E9: =D9+E8 -> 0 | F9: =E9+F8 -> 0 | G9: =F9+G8 -> 0 | H9: =G9+H8 -> 1 | I9: =H9+I8 -> 1 | J9: =I9+J8 -> 1 | K9: =J9+K8 -> 1 | ... BK9: =BJ9+BK8 -> 44
A10: strips_mature | B10: Mature strips (launched >= maturity months ago) | C10: 0 | D10: =IF(D7>Assumptions!$D$79,INDEX($D$9:$BK$9,D7-Assumptions!$D$79),0) -> 0 | E10: =IF(E7>Assumptions!$D$79,INDEX($D$9:$BK$9,E7-Assumptions!$D$79),0) -> 0 | F10: =IF(F7>Assumptions!$D$79,INDEX($D$9:$BK$9,F7-Assumptions!$D$79),0) -> 0 | G10: =IF(G7>Assumptions!$D$79,INDEX($D$9:$BK$9,G7-Assumptions!$D$79),0) -> 0 | H10: =IF(H7>Assumptions!$D$79,INDEX($D$9:$BK$9,H7-Assumptions!$D$79),0) -> 0 | I10: =IF(I7>Assumptions!$D$79,INDEX($D$9:$BK$9,I7-Assumptions!$D$79),0) -> 0 | J10: =IF(J7>Assumptions!$D$79,INDEX($D$9:$BK$9,J7-Assumptions!$D$79),0) -> 0 | K10: =IF(K7>Assumptions!$D$79,INDEX($D$9:$BK$9,K7-Assumptions!$D$79),0) -> 0 | ... BK10: =IF(BK7>Assumptions!$D$79,INDEX($D$9:$BK$9,BK7-Assumptions!$D$79),0) -> 38
A11: signups | B11: New merchant sign-ups | C11: 0 | D11: =Assumptions!$D$10*(D8*Assumptions!$D$111) -> 0 | E11: =Assumptions!$D$10*(E8*Assumptions!$D$111+D8*Assumptions!$D$112) -> 0 | F11: =Assumptions!$D$10*(F8*Assumptions!$D$111+E8*Assumptions!$D$112+D8*Assumptions!$D$113) -> 0 | G11: =Assumptions!$D$10*(G8*Assumptions!$D$111+F8*Assumptions!$D$112+E8*Assumptions!$D$113+D8*Assumptions!$D$114) -> 0 | H11: =Assumptions!$D$10*(H8*Assumptions!$D$111+G8*Assumptions!$D$112+F8*Assumptions!$D$113+E8*Assumptions!$D$114+D8*Assumptions!$D$115) -> 6 | I11: =Assumptions!$D$10*(I8*Assumptions!$D$111+H8*Assumptions!$D$112+G8*Assumptions!$D$113+F8*Assumptions!$D$114+E8*Assumptions!$D$115+D8*Assumptions!$D$116) -> 5.28 | J11: =Assumptions!$D$10*(J8*Assumptions!$D$111+I8*Assumptions!$D$112+H8*Assumptions!$D$113+G8*Assumptions!$D$114+F8*Assumptions!$D$115+E8*Assumptions!$D$116+D8*Assumptions!$D$117) -> 3.6 | K11: =Assumptions!$D$10*(K8*Assumptions!$D$111+J8*Assumptions!$D$112+I8*Assumptions!$D$113+H8*Assumptions!$D$114+G8*Assumptions!$D$115+F8*Assumptions!$D$116+E8*Assumptions!$D$117+D8*Assumptions!$D$118) -> 2.4 | L11: =Assumptions!$D$10*(L8*Assumptions!$D$111+K8*Assumptions!$D$112+J8*Assumptions!$D$113+I8*Assumptions!$D$114+H8*Assumptions!$D$115+G8*Assumptions!$D$116+F8*Assumptions!$D$117+E8*Assumptions!$D$118+D8*Assumptions!$D$119) -> 1.44 | M11: =Assumptions!$D$10*(M8*Assumptions!$D$111+L8*Assumptions!$D$112+K8*Assumptions!$D$113+J8*Assumptions!$D$114+I8*Assumptions!$D$115+H8*Assumptions!$D$116+G8*Assumptions!$D$117+F8*Assumptions!$D$118+E8*Assumptions!$D$119+D8*Assumptions!$D$120) -> 1.2 | N11: =Assumptions!$D$10*(N8*Assumptions!$D$111+M8*Assumptions!$D$112+L8*Assumptions!$D$113+K8*Assumptions!$D$114+J8*Assumptions!$D$115+I8*Assumptions!$D$116+H8*Assumptions!$D$117+G8*Assumptions!$D$118+F8*Assumptions!$D$119+E8*Assumptions!$D$120+D8*Assumptions!$D$121) -> 6.24 | O11: =Assumptions!$D$10*(O8*Assumptions!$D$111+N8*Assumptions!$D$112+M8*Assumptions!$D$113+L8*Assumptions!$D$114+K8*Assumptions!$D$115+J8*Assumptions!$D$116+I8*Assumptions!$D$117+H8*Assumptions!$D$118+G8*Assumptions!$D$119+F8*Assumptions!$D$120+E8*Assumptions!$D$121+D8*Assumptions!$D$122) -> 5.52 | P11: =Assumptions!$D$10*(P8*Assumptions!$D$111+O8*Assumptions!$D$112+N8*Assumptions!$D$113+M8*Assumptions!$D$114+L8*Assumptions!$D$115+K8*Assumptions!$D$116+J8*Assumptions!$D$117+I8*Assumptions!$D$118+H8*Assumptions!$D$119+G8*Assumptions!$D$120+F8*Assumptions!$D$121+E8*Assumptions!$D$122+D8*Assumptions!$D$123) -> 3.84 | Q11: =Assumptions!$D$10*(Q8*Assumptions!$D$111+P8*Assumptions!$D$112+O8*Assumptions!$D$113+N8*Assumptions!$D$114+M8*Assumptions!$D$115+L8*Assumptions!$D$116+K8*Assumptions!$D$117+J8*Assumptions!$D$118+I8*Assumptions!$D$119+H8*Assumptions!$D$120+G8*Assumptions!$D$121+F8*Assumptions!$D$122+E8*Assumptions!$D$123+D8*Assumptions!$D$124) -> 8.64 | R11: =Assumptions!$D$10*(R8*Assumptions!$D$111+Q8*Assumptions!$D$112+P8*Assumptions!$D$113+O8*Assumptions!$D$114+N8*Assumptions!$D$115+M8*Assumptions!$D$116+L8*Assumptions!$D$117+K8*Assumptions!$D$118+J8*Assumptions!$D$119+I8*Assumptions!$D$120+H8*Assumptions!$D$121+G8*Assumptions!$D$122+F8*Assumptions!$D$123+E8*Assumptions!$D$124+D8*Assumptions!$D$125) -> 6.96 | S11: =Assumptions!$D$10*(S8*Assumptions!$D$111+R8*Assumptions!$D$112+Q8*Assumptions!$D$113+P8*Assumptions!$D$114+O8*Assumptions!$D$115+N8*Assumptions!$D$116+M8*Assumptions!$D$117+L8*Assumptions!$D$118+K8*Assumptions!$D$119+J8*Assumptions!$D$120+I8*Assumptions!$D$121+H8*Assumptions!$D$122+G8*Assumptions!$D$123+F8*Assumptions!$D$124+E8*Assumptions!$D$125+D8*Assumptions!$D$126) -> 5.04 | T11: =Assumptions!$D$10*(T8*Assumptions!$D$111+S8*Assumptions!$D$112+R8*Assumptions!$D$113+Q8*Assumptions!$D$114+P8*Assumptions!$D$115+O8*Assumptions!$D$116+N8*Assumptions!$D$117+M8*Assumptions!$D$118+L8*Assumptions!$D$119+K8*Assumptions!$D$120+J8*Assumptions!$D$121+I8*Assumptions!$D$122+H8*Assumptions!$D$123+G8*Assumptions!$D$124+F8*Assumptions!$D$125+E8*Assumptions!$D$126+D8*Assumptions!$D$127) -> 8.88 | U11: =Assumptions!$D$10*(U8*Assumptions!$D$111+T8*Assumptions!$D$112+S8*Assumptions!$D$113+R8*Assumptions!$D$114+Q8*Assumptions!$D$115+P8*Assumptions!$D$116+O8*Assumptions!$D$117+N8*Assumptions!$D$118+M8*Assumptions!$D$119+L8*Assumptions!$D$120+K8*Assumptions!$D$121+J8*Assumptions!$D$122+I8*Assumptions!$D$123+H8*Assumptions!$D$124+G8*Assumptions!$D$125+F8*Assumptions!$D$126+E8*Assumptions!$D$127+D8*Assumptions!$D$128) -> 13.2 | V11: =Assumptions!$D$10*(V8*Assumptions!$D$111+U8*Assumptions!$D$112+T8*Assumptions!$D$113+S8*Assumptions!$D$114+R8*Assumptions!$D$115+Q8*Assumptions!$D$116+P8*Assumptions!$D$117+O8*Assumptions!$D$118+N8*Assumptions!$D$119+M8*Assumptions!$D$120+L8*Assumptions!$D$121+K8*Assumptions!$D$122+J8*Assumptions!$D$123+I8*Assumptions!$D$124+H8*Assumptions!$D$125+G8*Assumptions!$D$126+F8*Assumptions!$D$127+E8*Assumptions!$D$128+D8*Assumptions!$D$129) -> 10.56 | W11: =Assumptions!$D$10*(W8*Assumptions!$D$111+V8*Assumptions!$D$112+U8*Assumptions!$D$113+T8*Assumptions!$D$114+S8*Assumptions!$D$115+R8*Assumptions!$D$116+Q8*Assumptions!$D$117+P8*Assumptions!$D$118+O8*Assumptions!$D$119+N8*Assumptions!$D$120+M8*Assumptions!$D$121+L8*Assumptions!$D$122+K8*Assumptions!$D$123+J8*Assumptions!$D$124+I8*Assumptions!$D$125+H8*Assumptions!$D$126+G8*Assumptions!$D$127+F8*Assumptions!$D$128+E8*Assumptions!$D$129+D8*Assumptions!$D$130) -> 12.72 | X11: =Assumptions!$D$10*(X8*Assumptions!$D$111+W8*Assumptions!$D$112+V8*Assumptions!$D$113+U8*Assumptions!$D$114+T8*Assumptions!$D$115+S8*Assumptions!$D$116+R8*Assumptions!$D$117+Q8*Assumptions!$D$118+P8*Assumptions!$D$119+O8*Assumptions!$D$120+N8*Assumptions!$D$121+M8*Assumptions!$D$122+L8*Assumptions!$D$123+K8*Assumptions!$D$124+J8*Assumptions!$D$125+I8*Assumptions!$D$126+H8*Assumptions!$D$127+G8*Assumptions!$D$128+F8*Assumptions!$D$129+E8*Assumptions!$D$130+D8*Assumptions!$D$131) -> 15.84 | Y11: =Assumptions!$D$10*(Y8*Assumptions!$D$111+X8*Assumptions!$D$112+W8*Assumptions!$D$113+V8*Assumptions!$D$114+U8*Assumptions!$D$115+T8*Assumptions!$D$116+S8*Assumptions!$D$117+R8*Assumptions!$D$118+Q8*Assumptions!$D$119+P8*Assumptions!$D$120+O8*Assumptions!$D$121+N8*Assumptions!$D$122+M8*Assumptions!$D$123+L8*Assumptions!$D$124+K8*Assumptions!$D$125+J8*Assumptions!$D$126+I8*Assumptions!$D$127+H8*Assumptions!$D$128+G8*Assumptions!$D$129+F8*Assumptions!$D$130+E8*Assumptions!$D$131+D8*Assumptions!$D$132) -> 12.24 | Z11: =Assumptions!$D$10*(Z8*Assumptions!$D$111+Y8*Assumptions!$D$112+X8*Assumptions!$D$113+W8*Assumptions!$D$114+V8*Assumptions!$D$115+U8*Assumptions!$D$116+T8*Assumptions!$D$117+S8*Assumptions!$D$118+R8*Assumptions!$D$119+Q8*Assumptions!$D$120+P8*Assumptions!$D$121+O8*Assumptions!$D$122+N8*Assumptions!$D$123+M8*Assumptions!$D$124+L8*Assumptions!$D$125+K8*Assumptions!$D$126+J8*Assumptions!$D$127+I8*Assumptions!$D$128+H8*Assumptions!$D$129+G8*Assumptions!$D$130+F8*Assumptions!$D$131+E8*Assumptions!$D$132+D8*Assumptions!$D$133) -> 14.16 | AA11: =Assumptions!$D$10*(AA8*Assumptions!$D$111+Z8*Assumptions!$D$112+Y8*Assumptions!$D$113+X8*Assumptions!$D$114+W8*Assumptions!$D$115+V8*Assumptions!$D$116+U8*Assumptions!$D$117+T8*Assumptions!$D$118+S8*Assumptions!$D$119+R8*Assumptions!$D$120+Q8*Assumptions!$D$121+P8*Assumptions!$D$122+O8*Assumptions!$D$123+N8*Assumptions!$D$124+M8*Assumptions!$D$125+L8*Assumptions!$D$126+K8*Assumptions!$D$127+J8*Assumptions!$D$128+I8*Assumptions!$D$129+H8*Assumptions!$D$130+G8*Assumptions!$D$131+F8*Assumptions!$D$132+E8*Assumptions!$D$133) -> 16.32 | AB11: =Assumptions!$D$10*(AB8*Assumptions!$D$111+AA8*Assumptions!$D$112+Z8*Assumptions!$D$113+Y8*Assumptions!$D$114+X8*Assumptions!$D$115+W8*Assumptions!$D$116+V8*Assumptions!$D$117+U8*Assumptions!$D$118+T8*Assumptions!$D$119+S8*Assumptions!$D$120+R8*Assumptions!$D$121+Q8*Assumptions!$D$122+P8*Assumptions!$D$123+O8*Assumptions!$D$124+N8*Assumptions!$D$125+M8*Assumptions!$D$126+L8*Assumptions!$D$127+K8*Assumptions!$D$128+J8*Assumptions!$D$129+I8*Assumptions!$D$130+H8*Assumptions!$D$131+G8*Assumptions!$D$132+F8*Assumptions!$D$133) -> 12.72 | AC11: =Assumptions!$D$10*(AC8*Assumptions!$D$111+AB8*Assumptions!$D$112+AA8*Assumptions!$D$113+Z8*Assumptions!$D$114+Y8*Assumptions!$D$115+X8*Assumptions!$D$116+W8*Assumptions!$D$117+V8*Assumptions!$D$118+U8*Assumptions!$D$119+T8*Assumptions!$D$120+S8*Assumptions!$D$121+R8*Assumptions!$D$122+Q8*Assumptions!$D$123+P8*Assumptions!$D$124+O8*Assumptions!$D$125+N8*Assumptions!$D$126+M8*Assumptions!$D$127+L8*Assumptions!$D$128+K8*Assumptions!$D$129+J8*Assumptions!$D$130+I8*Assumptions!$D$131+H8*Assumptions!$D$132+G8*Assumptions!$D$133) -> 14.64 | AD11: =Assumptions!$D$10*(AD8*Assumptions!$D$111+AC8*Assumptions!$D$112+AB8*Assumptions!$D$113+AA8*Assumptions!$D$114+Z8*Assumptions!$D$115+Y8*Assumptions!$D$116+X8*Assumptions!$D$117+W8*Assumptions!$D$118+V8*Assumptions!$D$119+U8*Assumptions!$D$120+T8*Assumptions!$D$121+S8*Assumptions!$D$122+R8*Assumptions!$D$123+Q8*Assumptions!$D$124+P8*Assumptions!$D$125+O8*Assumptions!$D$126+N8*Assumptions!$D$127+M8*Assumptions!$D$128+L8*Assumptions!$D$129+K8*Assumptions!$D$130+J8*Assumptions!$D$131+I8*Assumptions!$D$132+H8*Assumptions!$D$133) -> 16.8 | AE11: =Assumptions!$D$10*(AE8*Assumptions!$D$111+AD8*Assumptions!$D$112+AC8*Assumptions!$D$113+AB8*Assumptions!$D$114+AA8*Assumptions!$D$115+Z8*Assumptions!$D$116+Y8*Assumptions!$D$117+X8*Assumptions!$D$118+W8*Assumptions!$D$119+V8*Assumptions!$D$120+U8*Assumptions!$D$121+T8*Assumptions!$D$122+S8*Assumptions!$D$123+R8*Assumptions!$D$124+Q8*Assumptions!$D$125+P8*Assumptions!$D$126+O8*Assumptions!$D$127+N8*Assumptions!$D$128+M8*Assumptions!$D$129+L8*Assumptions!$D$130+K8*Assumptions!$D$131+J8*Assumptions!$D$132+I8*Assumptions!$D$133) -> 18.96 | AF11: =Assumptions!$D$10*(AF8*Assumptions!$D$111+AE8*Assumptions!$D$112+AD8*Assumptions!$D$113+AC8*Assumptions!$D$114+AB8*Assumptions!$D$115+AA8*Assumptions!$D$116+Z8*Assumptions!$D$117+Y8*Assumptions!$D$118+X8*Assumptions!$D$119+W8*Assumptions!$D$120+V8*Assumptions!$D$121+U8*Assumptions!$D$122+T8*Assumptions!$D$123+S8*Assumptions!$D$124+R8*Assumptions!$D$125+Q8*Assumptions!$D$126+P8*Assumptions!$D$127+O8*Assumptions!$D$128+N8*Assumptions!$D$129+M8*Assumptions!$D$130+L8*Assumptions!$D$131+K8*Assumptions!$D$132+J8*Assumptions!$D$133) -> 20.16 | AG11: =Assumptions!$D$10*(AG8*Assumptions!$D$111+AF8*Assumptions!$D$112+AE8*Assumptions!$D$113+AD8*Assumptions!$D$114+AC8*Assumptions!$D$115+AB8*Assumptions!$D$116+AA8*Assumptions!$D$117+Z8*Assumptions!$D$118+Y8*Assumptions!$D$119+X8*Assumptions!$D$120+W8*Assumptions!$D$121+V8*Assumptions!$D$122+U8*Assumptions!$D$123+T8*Assumptions!$D$124+S8*Assumptions!$D$125+R8*Assumptions!$D$126+Q8*Assumptions!$D$127+P8*Assumptions!$D$128+O8*Assumptions!$D$129+N8*Assumptions!$D$130+M8*Assumptions!$D$131+L8*Assumptions!$D$132+K8*Assumptions!$D$133) -> 20.64 | ... BK11: =Assumptions!$D$10*(BK8*Assumptions!$D$111+BJ8*Assumptions!$D$112+BI8*Assumptions!$D$113+BH8*Assumptions!$D$114+BG8*Assumptions!$D$115+BF8*Assumptions!$D$116+BE8*Assumptions!$D$117+BD8*Assumptions!$D$118+BC8*Assumptions!$D$119+BB8*Assumptions!$D$120+BA8*Assumptions!$D$121+AZ8*Assumptions!$D$122+AY8*Assumptions!$D$123+AX8*Assumptions!$D$124+AW8*Assumptions!$D$125+AV8*Assumptions!$D$126+AU8*Assumptions!$D$127+AT8*Assumptions!$D$128+AS8*Assumptions!$D$129+AR8*Assumptions!$D$130+AQ8*Assumptions!$D$131+AP8*Assumptions!$D$132+AO8*Assumptions!$D$133) -> 24
A12: network_merchants | B12: Network merchants (signed, net of churn) | C12: 0 | D12: =C12*(1-Assumptions!$D$12)+D11 -> 0 | E12: =D12*(1-Assumptions!$D$12)+E11 -> 0 | F12: =E12*(1-Assumptions!$D$12)+F11 -> 0 | G12: =F12*(1-Assumptions!$D$12)+G11 -> 0 | H12: =G12*(1-Assumptions!$D$12)+H11 -> 6 | I12: =H12*(1-Assumptions!$D$12)+I11 -> 11.13 | J12: =I12*(1-Assumptions!$D$12)+J11 -> 14.45175 | K12: =J12*(1-Assumptions!$D$12)+K11 -> 16.490456 | ... BK12: =BJ12*(1-Assumptions!$D$12)+BK11 -> 602.69342
A13: active_merchants | B13: Active merchants (>= 25 active members) | C13: 0 | D13: =D12*Assumptions!$D$11 -> 0 | E13: =E12*Assumptions!$D$11 -> 0 | F13: =F12*Assumptions!$D$11 -> 0 | G13: =G12*Assumptions!$D$11 -> 0 | H13: =H12*Assumptions!$D$11 -> 3 | I13: =I12*Assumptions!$D$11 -> 5.565 | J13: =J12*Assumptions!$D$11 -> 7.225875 | K13: =K12*Assumptions!$D$11 -> 8.2452281 | ... BK13: =BK12*Assumptions!$D$11 -> 301.34671
A14: activated_new | B14: Newly activated merchants | C14: 0 | D14: =D11*Assumptions!$D$11 -> 0 | E14: =E11*Assumptions!$D$11 -> 0 | F14: =F11*Assumptions!$D$11 -> 0 | G14: =G11*Assumptions!$D$11 -> 0 | H14: =H11*Assumptions!$D$11 -> 3 | I14: =I11*Assumptions!$D$11 -> 2.64 | J14: =J11*Assumptions!$D$11 -> 1.8 | K14: =K11*Assumptions!$D$11 -> 1.2 | ... BK14: =BK11*Assumptions!$D$11 -> 12
B15: Rollout gates (1 = unlocked; plans.ts unlockAtMerchants)
A16: plus_unlocked | B16: Plus features GA | C16: 0 | D16: =IF(OR(C16=1,AND(D13>=Assumptions!$D$18,D7>=Assumptions!$D$19)),1,0) -> 0 | E16: =IF(OR(D16=1,AND(E13>=Assumptions!$D$18,E7>=Assumptions!$D$19)),1,0) -> 0 | F16: =IF(OR(E16=1,AND(F13>=Assumptions!$D$18,F7>=Assumptions!$D$19)),1,0) -> 0 | G16: =IF(OR(F16=1,AND(G13>=Assumptions!$D$18,G7>=Assumptions!$D$19)),1,0) -> 0 | H16: =IF(OR(G16=1,AND(H13>=Assumptions!$D$18,H7>=Assumptions!$D$19)),1,0) -> 0 | I16: =IF(OR(H16=1,AND(I13>=Assumptions!$D$18,I7>=Assumptions!$D$19)),1,0) -> 0 | J16: =IF(OR(I16=1,AND(J13>=Assumptions!$D$18,J7>=Assumptions!$D$19)),1,0) -> 0 | K16: =IF(OR(J16=1,AND(K13>=Assumptions!$D$18,K7>=Assumptions!$D$19)),1,0) -> 0 | ... BK16: =IF(OR(BJ16=1,AND(BK13>=Assumptions!$D$18,BK7>=Assumptions!$D$19)),1,0) -> 1
A17: pro_unlocked | B17: Pro features GA | C17: 0 | D17: =IF(OR(C17=1,AND(D13>=Assumptions!$D$20,D7>=Assumptions!$D$21)),1,0) -> 0 | E17: =IF(OR(D17=1,AND(E13>=Assumptions!$D$20,E7>=Assumptions!$D$21)),1,0) -> 0 | F17: =IF(OR(E17=1,AND(F13>=Assumptions!$D$20,F7>=Assumptions!$D$21)),1,0) -> 0 | G17: =IF(OR(F17=1,AND(G13>=Assumptions!$D$20,G7>=Assumptions!$D$21)),1,0) -> 0 | H17: =IF(OR(G17=1,AND(H13>=Assumptions!$D$20,H7>=Assumptions!$D$21)),1,0) -> 0 | I17: =IF(OR(H17=1,AND(I13>=Assumptions!$D$20,I7>=Assumptions!$D$21)),1,0) -> 0 | J17: =IF(OR(I17=1,AND(J13>=Assumptions!$D$20,J7>=Assumptions!$D$21)),1,0) -> 0 | K17: =IF(OR(J17=1,AND(K13>=Assumptions!$D$20,K7>=Assumptions!$D$21)),1,0) -> 0 | ... BK17: =IF(OR(BJ17=1,AND(BK13>=Assumptions!$D$20,BK7>=Assumptions!$D$21)),1,0) -> 1
A18: bia_unlocked | B18: BIA campaigns available | C18: 0 | D18: =IF(OR(C18=1,D13>=Assumptions!$D$22),1,0) -> 0 | E18: =IF(OR(D18=1,E13>=Assumptions!$D$22),1,0) -> 0 | F18: =IF(OR(E18=1,F13>=Assumptions!$D$22),1,0) -> 0 | G18: =IF(OR(F18=1,G13>=Assumptions!$D$22),1,0) -> 0 | H18: =IF(OR(G18=1,H13>=Assumptions!$D$22),1,0) -> 0 | I18: =IF(OR(H18=1,I13>=Assumptions!$D$22),1,0) -> 0 | J18: =IF(OR(I18=1,J13>=Assumptions!$D$22),1,0) -> 0 | K18: =IF(OR(J18=1,K13>=Assumptions!$D$22),1,0) -> 0 | ... BK18: =IF(OR(BJ18=1,BK13>=Assumptions!$D$22),1,0) -> 1
A19: ads_unlocked | B19: Ads available | C19: 0 | D19: =IF(OR(C19=1,AND(D13>=Assumptions!$D$23,D7>=Assumptions!$D$24)),1,0) -> 0 | E19: =IF(OR(D19=1,AND(E13>=Assumptions!$D$23,E7>=Assumptions!$D$24)),1,0) -> 0 | F19: =IF(OR(E19=1,AND(F13>=Assumptions!$D$23,F7>=Assumptions!$D$24)),1,0) -> 0 | G19: =IF(OR(F19=1,AND(G13>=Assumptions!$D$23,G7>=Assumptions!$D$24)),1,0) -> 0 | H19: =IF(OR(G19=1,AND(H13>=Assumptions!$D$23,H7>=Assumptions!$D$24)),1,0) -> 0 | I19: =IF(OR(H19=1,AND(I13>=Assumptions!$D$23,I7>=Assumptions!$D$24)),1,0) -> 0 | J19: =IF(OR(I19=1,AND(J13>=Assumptions!$D$23,J7>=Assumptions!$D$24)),1,0) -> 0 | K19: =IF(OR(J19=1,AND(K13>=Assumptions!$D$23,K7>=Assumptions!$D$24)),1,0) -> 0 | ... BK19: =IF(OR(BJ19=1,AND(BK13>=Assumptions!$D$23,BK7>=Assumptions!$D$24)),1,0) -> 0
A20: ads_months | B20: Months since ads unlocked | C20: 0 | D20: =IF(D19=1,C20+1,0) -> 0 | E20: =IF(E19=1,D20+1,0) -> 0 | F20: =IF(F19=1,E20+1,0) -> 0 | G20: =IF(G19=1,F20+1,0) -> 0 | H20: =IF(H19=1,G20+1,0) -> 0 | I20: =IF(I19=1,H20+1,0) -> 0 | J20: =IF(J19=1,I20+1,0) -> 0 | K20: =IF(K19=1,J20+1,0) -> 0 | ... BK20: =IF(BK19=1,BJ20+1,0) -> 0
A21: ads_ramp | B21: Ad demand ramp | C21: 0 | D21: =MIN(1,D20/Assumptions!$D$77) -> 0 | E21: =MIN(1,E20/Assumptions!$D$77) -> 0 | F21: =MIN(1,F20/Assumptions!$D$77) -> 0 | G21: =MIN(1,G20/Assumptions!$D$77) -> 0 | H21: =MIN(1,H20/Assumptions!$D$77) -> 0 | I21: =MIN(1,I20/Assumptions!$D$77) -> 0 | J21: =MIN(1,J20/Assumptions!$D$77) -> 0 | K21: =MIN(1,K20/Assumptions!$D$77) -> 0 | ... BK21: =MIN(1,BK20/Assumptions!$D$77) -> 0
B22: Customers
A23: memberships | B23: Memberships (customer-shop pairs) | C23: 0 | D23: =C23+(D13*Assumptions!$D$13-C23)*Assumptions!$D$14 -> 0 | E23: =D23+(E13*Assumptions!$D$13-D23)*Assumptions!$D$14 -> 0 | F23: =E23+(F13*Assumptions!$D$13-E23)*Assumptions!$D$14 -> 0 | G23: =F23+(G13*Assumptions!$D$13-F23)*Assumptions!$D$14 -> 0 | H23: =G23+(H13*Assumptions!$D$13-G23)*Assumptions!$D$14 -> 52.5 | I23: =H23+(I13*Assumptions!$D$13-H23)*Assumptions!$D$14 -> 131.5125 | J23: =I23+(J13*Assumptions!$D$13-I23)*Assumptions!$D$14 -> 211.93594 | K23: =J23+(K13*Assumptions!$D$13-J23)*Assumptions!$D$14 -> 282.04985 | ... BK23: =BJ23+(BK13*Assumptions!$D$13-BJ23)*Assumptions!$D$14 -> 14620.765
A24: active_customers | B24: Active customers (unique) | C24: 0 | D24: =D23/Assumptions!$D$15 -> 0 | E24: =E23/Assumptions!$D$15 -> 0 | F24: =F23/Assumptions!$D$15 -> 0 | G24: =G23/Assumptions!$D$15 -> 0 | H24: =H23/Assumptions!$D$15 -> 37.5 | I24: =I23/Assumptions!$D$15 -> 93.9375 | J24: =J23/Assumptions!$D$15 -> 151.38281 | K24: =K23/Assumptions!$D$15 -> 201.46418 | ... BK24: =BK23/Assumptions!$D$15 -> 10443.403
A25: new_customers | B25: New / re-acquired customers | C25: 0 | D25: =MAX(0,D24-C24)+C24*Assumptions!$D$16 -> 0 | E25: =MAX(0,E24-D24)+D24*Assumptions!$D$16 -> 0 | F25: =MAX(0,F24-E24)+E24*Assumptions!$D$16 -> 0 | G25: =MAX(0,G24-F24)+F24*Assumptions!$D$16 -> 0 | H25: =MAX(0,H24-G24)+G24*Assumptions!$D$16 -> 37.5 | I25: =MAX(0,I24-H24)+H24*Assumptions!$D$16 -> 57.9375 | J25: =MAX(0,J24-I24)+I24*Assumptions!$D$16 -> 61.202813 | K25: =MAX(0,K24-J24)+J24*Assumptions!$D$16 -> 56.13668 | ... BK25: =MAX(0,BK24-BJ24)+BJ24*Assumptions!$D$16 -> 582.62385
B26: Paying merchants by vertical (repair/auto gated by Pro, others by Plus)
A27: paid_food_bev | B27: Paying — Cafes, restaurants, bakeries | C27: 0 | D27: =C27*(1-Assumptions!$D$41)+D16*((1-(1-Assumptions!$D$30)^(1/12))*Assumptions!$D$40)*MAX(0,D13*Assumptions!$D$25-C27) -> 0 | E27: =D27*(1-Assumptions!$D$41)+E16*((1-(1-Assumptions!$D$30)^(1/12))*Assumptions!$D$40)*MAX(0,E13*Assumptions!$D$25-D27) -> 0 | F27: =E27*(1-Assumptions!$D$41)+F16*((1-(1-Assumptions!$D$30)^(1/12))*Assumptions!$D$40)*MAX(0,F13*Assumptions!$D$25-E27) -> 0 | G27: =F27*(1-Assumptions!$D$41)+G16*((1-(1-Assumptions!$D$30)^(1/12))*Assumptions!$D$40)*MAX(0,G13*Assumptions!$D$25-F27) -> 0 | H27: =G27*(1-Assumptions!$D$41)+H16*((1-(1-Assumptions!$D$30)^(1/12))*Assumptions!$D$40)*MAX(0,H13*Assumptions!$D$25-G27) -> 0 | I27: =H27*(1-Assumptions!$D$41)+I16*((1-(1-Assumptions!$D$30)^(1/12))*Assumptions!$D$40)*MAX(0,I13*Assumptions!$D$25-H27) -> 0 | J27: =I27*(1-Assumptions!$D$41)+J16*((1-(1-Assumptions!$D$30)^(1/12))*Assumptions!$D$40)*MAX(0,J13*Assumptions!$D$25-I27) -> 0 | K27: =J27*(1-Assumptions!$D$41)+K16*((1-(1-Assumptions!$D$30)^(1/12))*Assumptions!$D$40)*MAX(0,K13*Assumptions!$D$25-J27) -> 0 | ... BK27: =BJ27*(1-Assumptions!$D$41)+BK16*((1-(1-Assumptions!$D$30)^(1/12))*Assumptions!$D$40)*MAX(0,BK13*Assumptions!$D$25-BJ27) -> 13.27614
A28: paid_retail | B28: Paying — Independent retail | C28: 0 | D28: =C28*(1-Assumptions!$D$41)+D16*((1-(1-Assumptions!$D$31)^(1/12))*Assumptions!$D$40)*MAX(0,D13*Assumptions!$D$26-C28) -> 0 | E28: =D28*(1-Assumptions!$D$41)+E16*((1-(1-Assumptions!$D$31)^(1/12))*Assumptions!$D$40)*MAX(0,E13*Assumptions!$D$26-D28) -> 0 | F28: =E28*(1-Assumptions!$D$41)+F16*((1-(1-Assumptions!$D$31)^(1/12))*Assumptions!$D$40)*MAX(0,F13*Assumptions!$D$26-E28) -> 0 | G28: =F28*(1-Assumptions!$D$41)+G16*((1-(1-Assumptions!$D$31)^(1/12))*Assumptions!$D$40)*MAX(0,G13*Assumptions!$D$26-F28) -> 0 | H28: =G28*(1-Assumptions!$D$41)+H16*((1-(1-Assumptions!$D$31)^(1/12))*Assumptions!$D$40)*MAX(0,H13*Assumptions!$D$26-G28) -> 0 | I28: =H28*(1-Assumptions!$D$41)+I16*((1-(1-Assumptions!$D$31)^(1/12))*Assumptions!$D$40)*MAX(0,I13*Assumptions!$D$26-H28) -> 0 | J28: =I28*(1-Assumptions!$D$41)+J16*((1-(1-Assumptions!$D$31)^(1/12))*Assumptions!$D$40)*MAX(0,J13*Assumptions!$D$26-I28) -> 0 | K28: =J28*(1-Assumptions!$D$41)+K16*((1-(1-Assumptions!$D$31)^(1/12))*Assumptions!$D$40)*MAX(0,K13*Assumptions!$D$26-J28) -> 0 | ... BK28: =BJ28*(1-Assumptions!$D$41)+BK16*((1-(1-Assumptions!$D$31)^(1/12))*Assumptions!$D$40)*MAX(0,BK13*Assumptions!$D$26-BJ28) -> 5.6778119
A29: paid_repair_auto | B29: Paying — Repair, auto, alterations, print | C29: 0 | D29: =C29*(1-Assumptions!$D$41)+D17*((1-(1-Assumptions!$D$32)^(1/12))*Assumptions!$D$40)*MAX(0,D13*Assumptions!$D$27-C29) -> 0 | E29: =D29*(1-Assumptions!$D$41)+E17*((1-(1-Assumptions!$D$32)^(1/12))*Assumptions!$D$40)*MAX(0,E13*Assumptions!$D$27-D29) -> 0 | F29: =E29*(1-Assumptions!$D$41)+F17*((1-(1-Assumptions!$D$32)^(1/12))*Assumptions!$D$40)*MAX(0,F13*Assumptions!$D$27-E29) -> 0 | G29: =F29*(1-Assumptions!$D$41)+G17*((1-(1-Assumptions!$D$32)^(1/12))*Assumptions!$D$40)*MAX(0,G13*Assumptions!$D$27-F29) -> 0 | H29: =G29*(1-Assumptions!$D$41)+H17*((1-(1-Assumptions!$D$32)^(1/12))*Assumptions!$D$40)*MAX(0,H13*Assumptions!$D$27-G29) -> 0 | I29: =H29*(1-Assumptions!$D$41)+I17*((1-(1-Assumptions!$D$32)^(1/12))*Assumptions!$D$40)*MAX(0,I13*Assumptions!$D$27-H29) -> 0 | J29: =I29*(1-Assumptions!$D$41)+J17*((1-(1-Assumptions!$D$32)^(1/12))*Assumptions!$D$40)*MAX(0,J13*Assumptions!$D$27-I29) -> 0 | K29: =J29*(1-Assumptions!$D$41)+K17*((1-(1-Assumptions!$D$32)^(1/12))*Assumptions!$D$40)*MAX(0,K13*Assumptions!$D$27-J29) -> 0 | ... BK29: =BJ29*(1-Assumptions!$D$41)+BK17*((1-(1-Assumptions!$D$32)^(1/12))*Assumptions!$D$40)*MAX(0,BK13*Assumptions!$D$27-BJ29) -> 15.303559
A30: paid_personal_services | B30: Paying — Salons, barbers, fitness, pets | C30: 0 | D30: =C30*(1-Assumptions!$D$41)+D16*((1-(1-Assumptions!$D$33)^(1/12))*Assumptions!$D$40)*MAX(0,D13*Assumptions!$D$28-C30) -> 0 | E30: =D30*(1-Assumptions!$D$41)+E16*((1-(1-Assumptions!$D$33)^(1/12))*Assumptions!$D$40)*MAX(0,E13*Assumptions!$D$28-D30) -> 0 | F30: =E30*(1-Assumptions!$D$41)+F16*((1-(1-Assumptions!$D$33)^(1/12))*Assumptions!$D$40)*MAX(0,F13*Assumptions!$D$28-E30) -> 0 | G30: =F30*(1-Assumptions!$D$41)+G16*((1-(1-Assumptions!$D$33)^(1/12))*Assumptions!$D$40)*MAX(0,G13*Assumptions!$D$28-F30) -> 0 | H30: =G30*(1-Assumptions!$D$41)+H16*((1-(1-Assumptions!$D$33)^(1/12))*Assumptions!$D$40)*MAX(0,H13*Assumptions!$D$28-G30) -> 0 | I30: =H30*(1-Assumptions!$D$41)+I16*((1-(1-Assumptions!$D$33)^(1/12))*Assumptions!$D$40)*MAX(0,I13*Assumptions!$D$28-H30) -> 0 | J30: =I30*(1-Assumptions!$D$41)+J16*((1-(1-Assumptions!$D$33)^(1/12))*Assumptions!$D$40)*MAX(0,J13*Assumptions!$D$28-I30) -> 0 | K30: =J30*(1-Assumptions!$D$41)+K16*((1-(1-Assumptions!$D$33)^(1/12))*Assumptions!$D$40)*MAX(0,K13*Assumptions!$D$28-J30) -> 0 | ... BK30: =BJ30*(1-Assumptions!$D$41)+BK16*((1-(1-Assumptions!$D$33)^(1/12))*Assumptions!$D$40)*MAX(0,BK13*Assumptions!$D$28-BJ30) -> 3.409138
A31: paid_pharmacy | B31: Paying — Independent pharmacies (front store only) | C31: 0 | D31: =C31*(1-Assumptions!$D$41)+D16*((1-(1-Assumptions!$D$34)^(1/12))*Assumptions!$D$40)*MAX(0,D13*Assumptions!$D$29-C31) -> 0 | E31: =D31*(1-Assumptions!$D$41)+E16*((1-(1-Assumptions!$D$34)^(1/12))*Assumptions!$D$40)*MAX(0,E13*Assumptions!$D$29-D31) -> 0 | F31: =E31*(1-Assumptions!$D$41)+F16*((1-(1-Assumptions!$D$34)^(1/12))*Assumptions!$D$40)*MAX(0,F13*Assumptions!$D$29-E31) -> 0 | G31: =F31*(1-Assumptions!$D$41)+G16*((1-(1-Assumptions!$D$34)^(1/12))*Assumptions!$D$40)*MAX(0,G13*Assumptions!$D$29-F31) -> 0 | H31: =G31*(1-Assumptions!$D$41)+H16*((1-(1-Assumptions!$D$34)^(1/12))*Assumptions!$D$40)*MAX(0,H13*Assumptions!$D$29-G31) -> 0 | I31: =H31*(1-Assumptions!$D$41)+I16*((1-(1-Assumptions!$D$34)^(1/12))*Assumptions!$D$40)*MAX(0,I13*Assumptions!$D$29-H31) -> 0 | J31: =I31*(1-Assumptions!$D$41)+J16*((1-(1-Assumptions!$D$34)^(1/12))*Assumptions!$D$40)*MAX(0,J13*Assumptions!$D$29-I31) -> 0 | K31: =J31*(1-Assumptions!$D$41)+K16*((1-(1-Assumptions!$D$34)^(1/12))*Assumptions!$D$40)*MAX(0,K13*Assumptions!$D$29-J31) -> 0 | ... BK31: =BJ31*(1-Assumptions!$D$41)+BK16*((1-(1-Assumptions!$D$34)^(1/12))*Assumptions!$D$40)*MAX(0,BK13*Assumptions!$D$29-BJ31) -> 0.75599071
A32: paid_total | B32: Paying merchants (total) | C32: 0 | D32: =D27+D28+D29+D30+D31 -> 0 | E32: =E27+E28+E29+E30+E31 -> 0 | F32: =F27+F28+F29+F30+F31 -> 0 | G32: =G27+G28+G29+G30+G31 -> 0 | H32: =H27+H28+H29+H30+H31 -> 0 | I32: =I27+I28+I29+I30+I31 -> 0 | J32: =J27+J28+J29+J30+J31 -> 0 | K32: =K27+K28+K29+K30+K31 -> 0 | ... BK32: =BK27+BK28+BK29+BK30+BK31 -> 38.42264
A33: plus_merchants | B33: Plus merchants | D33: =D27*(1-Assumptions!$D$35)+D28*(1-Assumptions!$D$36)+D29*(1-Assumptions!$D$37)+D30*(1-Assumptions!$D$38)+D31*(1-Assumptions!$D$39) -> 0 | E33: =E27*(1-Assumptions!$D$35)+E28*(1-Assumptions!$D$36)+E29*(1-Assumptions!$D$37)+E30*(1-Assumptions!$D$38)+E31*(1-Assumptions!$D$39) -> 0 | F33: =F27*(1-Assumptions!$D$35)+F28*(1-Assumptions!$D$36)+F29*(1-Assumptions!$D$37)+F30*(1-Assumptions!$D$38)+F31*(1-Assumptions!$D$39) -> 0 | G33: =G27*(1-Assumptions!$D$35)+G28*(1-Assumptions!$D$36)+G29*(1-Assumptions!$D$37)+G30*(1-Assumptions!$D$38)+G31*(1-Assumptions!$D$39) -> 0 | H33: =H27*(1-Assumptions!$D$35)+H28*(1-Assumptions!$D$36)+H29*(1-Assumptions!$D$37)+H30*(1-Assumptions!$D$38)+H31*(1-Assumptions!$D$39) -> 0 | I33: =I27*(1-Assumptions!$D$35)+I28*(1-Assumptions!$D$36)+I29*(1-Assumptions!$D$37)+I30*(1-Assumptions!$D$38)+I31*(1-Assumptions!$D$39) -> 0 | J33: =J27*(1-Assumptions!$D$35)+J28*(1-Assumptions!$D$36)+J29*(1-Assumptions!$D$37)+J30*(1-Assumptions!$D$38)+J31*(1-Assumptions!$D$39) -> 0 | K33: =K27*(1-Assumptions!$D$35)+K28*(1-Assumptions!$D$36)+K29*(1-Assumptions!$D$37)+K30*(1-Assumptions!$D$38)+K31*(1-Assumptions!$D$39) -> 0 | ... BK33: =BK27*(1-Assumptions!$D$35)+BK28*(1-Assumptions!$D$36)+BK29*(1-Assumptions!$D$37)+BK30*(1-Assumptions!$D$38)+BK31*(1-Assumptions!$D$39) -> 23.444176
A34: pro_merchants | B34: Pro merchants | D34: =D27*Assumptions!$D$35+D28*Assumptions!$D$36+D29*Assumptions!$D$37+D30*Assumptions!$D$38+D31*Assumptions!$D$39 -> 0 | E34: =E27*Assumptions!$D$35+E28*Assumptions!$D$36+E29*Assumptions!$D$37+E30*Assumptions!$D$38+E31*Assumptions!$D$39 -> 0 | F34: =F27*Assumptions!$D$35+F28*Assumptions!$D$36+F29*Assumptions!$D$37+F30*Assumptions!$D$38+F31*Assumptions!$D$39 -> 0 | G34: =G27*Assumptions!$D$35+G28*Assumptions!$D$36+G29*Assumptions!$D$37+G30*Assumptions!$D$38+G31*Assumptions!$D$39 -> 0 | H34: =H27*Assumptions!$D$35+H28*Assumptions!$D$36+H29*Assumptions!$D$37+H30*Assumptions!$D$38+H31*Assumptions!$D$39 -> 0 | I34: =I27*Assumptions!$D$35+I28*Assumptions!$D$36+I29*Assumptions!$D$37+I30*Assumptions!$D$38+I31*Assumptions!$D$39 -> 0 | J34: =J27*Assumptions!$D$35+J28*Assumptions!$D$36+J29*Assumptions!$D$37+J30*Assumptions!$D$38+J31*Assumptions!$D$39 -> 0 | K34: =K27*Assumptions!$D$35+K28*Assumptions!$D$36+K29*Assumptions!$D$37+K30*Assumptions!$D$38+K31*Assumptions!$D$39 -> 0 | ... BK34: =BK27*Assumptions!$D$35+BK28*Assumptions!$D$36+BK29*Assumptions!$D$37+BK30*Assumptions!$D$38+BK31*Assumptions!$D$39 -> 14.978464
A35: new_conversions | B35: New paid conversions | D35: =MAX(0,D32-C32*(1-Assumptions!$D$41)) -> 0 | E35: =MAX(0,E32-D32*(1-Assumptions!$D$41)) -> 0 | F35: =MAX(0,F32-E32*(1-Assumptions!$D$41)) -> 0 | G35: =MAX(0,G32-F32*(1-Assumptions!$D$41)) -> 0 | H35: =MAX(0,H32-G32*(1-Assumptions!$D$41)) -> 0 | I35: =MAX(0,I32-H32*(1-Assumptions!$D$41)) -> 0 | J35: =MAX(0,J32-I32*(1-Assumptions!$D$41)) -> 0 | K35: =MAX(0,K32-J32*(1-Assumptions!$D$41)) -> 0 | ... BK35: =MAX(0,BK32-BJ32*(1-Assumptions!$D$41)) -> 2.9294255
B36: Revenue (CAD)
A37: rev_plus | B37: Plus subscriptions | D37: =D33*Assumptions!$D$42 -> 0 | E37: =E33*Assumptions!$D$42 -> 0 | F37: =F33*Assumptions!$D$42 -> 0 | G37: =G33*Assumptions!$D$42 -> 0 | H37: =H33*Assumptions!$D$42 -> 0 | I37: =I33*Assumptions!$D$42 -> 0 | J37: =J33*Assumptions!$D$42 -> 0 | K37: =K33*Assumptions!$D$42 -> 0 | ... BK37: =BK33*Assumptions!$D$42 -> 914.32285
A38: rev_pro | B38: Pro subscriptions | D38: =D34*Assumptions!$D$43 -> 0 | E38: =E34*Assumptions!$D$43 -> 0 | F38: =F34*Assumptions!$D$43 -> 0 | G38: =G34*Assumptions!$D$43 -> 0 | H38: =H34*Assumptions!$D$43 -> 0 | I38: =I34*Assumptions!$D$43 -> 0 | J38: =J34*Assumptions!$D$43 -> 0 | K38: =K34*Assumptions!$D$43 -> 0 | ... BK38: =BK34*Assumptions!$D$43 -> 1183.2986
A39: gmv_in_app | B39: In-app payment volume (GMV) | D39: =(D33*Assumptions!$D$46+D34*Assumptions!$D$47)*Assumptions!$D$45 -> 0 | E39: =(E33*Assumptions!$D$46+E34*Assumptions!$D$47)*Assumptions!$D$45 -> 0 | F39: =(F33*Assumptions!$D$46+F34*Assumptions!$D$47)*Assumptions!$D$45 -> 0 | G39: =(G33*Assumptions!$D$46+G34*Assumptions!$D$47)*Assumptions!$D$45 -> 0 | H39: =(H33*Assumptions!$D$46+H34*Assumptions!$D$47)*Assumptions!$D$45 -> 0 | I39: =(I33*Assumptions!$D$46+I34*Assumptions!$D$47)*Assumptions!$D$45 -> 0 | J39: =(J33*Assumptions!$D$46+J34*Assumptions!$D$47)*Assumptions!$D$45 -> 0 | K39: =(K33*Assumptions!$D$46+K34*Assumptions!$D$47)*Assumptions!$D$45 -> 0 | ... BK39: =(BK33*Assumptions!$D$46+BK34*Assumptions!$D$47)*Assumptions!$D$45 -> 59392.489
A40: rev_payments | B40: Platform fee on payments (0.75%) | D40: =D39*Assumptions!$D$44 -> 0 | E40: =E39*Assumptions!$D$44 -> 0 | F40: =F39*Assumptions!$D$44 -> 0 | G40: =G39*Assumptions!$D$44 -> 0 | H40: =H39*Assumptions!$D$44 -> 0 | I40: =I39*Assumptions!$D$44 -> 0 | J40: =J39*Assumptions!$D$44 -> 0 | K40: =K39*Assumptions!$D$44 -> 0 | ... BK40: =BK39*Assumptions!$D$44 -> 445.44367
A41: rev_ads_impressions | B41: Sponsored listings/promos (CPM) | D41: =D24*Assumptions!$D$17*Assumptions!$D$68*Assumptions!$D$69*Assumptions!$D$70*Assumptions!$D$71/1000*D21 -> 0 | E41: =E24*Assumptions!$D$17*Assumptions!$D$68*Assumptions!$D$69*Assumptions!$D$70*Assumptions!$D$71/1000*E21 -> 0 | F41: =F24*Assumptions!$D$17*Assumptions!$D$68*Assumptions!$D$69*Assumptions!$D$70*Assumptions!$D$71/1000*F21 -> 0 | G41: =G24*Assumptions!$D$17*Assumptions!$D$68*Assumptions!$D$69*Assumptions!$D$70*Assumptions!$D$71/1000*G21 -> 0 | H41: =H24*Assumptions!$D$17*Assumptions!$D$68*Assumptions!$D$69*Assumptions!$D$70*Assumptions!$D$71/1000*H21 -> 0 | I41: =I24*Assumptions!$D$17*Assumptions!$D$68*Assumptions!$D$69*Assumptions!$D$70*Assumptions!$D$71/1000*I21 -> 0 | J41: =J24*Assumptions!$D$17*Assumptions!$D$68*Assumptions!$D$69*Assumptions!$D$70*Assumptions!$D$71/1000*J21 -> 0 | K41: =K24*Assumptions!$D$17*Assumptions!$D$68*Assumptions!$D$69*Assumptions!$D$70*Assumptions!$D$71/1000*K21 -> 0 | ... BK41: =BK24*Assumptions!$D$17*Assumptions!$D$68*Assumptions!$D$69*Assumptions!$D$70*Assumptions!$D$71/1000*BK21 -> 0
A42: rev_map_pins | B42: Featured map pins | D42: =D13*Assumptions!$D$72*Assumptions!$D$73*D21 -> 0 | E42: =E13*Assumptions!$D$72*Assumptions!$D$73*E21 -> 0 | F42: =F13*Assumptions!$D$72*Assumptions!$D$73*F21 -> 0 | G42: =G13*Assumptions!$D$72*Assumptions!$D$73*G21 -> 0 | H42: =H13*Assumptions!$D$72*Assumptions!$D$73*H21 -> 0 | I42: =I13*Assumptions!$D$72*Assumptions!$D$73*I21 -> 0 | J42: =J13*Assumptions!$D$72*Assumptions!$D$73*J21 -> 0 | K42: =K13*Assumptions!$D$72*Assumptions!$D$73*K21 -> 0 | ... BK42: =BK13*Assumptions!$D$72*Assumptions!$D$73*BK21 -> 0
A43: rev_push_boosts | B43: Nearby push boosts | D43: =D13*Assumptions!$D$74*Assumptions!$D$75*Assumptions!$D$76*D21 -> 0 | E43: =E13*Assumptions!$D$74*Assumptions!$D$75*Assumptions!$D$76*E21 -> 0 | F43: =F13*Assumptions!$D$74*Assumptions!$D$75*Assumptions!$D$76*F21 -> 0 | G43: =G13*Assumptions!$D$74*Assumptions!$D$75*Assumptions!$D$76*G21 -> 0 | H43: =H13*Assumptions!$D$74*Assumptions!$D$75*Assumptions!$D$76*H21 -> 0 | I43: =I13*Assumptions!$D$74*Assumptions!$D$75*Assumptions!$D$76*I21 -> 0 | J43: =J13*Assumptions!$D$74*Assumptions!$D$75*Assumptions!$D$76*J21 -> 0 | K43: =K13*Assumptions!$D$74*Assumptions!$D$75*Assumptions!$D$76*K21 -> 0 | ... BK43: =BK13*Assumptions!$D$74*Assumptions!$D$75*Assumptions!$D$76*BK21 -> 0
A44: bia_campaigns | B44: BIA campaigns sold (expected) | D44: =D10*Assumptions!$D$80/12*D18 -> 0 | E44: =E10*Assumptions!$D$80/12*E18 -> 0 | F44: =F10*Assumptions!$D$80/12*F18 -> 0 | G44: =G10*Assumptions!$D$80/12*G18 -> 0 | H44: =H10*Assumptions!$D$80/12*H18 -> 0 | I44: =I10*Assumptions!$D$80/12*I18 -> 0 | J44: =J10*Assumptions!$D$80/12*J18 -> 0 | K44: =K10*Assumptions!$D$80/12*K18 -> 0 | ... BK44: =BK10*Assumptions!$D$80/12*BK18 -> 1.5833333
A45: rev_bia | B45: BIA neighbourhood campaigns | D45: =D44*Assumptions!$D$81 -> 0 | E45: =E44*Assumptions!$D$81 -> 0 | F45: =F44*Assumptions!$D$81 -> 0 | G45: =G44*Assumptions!$D$81 -> 0 | H45: =H44*Assumptions!$D$81 -> 0 | I45: =I44*Assumptions!$D$81 -> 0 | J45: =J44*Assumptions!$D$81 -> 0 | K45: =K44*Assumptions!$D$81 -> 0 | ... BK45: =BK44*Assumptions!$D$81 -> 3562.5
A46: rev_total | B46: Total revenue | D46: =D37+D38+D40+D41+D42+D43+D45 -> 0 | E46: =E37+E38+E40+E41+E42+E43+E45 -> 0 | F46: =F37+F38+F40+F41+F42+F43+F45 -> 0 | G46: =G37+G38+G40+G41+G42+G43+G45 -> 0 | H46: =H37+H38+H40+H41+H42+H43+H45 -> 0 | I46: =I37+I38+I40+I41+I42+I43+I45 -> 0 | J46: =J37+J38+J40+J41+J42+J43+J45 -> 0 | K46: =K37+K38+K40+K41+K42+K43+K45 -> 0 | ... BK46: =BK37+BK38+BK40+BK41+BK42+BK43+BK45 -> 6105.5652
A47: mrr_subscriptions | B47: Subscription MRR | D47: =D37+D38 -> 0 | E47: =E37+E38 -> 0 | F47: =F37+F38 -> 0 | G47: =G37+G38 -> 0 | H47: =H37+H38 -> 0 | I47: =I37+I38 -> 0 | J47: =J37+J38 -> 0 | K47: =K37+K38 -> 0 | ... BK47: =BK37+BK38 -> 2097.6215
B48: Variable costs (CAD)
A49: cost_free_merchants | B49: Free-tier merchant cost (infra + support) | D49: =D12*(Assumptions!$D$60+Assumptions!$D$63/60*Assumptions!$D$62) -> 0 | E49: =E12*(Assumptions!$D$60+Assumptions!$D$63/60*Assumptions!$D$62) -> 0 | F49: =F12*(Assumptions!$D$60+Assumptions!$D$63/60*Assumptions!$D$62) -> 0 | G49: =G12*(Assumptions!$D$60+Assumptions!$D$63/60*Assumptions!$D$62) -> 0 | H49: =H12*(Assumptions!$D$60+Assumptions!$D$63/60*Assumptions!$D$62) -> 18.5 | I49: =I12*(Assumptions!$D$60+Assumptions!$D$63/60*Assumptions!$D$62) -> 34.3175 | J49: =J12*(Assumptions!$D$60+Assumptions!$D$63/60*Assumptions!$D$62) -> 44.559562 | K49: =K12*(Assumptions!$D$60+Assumptions!$D$63/60*Assumptions!$D$62) -> 50.845573 | ... BK49: =BK12*(Assumptions!$D$60+Assumptions!$D$63/60*Assumptions!$D$62) -> 1858.3047
A50: cost_paid_support | B50: Extra support, paying merchants | D50: =D32*Assumptions!$D$64/60*Assumptions!$D$62 -> 0 | E50: =E32*Assumptions!$D$64/60*Assumptions!$D$62 -> 0 | F50: =F32*Assumptions!$D$64/60*Assumptions!$D$62 -> 0 | G50: =G32*Assumptions!$D$64/60*Assumptions!$D$62 -> 0 | H50: =H32*Assumptions!$D$64/60*Assumptions!$D$62 -> 0 | I50: =I32*Assumptions!$D$64/60*Assumptions!$D$62 -> 0 | J50: =J32*Assumptions!$D$64/60*Assumptions!$D$62 -> 0 | K50: =K32*Assumptions!$D$64/60*Assumptions!$D$62 -> 0 | ... BK50: =BK32*Assumptions!$D$64/60*Assumptions!$D$62 -> 240.1415
A51: cost_customer_infra | B51: Customer infra | D51: =D24*Assumptions!$D$61 -> 0 | E51: =E24*Assumptions!$D$61 -> 0 | F51: =F24*Assumptions!$D$61 -> 0 | G51: =G24*Assumptions!$D$61 -> 0 | H51: =H24*Assumptions!$D$61 -> 0.375 | I51: =I24*Assumptions!$D$61 -> 0.939375 | J51: =J24*Assumptions!$D$61 -> 1.5138281 | K51: =K24*Assumptions!$D$61 -> 2.0146418 | ... BK51: =BK24*Assumptions!$D$61 -> 104.43403
A52: cost_sms | B52: SMS (Twilio) | D52: =(D33*Assumptions!$D$56+D34*Assumptions!$D$57+D25*Assumptions!$D$58+D24*Assumptions!$D$59)*Assumptions!$D$55 -> 0 | E52: =(E33*Assumptions!$D$56+E34*Assumptions!$D$57+E25*Assumptions!$D$58+E24*Assumptions!$D$59)*Assumptions!$D$55 -> 0 | F52: =(F33*Assumptions!$D$56+F34*Assumptions!$D$57+F25*Assumptions!$D$58+F24*Assumptions!$D$59)*Assumptions!$D$55 -> 0 | G52: =(G33*Assumptions!$D$56+G34*Assumptions!$D$57+G25*Assumptions!$D$58+G24*Assumptions!$D$59)*Assumptions!$D$55 -> 0 | H52: =(H33*Assumptions!$D$56+H34*Assumptions!$D$57+H25*Assumptions!$D$58+H24*Assumptions!$D$59)*Assumptions!$D$55 -> 1.485 | I52: =(I33*Assumptions!$D$56+I34*Assumptions!$D$57+I25*Assumptions!$D$58+I24*Assumptions!$D$59)*Assumptions!$D$55 -> 2.531925 | J52: =(J33*Assumptions!$D$56+J34*Assumptions!$D$57+J25*Assumptions!$D$58+J24*Assumptions!$D$59)*Assumptions!$D$55 -> 3.0188194 | K52: =(K33*Assumptions!$D$56+K34*Assumptions!$D$57+K25*Assumptions!$D$58+K24*Assumptions!$D$59)*Assumptions!$D$55 -> 3.182174 | ... BK52: =(BK33*Assumptions!$D$56+BK34*Assumptions!$D$57+BK25*Assumptions!$D$58+BK24*Assumptions!$D$59)*Assumptions!$D$55 -> 539.45819
A53: cost_payments | B53: Stripe Connect platform costs | D53: =D39*Assumptions!$D$51+D32*Assumptions!$D$45*Assumptions!$D$52 -> 0 | E53: =E39*Assumptions!$D$51+E32*Assumptions!$D$45*Assumptions!$D$52 -> 0 | F53: =F39*Assumptions!$D$51+F32*Assumptions!$D$45*Assumptions!$D$52 -> 0 | G53: =G39*Assumptions!$D$51+G32*Assumptions!$D$45*Assumptions!$D$52 -> 0 | H53: =H39*Assumptions!$D$51+H32*Assumptions!$D$45*Assumptions!$D$52 -> 0 | I53: =I39*Assumptions!$D$51+I32*Assumptions!$D$45*Assumptions!$D$52 -> 0 | J53: =J39*Assumptions!$D$51+J32*Assumptions!$D$45*Assumptions!$D$52 -> 0 | K53: =K39*Assumptions!$D$51+K32*Assumptions!$D$45*Assumptions!$D$52 -> 0 | ... BK53: =BK39*Assumptions!$D$51+BK32*Assumptions!$D$45*Assumptions!$D$52 -> 179.21933
A54: cost_billing | B54: Subscription billing fees | D54: =(D37+D38)*Assumptions!$D$53+D32*Assumptions!$D$54 -> 0 | E54: =(E37+E38)*Assumptions!$D$53+E32*Assumptions!$D$54 -> 0 | F54: =(F37+F38)*Assumptions!$D$53+F32*Assumptions!$D$54 -> 0 | G54: =(G37+G38)*Assumptions!$D$53+G32*Assumptions!$D$54 -> 0 | H54: =(H37+H38)*Assumptions!$D$53+H32*Assumptions!$D$54 -> 0 | I54: =(I37+I38)*Assumptions!$D$53+I32*Assumptions!$D$54 -> 0 | J54: =(J37+J38)*Assumptions!$D$53+J32*Assumptions!$D$54 -> 0 | K54: =(K37+K38)*Assumptions!$D$53+K32*Assumptions!$D$54 -> 0 | ... BK54: =(BK37+BK38)*Assumptions!$D$53+BK32*Assumptions!$D$54 -> 82.845923
A55: cost_network_perks | B55: Platform-funded network perks | D55: =D25*Assumptions!$D$65*Assumptions!$D$66*Assumptions!$D$67 -> 0 | E55: =E25*Assumptions!$D$65*Assumptions!$D$66*Assumptions!$D$67 -> 0 | F55: =F25*Assumptions!$D$65*Assumptions!$D$66*Assumptions!$D$67 -> 0 | G55: =G25*Assumptions!$D$65*Assumptions!$D$66*Assumptions!$D$67 -> 0 | H55: =H25*Assumptions!$D$65*Assumptions!$D$66*Assumptions!$D$67 -> 10.125 | I55: =I25*Assumptions!$D$65*Assumptions!$D$66*Assumptions!$D$67 -> 15.643125 | J55: =J25*Assumptions!$D$65*Assumptions!$D$66*Assumptions!$D$67 -> 16.524759 | K55: =K25*Assumptions!$D$65*Assumptions!$D$66*Assumptions!$D$67 -> 15.156904 | ... BK55: =BK25*Assumptions!$D$65*Assumptions!$D$66*Assumptions!$D$67 -> 157.30844
A56: cost_ads_ops | B56: Ad operations | D56: =(D41+D42+D43)*Assumptions!$D$78 -> 0 | E56: =(E41+E42+E43)*Assumptions!$D$78 -> 0 | F56: =(F41+F42+F43)*Assumptions!$D$78 -> 0 | G56: =(G41+G42+G43)*Assumptions!$D$78 -> 0 | H56: =(H41+H42+H43)*Assumptions!$D$78 -> 0 | I56: =(I41+I42+I43)*Assumptions!$D$78 -> 0 | J56: =(J41+J42+J43)*Assumptions!$D$78 -> 0 | K56: =(K41+K42+K43)*Assumptions!$D$78 -> 0 | ... BK56: =(BK41+BK42+BK43)*Assumptions!$D$78 -> 0
A57: cost_bia | B57: BIA campaign delivery | D57: =D45*Assumptions!$D$82 -> 0 | E57: =E45*Assumptions!$D$82 -> 0 | F57: =F45*Assumptions!$D$82 -> 0 | G57: =G45*Assumptions!$D$82 -> 0 | H57: =H45*Assumptions!$D$82 -> 0 | I57: =I45*Assumptions!$D$82 -> 0 | J57: =J45*Assumptions!$D$82 -> 0 | K57: =K45*Assumptions!$D$82 -> 0 | ... BK57: =BK45*Assumptions!$D$82 -> 1068.75
A58: variable_total | B58: Total variable costs | D58: =D49+D50+D51+D52+D53+D54+D55+D56+D57 -> 0 | E58: =E49+E50+E51+E52+E53+E54+E55+E56+E57 -> 0 | F58: =F49+F50+F51+F52+F53+F54+F55+F56+F57 -> 0 | G58: =G49+G50+G51+G52+G53+G54+G55+G56+G57 -> 0 | H58: =H49+H50+H51+H52+H53+H54+H55+H56+H57 -> 30.485 | I58: =I49+I50+I51+I52+I53+I54+I55+I56+I57 -> 53.431925 | J58: =J49+J50+J51+J52+J53+J54+J55+J56+J57 -> 65.616969 | K58: =K49+K50+K51+K52+K53+K54+K55+K56+K57 -> 71.199293 | ... BK58: =BK49+BK50+BK51+BK52+BK53+BK54+BK55+BK56+BK57 -> 4230.4621
A59: gross_profit | B59: Gross profit | D59: =D46-D58 -> 0 | E59: =E46-E58 -> 0 | F59: =F46-F58 -> 0 | G59: =G46-G58 -> 0 | H59: =H46-H58 -> -30.485 | I59: =I46-I58 -> -53.431925 | J59: =J46-J58 -> -65.616969 | K59: =K46-K58 -> -71.199293 | ... BK59: =BK46-BK58 -> 1875.103
B60: Merchant acquisition (CAC) spend (CAD)
A61: rep_wage | B61: Rep hourly wage (indexed each Oct 1) | D61: =Assumptions!$D$83*(1+Assumptions!$D$84)^INT(D7/12) -> 17.95 | E61: =Assumptions!$D$83*(1+Assumptions!$D$84)^INT(E7/12) -> 17.95 | F61: =Assumptions!$D$83*(1+Assumptions!$D$84)^INT(F7/12) -> 17.95 | G61: =Assumptions!$D$83*(1+Assumptions!$D$84)^INT(G7/12) -> 17.95 | H61: =Assumptions!$D$83*(1+Assumptions!$D$84)^INT(H7/12) -> 17.95 | I61: =Assumptions!$D$83*(1+Assumptions!$D$84)^INT(I7/12) -> 17.95 | J61: =Assumptions!$D$83*(1+Assumptions!$D$84)^INT(J7/12) -> 17.95 | K61: =Assumptions!$D$83*(1+Assumptions!$D$84)^INT(K7/12) -> 17.95 | ... BK61: =Assumptions!$D$83*(1+Assumptions!$D$84)^INT(BK7/12) -> 20.308777
A62: cac_rep_wages | B62: Rep wages incl. payroll burden | D62: =D11*Assumptions!$D$86*D61*(1+Assumptions!$D$85)*Assumptions!$D$91 -> 0 | E62: =E11*Assumptions!$D$86*E61*(1+Assumptions!$D$85)*Assumptions!$D$91 -> 0 | F62: =F11*Assumptions!$D$86*F61*(1+Assumptions!$D$85)*Assumptions!$D$91 -> 0 | G62: =G11*Assumptions!$D$86*G61*(1+Assumptions!$D$85)*Assumptions!$D$91 -> 0 | H62: =H11*Assumptions!$D$86*H61*(1+Assumptions!$D$85)*Assumptions!$D$91 -> 425.9535 | I62: =I11*Assumptions!$D$86*I61*(1+Assumptions!$D$85)*Assumptions!$D$91 -> 374.83908 | J62: =J11*Assumptions!$D$86*J61*(1+Assumptions!$D$85)*Assumptions!$D$91 -> 255.5721 | K62: =K11*Assumptions!$D$86*K61*(1+Assumptions!$D$85)*Assumptions!$D$91 -> 170.3814 | ... BK62: =BK11*Assumptions!$D$86*BK61*(1+Assumptions!$D$85)*Assumptions!$D$91 -> 1927.7092
A63: cac_activation_bonus | B63: Activation bonuses incl. burden | D63: =D14*Assumptions!$D$87*(1+Assumptions!$D$85)*Assumptions!$D$91 -> 0 | E63: =E14*Assumptions!$D$87*(1+Assumptions!$D$85)*Assumptions!$D$91 -> 0 | F63: =F14*Assumptions!$D$87*(1+Assumptions!$D$85)*Assumptions!$D$91 -> 0 | G63: =G14*Assumptions!$D$87*(1+Assumptions!$D$85)*Assumptions!$D$91 -> 0 | H63: =H14*Assumptions!$D$87*(1+Assumptions!$D$85)*Assumptions!$D$91 -> 84.75 | I63: =I14*Assumptions!$D$87*(1+Assumptions!$D$85)*Assumptions!$D$91 -> 74.58 | J63: =J14*Assumptions!$D$87*(1+Assumptions!$D$85)*Assumptions!$D$91 -> 50.85 | K63: =K14*Assumptions!$D$87*(1+Assumptions!$D$85)*Assumptions!$D$91 -> 33.9 | ... BK63: =BK14*Assumptions!$D$87*(1+Assumptions!$D$85)*Assumptions!$D$91 -> 339
A64: cac_kits | B64: Counter kits | D64: =D11*Assumptions!$D$88*Assumptions!$D$91 -> 0 | E64: =E11*Assumptions!$D$88*Assumptions!$D$91 -> 0 | F64: =F11*Assumptions!$D$88*Assumptions!$D$91 -> 0 | G64: =G11*Assumptions!$D$88*Assumptions!$D$91 -> 0 | H64: =H11*Assumptions!$D$88*Assumptions!$D$91 -> 90 | I64: =I11*Assumptions!$D$88*Assumptions!$D$91 -> 79.2 | J64: =J11*Assumptions!$D$88*Assumptions!$D$91 -> 54 | K64: =K11*Assumptions!$D$88*Assumptions!$D$91 -> 36 | ... BK64: =BK11*Assumptions!$D$88*Assumptions!$D$91 -> 360
A65: cac_strip_launch | B65: Strip launch events | D65: =D8*Assumptions!$D$89*Assumptions!$D$91 -> 0 | E65: =E8*Assumptions!$D$89*Assumptions!$D$91 -> 0 | F65: =F8*Assumptions!$D$89*Assumptions!$D$91 -> 0 | G65: =G8*Assumptions!$D$89*Assumptions!$D$91 -> 0 | H65: =H8*Assumptions!$D$89*Assumptions!$D$91 -> 750 | I65: =I8*Assumptions!$D$89*Assumptions!$D$91 -> 0 | J65: =J8*Assumptions!$D$89*Assumptions!$D$91 -> 0 | K65: =K8*Assumptions!$D$89*Assumptions!$D$91 -> 0 | ... BK65: =BK8*Assumptions!$D$89*Assumptions!$D$91 -> 750
A66: cac_upsell | B66: Paid upsell cost | D66: =D35*Assumptions!$D$90*Assumptions!$D$91 -> 0 | E66: =E35*Assumptions!$D$90*Assumptions!$D$91 -> 0 | F66: =F35*Assumptions!$D$90*Assumptions!$D$91 -> 0 | G66: =G35*Assumptions!$D$90*Assumptions!$D$91 -> 0 | H66: =H35*Assumptions!$D$90*Assumptions!$D$91 -> 0 | I66: =I35*Assumptions!$D$90*Assumptions!$D$91 -> 0 | J66: =J35*Assumptions!$D$90*Assumptions!$D$91 -> 0 | K66: =K35*Assumptions!$D$90*Assumptions!$D$91 -> 0 | ... BK66: =BK35*Assumptions!$D$90*Assumptions!$D$91 -> 146.47127
A67: cac_total | B67: Total acquisition spend | D67: =D62+D63+D64+D65+D66 -> 0 | E67: =E62+E63+E64+E65+E66 -> 0 | F67: =F62+F63+F64+F65+F66 -> 0 | G67: =G62+G63+G64+G65+G66 -> 0 | H67: =H62+H63+H64+H65+H66 -> 1350.7035 | I67: =I62+I63+I64+I65+I66 -> 528.61908 | J67: =J62+J63+J64+J65+J66 -> 360.4221 | K67: =K62+K63+K64+K65+K66 -> 240.2814 | ... BK67: =BK62+BK63+BK64+BK65+BK66 -> 3523.1804
B68: Fixed operating costs (CAD)
A69: opex_fixed_overhead | B69: Fixed overhead | D69: =Assumptions!$D$108 -> 1465 | E69: =Assumptions!$D$108 -> 1465 | F69: =Assumptions!$D$108 -> 1465 | G69: =Assumptions!$D$108 -> 1465 | H69: =Assumptions!$D$108 -> 1465 | I69: =Assumptions!$D$108 -> 1465 | J69: =Assumptions!$D$108 -> 1465 | K69: =Assumptions!$D$108 -> 1465 | ... BK69: =Assumptions!$D$108 -> 1465
A70: opex_developer | B70: Part-time developer | D70: =IF(D7<=12,Assumptions!$D$100,IF(D7<=24,Assumptions!$D$101,Assumptions!$D$102)) -> 4000 | E70: =IF(E7<=12,Assumptions!$D$100,IF(E7<=24,Assumptions!$D$101,Assumptions!$D$102)) -> 4000 | F70: =IF(F7<=12,Assumptions!$D$100,IF(F7<=24,Assumptions!$D$101,Assumptions!$D$102)) -> 4000 | G70: =IF(G7<=12,Assumptions!$D$100,IF(G7<=24,Assumptions!$D$101,Assumptions!$D$102)) -> 4000 | H70: =IF(H7<=12,Assumptions!$D$100,IF(H7<=24,Assumptions!$D$101,Assumptions!$D$102)) -> 4000 | I70: =IF(I7<=12,Assumptions!$D$100,IF(I7<=24,Assumptions!$D$101,Assumptions!$D$102)) -> 4000 | J70: =IF(J7<=12,Assumptions!$D$100,IF(J7<=24,Assumptions!$D$101,Assumptions!$D$102)) -> 4000 | K70: =IF(K7<=12,Assumptions!$D$100,IF(K7<=24,Assumptions!$D$101,Assumptions!$D$102)) -> 4000 | ... BK70: =IF(BK7<=12,Assumptions!$D$100,IF(BK7<=24,Assumptions!$D$101,Assumptions!$D$102)) -> 6000
A71: opex_customer_success | B71: Account / BIA manager | D71: =INT(D13/Assumptions!$D$103)*Assumptions!$D$104 -> 0 | E71: =INT(E13/Assumptions!$D$103)*Assumptions!$D$104 -> 0 | F71: =INT(F13/Assumptions!$D$103)*Assumptions!$D$104 -> 0 | G71: =INT(G13/Assumptions!$D$103)*Assumptions!$D$104 -> 0 | H71: =INT(H13/Assumptions!$D$103)*Assumptions!$D$104 -> 0 | I71: =INT(I13/Assumptions!$D$103)*Assumptions!$D$104 -> 0 | J71: =INT(J13/Assumptions!$D$103)*Assumptions!$D$104 -> 0 | K71: =INT(K13/Assumptions!$D$103)*Assumptions!$D$104 -> 0 | ... BK71: =INT(BK13/Assumptions!$D$103)*Assumptions!$D$104 -> 0
A72: opex_founder_salary | B72: Founder salary | D72: =IF(D7>=Assumptions!$D$106,Assumptions!$D$105,0) -> 0 | E72: =IF(E7>=Assumptions!$D$106,Assumptions!$D$105,0) -> 0 | F72: =IF(F7>=Assumptions!$D$106,Assumptions!$D$105,0) -> 0 | G72: =IF(G7>=Assumptions!$D$106,Assumptions!$D$105,0) -> 0 | H72: =IF(H7>=Assumptions!$D$106,Assumptions!$D$105,0) -> 0 | I72: =IF(I7>=Assumptions!$D$106,Assumptions!$D$105,0) -> 0 | J72: =IF(J7>=Assumptions!$D$106,Assumptions!$D$105,0) -> 0 | K72: =IF(K7>=Assumptions!$D$106,Assumptions!$D$105,0) -> 0 | ... BK72: =IF(BK7>=Assumptions!$D$106,Assumptions!$D$105,0) -> 0
A73: opex_one_time | B73: One-time costs | D73: =Assumptions!C$144 -> 3500 | E73: =Assumptions!D$144 -> 1500 | F73: =Assumptions!E$144 -> 3000 | G73: =Assumptions!F$144 -> 0 | H73: =Assumptions!G$144 -> 0 | I73: =Assumptions!H$144 -> 0 | J73: =Assumptions!I$144 -> 0 | K73: =Assumptions!J$144 -> 0 | ... BK73: =Assumptions!BJ$144 -> 0
A74: opex_total | B74: Total fixed opex | D74: =D69+D70+D71+D72+D73 -> 8965 | E74: =E69+E70+E71+E72+E73 -> 6965 | F74: =F69+F70+F71+F72+F73 -> 8465 | G74: =G69+G70+G71+G72+G73 -> 5465 | H74: =H69+H70+H71+H72+H73 -> 5465 | I74: =I69+I70+I71+I72+I73 -> 5465 | J74: =J69+J70+J71+J72+J73 -> 5465 | K74: =K69+K70+K71+K72+K73 -> 5465 | ... BK74: =BK69+BK70+BK71+BK72+BK73 -> 7465
B75: Bottom line (CAD)
A76: ebitda | B76: EBITDA / net cash flow | D76: =D59-D67-D74 -> -8965 | E76: =E59-E67-E74 -> -6965 | F76: =F59-F67-F74 -> -8465 | G76: =G59-G67-G74 -> -5465 | H76: =H59-H67-H74 -> -6846.1885 | I76: =I59-I67-I74 -> -6047.051 | J76: =J59-J67-J74 -> -5891.0391 | K76: =K59-K67-K74 -> -5776.4807 | ... BK76: =BK59-BK67-BK74 -> -9113.0774
A77: cum_cash | B77: Cumulative cash (from starting cash) | C77: =Assumptions!$D$9 -> 0 | D77: =C77+D76 -> -8965 | E77: =D77+E76 -> -15930 | F77: =E77+F76 -> -24395 | G77: =F77+G76 -> -29860 | H77: =G77+H76 -> -36706.188 | I77: =H77+I76 -> -42753.24 | J77: =I77+J76 -> -48644.279 | K77: =J77+K76 -> -54420.759 | ... BK77: =BJ77+BK76 -> -545418.1
A78: merchant_paid_stripe_fees | B78: Info: Stripe fees paid by merchants (not ours) | D78: =D39*Assumptions!$D$49+D39/Assumptions!$D$48*Assumptions!$D$50 -> 0 | E78: =E39*Assumptions!$D$49+E39/Assumptions!$D$48*Assumptions!$D$50 -> 0 | F78: =F39*Assumptions!$D$49+F39/Assumptions!$D$48*Assumptions!$D$50 -> 0 | G78: =G39*Assumptions!$D$49+G39/Assumptions!$D$48*Assumptions!$D$50 -> 0 | H78: =H39*Assumptions!$D$49+H39/Assumptions!$D$48*Assumptions!$D$50 -> 0 | I78: =I39*Assumptions!$D$49+I39/Assumptions!$D$48*Assumptions!$D$50 -> 0 | J78: =J39*Assumptions!$D$49+J39/Assumptions!$D$48*Assumptions!$D$50 -> 0 | K78: =K39*Assumptions!$D$49+K39/Assumptions!$D$48*Assumptions!$D$50 -> 0 | ... BK78: =BK39*Assumptions!$D$49+BK39/Assumptions!$D$48*Assumptions!$D$50 -> 2231.4607
B79: Break-even helpers
A80: pos_flag | B80: EBITDA >= 0 | D80: =IF(D76>=0,1,0) -> 0 | E80: =IF(E76>=0,1,0) -> 0 | F80: =IF(F76>=0,1,0) -> 0 | G80: =IF(G76>=0,1,0) -> 0 | H80: =IF(H76>=0,1,0) -> 0 | I80: =IF(I76>=0,1,0) -> 0 | J80: =IF(J76>=0,1,0) -> 0 | K80: =IF(K76>=0,1,0) -> 0 | ... BK80: =IF(BK76>=0,1,0) -> 0
A81: stays36 | B81: EBITDA >= 0 from here to month 36 | D81: =IF(AND(D80=1,E81=1),1,0) -> 0 | E81: =IF(AND(E80=1,F81=1),1,0) -> 0 | F81: =IF(AND(F80=1,G81=1),1,0) -> 0 | G81: =IF(AND(G80=1,H81=1),1,0) -> 0 | H81: =IF(AND(H80=1,I81=1),1,0) -> 0 | I81: =IF(AND(I80=1,J81=1),1,0) -> 0 | J81: =IF(AND(J80=1,K81=1),1,0) -> 0 | K81: =IF(AND(K80=1,L81=1),1,0) -> 0 | ... AL81: =IF(AND(AL80=1,AM81=1),1,0) -> 0 | AM81: =AM80 -> 0
A82: stays60 | B82: EBITDA >= 0 from here to month 60 | D82: =IF(AND(D80=1,E82=1),1,0) -> 0 | E82: =IF(AND(E80=1,F82=1),1,0) -> 0 | F82: =IF(AND(F80=1,G82=1),1,0) -> 0 | G82: =IF(AND(G80=1,H82=1),1,0) -> 0 | H82: =IF(AND(H80=1,I82=1),1,0) -> 0 | I82: =IF(AND(I80=1,J82=1),1,0) -> 0 | J82: =IF(AND(J80=1,K82=1),1,0) -> 0 | K82: =IF(AND(K80=1,L82=1),1,0) -> 0 | ... BJ82: =IF(AND(BJ80=1,BK82=1),1,0) -> 0 | BK82: =BK80 -> 0
B84: Key outputs
B85: Break-even month (EBITDA >= 0 through month 36) | C85: =IFERROR(MATCH(1,D81:AM81,0),"none") -> none
B86: Break-even month, extended run (EBITDA >= 0 through month 60) | C86: =IFERROR(MATCH(1,D82:BK82,0),"none") -> none
B87: First month with EBITDA >= 0 (36m) | C87: =IFERROR(MATCH(1,D80:AM80,0),"none") -> none
B88: Peak cash need, months 1-36 | C88: =-MIN(0,MIN(D77:AM77)) -> 305899.55
B89: Month of cash trough (36m) | C89: =MATCH(MIN(D77:AM77),D77:AM77,0) -> 36
B90: Peak cash need, months 1-60 (to break-even) | C90: =-MIN(0,MIN(D77:BK77)) -> 545418.1
B91: Plus unlock month | C91: =IFERROR(MATCH(1,D16:AM16,0),"none") -> 36
B92: Pro unlock month | C92: =IFERROR(MATCH(1,D17:AM17,0),"none") -> 36
B93: BIA campaigns unlock month | C93: =IFERROR(MATCH(1,D18:AM18,0),"none") -> 29
B94: Ads unlock month | C94: =IFERROR(MATCH(1,D19:AM19,0),"none") -> none
B95: Month-36 active merchants | C95: =AM13 -> 155.61935
B96: Month-36 paying merchants | C96: =AM32 -> 1.8102727
B97: Month-36 active customers | C97: =AM24 -> 5041.5366
B98: Month-36 revenue | C98: =AM46 -> 1434.5128
B99: Month-36 EBITDA | C99: =AM76 -> -10902.903
B100: Year-1 revenue | C100: =SUM(D46:O46) -> 0
B101: Year-2 revenue | C101: =SUM(P46:AA46) -> 0
B102: Year-3 revenue | C102: =SUM(AB46:AM46) -> 8184.5128
...

Sheet Monthly_RecoGates
A1: Local Loyalty — monthly model: Base + reco gates scenario (CAD)
A2: Every cell is a formula driven by the Assumptions sheet (column E). Months 1-36 = projection; grey months 37-60 = extension used only to locate break-even.
B4: Model month | C4: 0 | D4: 1 | E4: 2 | F4: 3 | G4: 4 | H4: 5 | I4: 6 | J4: 7 | K4: 8 | L4: 9 | M4: 10 | N4: 11 | O4: 12 | P4: 13 | Q4: 14 | R4: 15 | S4: 16 | T4: 17 | U4: 18 | V4: 19 | W4: 20 | X4: 21 | Y4: 22 | Z4: 23 | AA4: 24 | AB4: 25 | AC4: 26 | AD4: 27 | AE4: 28 | AF4: 29 | AG4: 30 | AH4: 31 | AI4: 32 | AJ4: 33 | AK4: 34 | AL4: 35 | AM4: 36 | AN4: 37 | AO4: 38 | AP4: 39 | AQ4: 40 | AR4: 41 | AS4: 42 | AT4: 43 | AU4: 44 | AV4: 45 | AW4: 46 | AX4: 47 | AY4: 48 | AZ4: 49 | BA4: 50 | BB4: 51 | BC4: 52 | BD4: 53 | BE4: 54 | BF4: 55 | BG4: 56 | BH4: 57 | BI4: 58 | BJ4: 59 | BK4: 60
B5: Calendar month | C5: start | D5: 2026-11 | E5: 2026-12 | F5: 2027-01 | G5: 2027-02 | H5: 2027-03 | I5: 2027-04 | J5: 2027-05 | K5: 2027-06 | L5: 2027-07 | M5: 2027-08 | N5: 2027-09 | O5: 2027-10 | P5: 2027-11 | Q5: 2027-12 | R5: 2028-01 | S5: 2028-02 | T5: 2028-03 | U5: 2028-04 | V5: 2028-05 | W5: 2028-06 | X5: 2028-07 | Y5: 2028-08 | Z5: 2028-09 | AA5: 2028-10 | AB5: 2028-11 | AC5: 2028-12 | AD5: 2029-01 | AE5: 2029-02 | AF5: 2029-03 | AG5: 2029-04 | AH5: 2029-05 | AI5: 2029-06 | AJ5: 2029-07 | AK5: 2029-08 | AL5: 2029-09 | AM5: 2029-10 | AN5: 2029-11 | AO5: 2029-12 | AP5: 2030-01 | AQ5: 2030-02 | AR5: 2030-03 | AS5: 2030-04 | AT5: 2030-05 | AU5: 2030-06 | AV5: 2030-07 | AW5: 2030-08 | AX5: 2030-09 | AY5: 2030-10 | AZ5: 2030-11 | BA5: 2030-12 | BB5: 2031-01 | BC5: 2031-02 | BD5: 2031-03 | BE5: 2031-04 | BF5: 2031-05 | BG5: 2031-06 | BH5: 2031-07 | BI5: 2031-08 | BJ5: 2031-09 | BK5: 2031-10
B6: Strips & merchants
A7: month | B7: Model month | C7: 0 | D7: 1 | E7: 2 | F7: 3 | G7: 4 | H7: 5 | I7: 6 | J7: 7 | K7: 8 | L7: 9 | M7: 10 | N7: 11 | O7: 12 | P7: 13 | Q7: 14 | R7: 15 | S7: 16 | T7: 17 | U7: 18 | V7: 19 | W7: 20 | X7: 21 | Y7: 22 | Z7: 23 | AA7: 24 | AB7: 25 | AC7: 26 | AD7: 27 | AE7: 28 | AF7: 29 | AG7: 30 | AH7: 31 | AI7: 32 | AJ7: 33 | AK7: 34 | AL7: 35 | AM7: 36 | AN7: 37 | AO7: 38 | AP7: 39 | AQ7: 40 | AR7: 41 | AS7: 42 | AT7: 43 | AU7: 44 | AV7: 45 | AW7: 46 | AX7: 47 | AY7: 48 | AZ7: 49 | BA7: 50 | BB7: 51 | BC7: 52 | BD7: 53 | BE7: 54 | BF7: 55 | BG7: 56 | BH7: 57 | BI7: 58 | BJ7: 59 | BK7: 60
A8: strips_launched | B8: Strips launched | C8: 0 | D8: =Assumptions!C$141 -> 0 | E8: =Assumptions!D$141 -> 0 | F8: =Assumptions!E$141 -> 0 | G8: =Assumptions!F$141 -> 0 | H8: =Assumptions!G$141 -> 1 | I8: =Assumptions!H$141 -> 0 | J8: =Assumptions!I$141 -> 0 | K8: =Assumptions!J$141 -> 1 | ... BK8: =Assumptions!BJ$141 -> 1
A9: strips_cum | B9: Strips live (cumulative) | C9: 0 | D9: =C9+D8 -> 0 | E9: =D9+E8 -> 0 | F9: =E9+F8 -> 0 | G9: =F9+G8 -> 0 | H9: =G9+H8 -> 1 | I9: =H9+I8 -> 1 | J9: =I9+J8 -> 1 | K9: =J9+K8 -> 2 | ... BK9: =BJ9+BK8 -> 61
A10: strips_mature | B10: Mature strips (launched >= maturity months ago) | C10: 0 | D10: =IF(D7>Assumptions!$E$79,INDEX($D$9:$BK$9,D7-Assumptions!$E$79),0) -> 0 | E10: =IF(E7>Assumptions!$E$79,INDEX($D$9:$BK$9,E7-Assumptions!$E$79),0) -> 0 | F10: =IF(F7>Assumptions!$E$79,INDEX($D$9:$BK$9,F7-Assumptions!$E$79),0) -> 0 | G10: =IF(G7>Assumptions!$E$79,INDEX($D$9:$BK$9,G7-Assumptions!$E$79),0) -> 0 | H10: =IF(H7>Assumptions!$E$79,INDEX($D$9:$BK$9,H7-Assumptions!$E$79),0) -> 0 | I10: =IF(I7>Assumptions!$E$79,INDEX($D$9:$BK$9,I7-Assumptions!$E$79),0) -> 0 | J10: =IF(J7>Assumptions!$E$79,INDEX($D$9:$BK$9,J7-Assumptions!$E$79),0) -> 0 | K10: =IF(K7>Assumptions!$E$79,INDEX($D$9:$BK$9,K7-Assumptions!$E$79),0) -> 0 | ... BK10: =IF(BK7>Assumptions!$E$79,INDEX($D$9:$BK$9,BK7-Assumptions!$E$79),0) -> 53
A11: signups | B11: New merchant sign-ups | C11: 0 | D11: =Assumptions!$E$10*(D8*Assumptions!$E$111) -> 0 | E11: =Assumptions!$E$10*(E8*Assumptions!$E$111+D8*Assumptions!$E$112) -> 0 | F11: =Assumptions!$E$10*(F8*Assumptions!$E$111+E8*Assumptions!$E$112+D8*Assumptions!$E$113) -> 0 | G11: =Assumptions!$E$10*(G8*Assumptions!$E$111+F8*Assumptions!$E$112+E8*Assumptions!$E$113+D8*Assumptions!$E$114) -> 0 | H11: =Assumptions!$E$10*(H8*Assumptions!$E$111+G8*Assumptions!$E$112+F8*Assumptions!$E$113+E8*Assumptions!$E$114+D8*Assumptions!$E$115) -> 8 | I11: =Assumptions!$E$10*(I8*Assumptions!$E$111+H8*Assumptions!$E$112+G8*Assumptions!$E$113+F8*Assumptions!$E$114+E8*Assumptions!$E$115+D8*Assumptions!$E$116) -> 7.04 | J11: =Assumptions!$E$10*(J8*Assumptions!$E$111+I8*Assumptions!$E$112+H8*Assumptions!$E$113+G8*Assumptions!$E$114+F8*Assumptions!$E$115+E8*Assumptions!$E$116+D8*Assumptions!$E$117) -> 4.8 | K11: =Assumptions!$E$10*(K8*Assumptions!$E$111+J8*Assumptions!$E$112+I8*Assumptions!$E$113+H8*Assumptions!$E$114+G8*Assumptions!$E$115+F8*Assumptions!$E$116+E8*Assumptions!$E$117+D8*Assumptions!$E$118) -> 11.2 | L11: =Assumptions!$E$10*(L8*Assumptions!$E$111+K8*Assumptions!$E$112+J8*Assumptions!$E$113+I8*Assumptions!$E$114+H8*Assumptions!$E$115+G8*Assumptions!$E$116+F8*Assumptions!$E$117+E8*Assumptions!$E$118+D8*Assumptions!$E$119) -> 8.96 | M11: =Assumptions!$E$10*(M8*Assumptions!$E$111+L8*Assumptions!$E$112+K8*Assumptions!$E$113+J8*Assumptions!$E$114+I8*Assumptions!$E$115+H8*Assumptions!$E$116+G8*Assumptions!$E$117+F8*Assumptions!$E$118+E8*Assumptions!$E$119+D8*Assumptions!$E$120) -> 6.4 | N11: =Assumptions!$E$10*(N8*Assumptions!$E$111+M8*Assumptions!$E$112+L8*Assumptions!$E$113+K8*Assumptions!$E$114+J8*Assumptions!$E$115+I8*Assumptions!$E$116+H8*Assumptions!$E$117+G8*Assumptions!$E$118+F8*Assumptions!$E$119+E8*Assumptions!$E$120+D8*Assumptions!$E$121) -> 11.52 | O11: =Assumptions!$E$10*(O8*Assumptions!$E$111+N8*Assumptions!$E$112+M8*Assumptions!$E$113+L8*Assumptions!$E$114+K8*Assumptions!$E$115+J8*Assumptions!$E$116+I8*Assumptions!$E$117+H8*Assumptions!$E$118+G8*Assumptions!$E$119+F8*Assumptions!$E$120+E8*Assumptions!$E$121+D8*Assumptions!$E$122) -> 17.28 | P11: =Assumptions!$E$10*(P8*Assumptions!$E$111+O8*Assumptions!$E$112+N8*Assumptions!$E$113+M8*Assumptions!$E$114+L8*Assumptions!$E$115+K8*Assumptions!$E$116+J8*Assumptions!$E$117+I8*Assumptions!$E$118+H8*Assumptions!$E$119+G8*Assumptions!$E$120+F8*Assumptions!$E$121+E8*Assumptions!$E$122+D8*Assumptions!$E$123) -> 13.76 | Q11: =Assumptions!$E$10*(Q8*Assumptions!$E$111+P8*Assumptions!$E$112+O8*Assumptions!$E$113+N8*Assumptions!$E$114+M8*Assumptions!$E$115+L8*Assumptions!$E$116+K8*Assumptions!$E$117+J8*Assumptions!$E$118+I8*Assumptions!$E$119+H8*Assumptions!$E$120+G8*Assumptions!$E$121+F8*Assumptions!$E$122+E8*Assumptions!$E$123+D8*Assumptions!$E$124) -> 16.64 | R11: =Assumptions!$E$10*(R8*Assumptions!$E$111+Q8*Assumptions!$E$112+P8*Assumptions!$E$113+O8*Assumptions!$E$114+N8*Assumptions!$E$115+M8*Assumptions!$E$116+L8*Assumptions!$E$117+K8*Assumptions!$E$118+J8*Assumptions!$E$119+I8*Assumptions!$E$120+H8*Assumptions!$E$121+G8*Assumptions!$E$122+F8*Assumptions!$E$123+E8*Assumptions!$E$124+D8*Assumptions!$E$125) -> 20.8 | S11: =Assumptions!$E$10*(S8*Assumptions!$E$111+R8*Assumptions!$E$112+Q8*Assumptions!$E$113+P8*Assumptions!$E$114+O8*Assumptions!$E$115+N8*Assumptions!$E$116+M8*Assumptions!$E$117+L8*Assumptions!$E$118+K8*Assumptions!$E$119+J8*Assumptions!$E$120+I8*Assumptions!$E$121+H8*Assumptions!$E$122+G8*Assumptions!$E$123+F8*Assumptions!$E$124+E8*Assumptions!$E$125+D8*Assumptions!$E$126) -> 16 | T11: =Assumptions!$E$10*(T8*Assumptions!$E$111+S8*Assumptions!$E$112+R8*Assumptions!$E$113+Q8*Assumptions!$E$114+P8*Assumptions!$E$115+O8*Assumptions!$E$116+N8*Assumptions!$E$117+M8*Assumptions!$E$118+L8*Assumptions!$E$119+K8*Assumptions!$E$120+J8*Assumptions!$E$121+I8*Assumptions!$E$122+H8*Assumptions!$E$123+G8*Assumptions!$E$124+F8*Assumptions!$E$125+E8*Assumptions!$E$126+D8*Assumptions!$E$127) -> 18.56 | U11: =Assumptions!$E$10*(U8*Assumptions!$E$111+T8*Assumptions!$E$112+S8*Assumptions!$E$113+R8*Assumptions!$E$114+Q8*Assumptions!$E$115+P8*Assumptions!$E$116+O8*Assumptions!$E$117+N8*Assumptions!$E$118+M8*Assumptions!$E$119+L8*Assumptions!$E$120+K8*Assumptions!$E$121+J8*Assumptions!$E$122+I8*Assumptions!$E$123+H8*Assumptions!$E$124+G8*Assumptions!$E$125+F8*Assumptions!$E$126+E8*Assumptions!$E$127+D8*Assumptions!$E$128) -> 21.44 | V11: =Assumptions!$E$10*(V8*Assumptions!$E$111+U8*Assumptions!$E$112+T8*Assumptions!$E$113+S8*Assumptions!$E$114+R8*Assumptions!$E$115+Q8*Assumptions!$E$116+P8*Assumptions!$E$117+O8*Assumptions!$E$118+N8*Assumptions!$E$119+M8*Assumptions!$E$120+L8*Assumptions!$E$121+K8*Assumptions!$E$122+J8*Assumptions!$E$123+I8*Assumptions!$E$124+H8*Assumptions!$E$125+G8*Assumptions!$E$126+F8*Assumptions!$E$127+E8*Assumptions!$E$128+D8*Assumptions!$E$129) -> 24.64 | W11: =Assumptions!$E$10*(W8*Assumptions!$E$111+V8*Assumptions!$E$112+U8*Assumptions!$E$113+T8*Assumptions!$E$114+S8*Assumptions!$E$115+R8*Assumptions!$E$116+Q8*Assumptions!$E$117+P8*Assumptions!$E$118+O8*Assumptions!$E$119+N8*Assumptions!$E$120+M8*Assumptions!$E$121+L8*Assumptions!$E$122+K8*Assumptions!$E$123+J8*Assumptions!$E$124+I8*Assumptions!$E$125+H8*Assumptions!$E$126+G8*Assumptions!$E$127+F8*Assumptions!$E$128+E8*Assumptions!$E$129+D8*Assumptions!$E$130) -> 26.24 | X11: =Assumptions!$E$10*(X8*Assumptions!$E$111+W8*Assumptions!$E$112+V8*Assumptions!$E$113+U8*Assumptions!$E$114+T8*Assumptions!$E$115+S8*Assumptions!$E$116+R8*Assumptions!$E$117+Q8*Assumptions!$E$118+P8*Assumptions!$E$119+O8*Assumptions!$E$120+N8*Assumptions!$E$121+M8*Assumptions!$E$122+L8*Assumptions!$E$123+K8*Assumptions!$E$124+J8*Assumptions!$E$125+I8*Assumptions!$E$126+H8*Assumptions!$E$127+G8*Assumptions!$E$128+F8*Assumptions!$E$129+E8*Assumptions!$E$130+D8*Assumptions!$E$131) -> 26.88 | Y11: =Assumptions!$E$10*(Y8*Assumptions!$E$111+X8*Assumptions!$E$112+W8*Assumptions!$E$113+V8*Assumptions!$E$114+U8*Assumptions!$E$115+T8*Assumptions!$E$116+S8*Assumptions!$E$117+R8*Assumptions!$E$118+Q8*Assumptions!$E$119+P8*Assumptions!$E$120+O8*Assumptions!$E$121+N8*Assumptions!$E$122+M8*Assumptions!$E$123+L8*Assumptions!$E$124+K8*Assumptions!$E$125+J8*Assumptions!$E$126+I8*Assumptions!$E$127+H8*Assumptions!$E$128+G8*Assumptions!$E$129+F8*Assumptions!$E$130+E8*Assumptions!$E$131+D8*Assumptions!$E$132) -> 28.48 | Z11: =Assumptions!$E$10*(Z8*Assumptions!$E$111+Y8*Assumptions!$E$112+X8*Assumptions!$E$113+W8*Assumptions!$E$114+V8*Assumptions!$E$115+U8*Assumptions!$E$116+T8*Assumptions!$E$117+S8*Assumptions!$E$118+R8*Assumptions!$E$119+Q8*Assumptions!$E$120+P8*Assumptions!$E$121+O8*Assumptions!$E$122+N8*Assumptions!$E$123+M8*Assumptions!$E$124+L8*Assumptions!$E$125+K8*Assumptions!$E$126+J8*Assumptions!$E$127+I8*Assumptions!$E$128+H8*Assumptions!$E$129+G8*Assumptions!$E$130+F8*Assumptions!$E$131+E8*Assumptions!$E$132+D8*Assumptions!$E$133) -> 28.8 | AA11: =Assumptions!$E$10*(AA8*Assumptions!$E$111+Z8*Assumptions!$E$112+Y8*Assumptions!$E$113+X8*Assumptions!$E$114+W8*Assumptions!$E$115+V8*Assumptions!$E$116+U8*Assumptions!$E$117+T8*Assumptions!$E$118+S8*Assumptions!$E$119+R8*Assumptions!$E$120+Q8*Assumptions!$E$121+P8*Assumptions!$E$122+O8*Assumptions!$E$123+N8*Assumptions!$E$124+M8*Assumptions!$E$125+L8*Assumptions!$E$126+K8*Assumptions!$E$127+J8*Assumptions!$E$128+I8*Assumptions!$E$129+H8*Assumptions!$E$130+G8*Assumptions!$E$131+F8*Assumptions!$E$132+E8*Assumptions!$E$133) -> 29.12 | AB11: =Assumptions!$E$10*(AB8*Assumptions!$E$111+AA8*Assumptions!$E$112+Z8*Assumptions!$E$113+Y8*Assumptions!$E$114+X8*Assumptions!$E$115+W8*Assumptions!$E$116+V8*Assumptions!$E$117+U8*Assumptions!$E$118+T8*Assumptions!$E$119+S8*Assumptions!$E$120+R8*Assumptions!$E$121+Q8*Assumptions!$E$122+P8*Assumptions!$E$123+O8*Assumptions!$E$124+N8*Assumptions!$E$125+M8*Assumptions!$E$126+L8*Assumptions!$E$127+K8*Assumptions!$E$128+J8*Assumptions!$E$129+I8*Assumptions!$E$130+H8*Assumptions!$E$131+G8*Assumptions!$E$132+F8*Assumptions!$E$133) -> 29.44 | AC11: =Assumptions!$E$10*(AC8*Assumptions!$E$111+AB8*Assumptions!$E$112+AA8*Assumptions!$E$113+Z8*Assumptions!$E$114+Y8*Assumptions!$E$115+X8*Assumptions!$E$116+W8*Assumptions!$E$117+V8*Assumptions!$E$118+U8*Assumptions!$E$119+T8*Assumptions!$E$120+S8*Assumptions!$E$121+R8*Assumptions!$E$122+Q8*Assumptions!$E$123+P8*Assumptions!$E$124+O8*Assumptions!$E$125+N8*Assumptions!$E$126+M8*Assumptions!$E$127+L8*Assumptions!$E$128+K8*Assumptions!$E$129+J8*Assumptions!$E$130+I8*Assumptions!$E$131+H8*Assumptions!$E$132+G8*Assumptions!$E$133) -> 29.76 | AD11: =Assumptions!$E$10*(AD8*Assumptions!$E$111+AC8*Assumptions!$E$112+AB8*Assumptions!$E$113+AA8*Assumptions!$E$114+Z8*Assumptions!$E$115+Y8*Assumptions!$E$116+X8*Assumptions!$E$117+W8*Assumptions!$E$118+V8*Assumptions!$E$119+U8*Assumptions!$E$120+T8*Assumptions!$E$121+S8*Assumptions!$E$122+R8*Assumptions!$E$123+Q8*Assumptions!$E$124+P8*Assumptions!$E$125+O8*Assumptions!$E$126+N8*Assumptions!$E$127+M8*Assumptions!$E$128+L8*Assumptions!$E$129+K8*Assumptions!$E$130+J8*Assumptions!$E$131+I8*Assumptions!$E$132+H8*Assumptions!$E$133) -> 30.08 | AE11: =Assumptions!$E$10*(AE8*Assumptions!$E$111+AD8*Assumptions!$E$112+AC8*Assumptions!$E$113+AB8*Assumptions!$E$114+AA8*Assumptions!$E$115+Z8*Assumptions!$E$116+Y8*Assumptions!$E$117+X8*Assumptions!$E$118+W8*Assumptions!$E$119+V8*Assumptions!$E$120+U8*Assumptions!$E$121+T8*Assumptions!$E$122+S8*Assumptions!$E$123+R8*Assumptions!$E$124+Q8*Assumptions!$E$125+P8*Assumptions!$E$126+O8*Assumptions!$E$127+N8*Assumptions!$E$128+M8*Assumptions!$E$129+L8*Assumptions!$E$130+K8*Assumptions!$E$131+J8*Assumptions!$E$132+I8*Assumptions!$E$133) -> 30.08 | AF11: =Assumptions!$E$10*(AF8*Assumptions!$E$111+AE8*Assumptions!$E$112+AD8*Assumptions!$E$113+AC8*Assumptions!$E$114+AB8*Assumptions!$E$115+AA8*Assumptions!$E$116+Z8*Assumptions!$E$117+Y8*Assumptions!$E$118+X8*Assumptions!$E$119+W8*Assumptions!$E$120+V8*Assumptions!$E$121+U8*Assumptions!$E$122+T8*Assumptions!$E$123+S8*Assumptions!$E$124+R8*Assumptions!$E$125+Q8*Assumptions!$E$126+P8*Assumptions!$E$127+O8*Assumptions!$E$128+N8*Assumptions!$E$129+M8*Assumptions!$E$130+L8*Assumptions!$E$131+K8*Assumptions!$E$132+J8*Assumptions!$E$133) -> 38.4 | AG11: =Assumptions!$E$10*(AG8*Assumptions!$E$111+AF8*Assumptions!$E$112+AE8*Assumptions!$E$113+AD8*Assumptions!$E$114+AC8*Assumptions!$E$115+AB8*Assumptions!$E$116+AA8*Assumptions!$E$117+Z8*Assumptions!$E$118+Y8*Assumptions!$E$119+X8*Assumptions!$E$120+W8*Assumptions!$E$121+V8*Assumptions!$E$122+U8*Assumptions!$E$123+T8*Assumptions!$E$124+S8*Assumptions!$E$125+R8*Assumptions!$E$126+Q8*Assumptions!$E$127+P8*Assumptions!$E$128+O8*Assumptions!$E$129+N8*Assumptions!$E$130+M8*Assumptions!$E$131+L8*Assumptions!$E$132+K8*Assumptions!$E$133) -> 37.76 | ... BK11: =Assumptions!$E$10*(BK8*Assumptions!$E$111+BJ8*Assumptions!$E$112+BI8*Assumptions!$E$113+BH8*Assumptions!$E$114+BG8*Assumptions!$E$115+BF8*Assumptions!$E$116+BE8*Assumptions!$E$117+BD8*Assumptions!$E$118+BC8*Assumptions!$E$119+BB8*Assumptions!$E$120+BA8*Assumptions!$E$121+AZ8*Assumptions!$E$122+AY8*Assumptions!$E$123+AX8*Assumptions!$E$124+AW8*Assumptions!$E$125+AV8*Assumptions!$E$126+AU8*Assumptions!$E$127+AT8*Assumptions!$E$128+AS8*Assumptions!$E$129+AR8*Assumptions!$E$130+AQ8*Assumptions!$E$131+AP8*Assumptions!$E$132+AO8*Assumptions!$E$133) -> 42.88
A12: network_merchants | B12: Network merchants (signed, net of churn) | C12: 0 | D12: =C12*(1-Assumptions!$E$12)+D11 -> 0 | E12: =D12*(1-Assumptions!$E$12)+E11 -> 0 | F12: =E12*(1-Assumptions!$E$12)+F11 -> 0 | G12: =F12*(1-Assumptions!$E$12)+G11 -> 0 | H12: =G12*(1-Assumptions!$E$12)+H11 -> 8 | I12: =H12*(1-Assumptions!$E$12)+I11 -> 14.92 | J12: =I12*(1-Assumptions!$E$12)+J11 -> 19.4962 | K12: =J12*(1-Assumptions!$E$12)+K11 -> 30.403757 | ... BK12: =BJ12*(1-Assumptions!$E$12)+BK11 -> 1320.3863
A13: active_merchants | B13: Active merchants (>= 25 active members) | C13: 0 | D13: =D12*Assumptions!$E$11 -> 0 | E13: =E12*Assumptions!$E$11 -> 0 | F13: =F12*Assumptions!$E$11 -> 0 | G13: =G12*Assumptions!$E$11 -> 0 | H13: =H12*Assumptions!$E$11 -> 4.8 | I13: =I12*Assumptions!$E$11 -> 8.952 | J13: =J12*Assumptions!$E$11 -> 11.69772 | K13: =K12*Assumptions!$E$11 -> 18.242254 | ... BK13: =BK12*Assumptions!$E$11 -> 792.23178
A14: activated_new | B14: Newly activated merchants | C14: 0 | D14: =D11*Assumptions!$E$11 -> 0 | E14: =E11*Assumptions!$E$11 -> 0 | F14: =F11*Assumptions!$E$11 -> 0 | G14: =G11*Assumptions!$E$11 -> 0 | H14: =H11*Assumptions!$E$11 -> 4.8 | I14: =I11*Assumptions!$E$11 -> 4.224 | J14: =J11*Assumptions!$E$11 -> 2.88 | K14: =K11*Assumptions!$E$11 -> 6.72 | ... BK14: =BK11*Assumptions!$E$11 -> 25.728
B15: Rollout gates (1 = unlocked; plans.ts unlockAtMerchants)
A16: plus_unlocked | B16: Plus features GA | C16: 0 | D16: =IF(OR(C16=1,AND(D13>=Assumptions!$E$18,D7>=Assumptions!$E$19)),1,0) -> 0 | E16: =IF(OR(D16=1,AND(E13>=Assumptions!$E$18,E7>=Assumptions!$E$19)),1,0) -> 0 | F16: =IF(OR(E16=1,AND(F13>=Assumptions!$E$18,F7>=Assumptions!$E$19)),1,0) -> 0 | G16: =IF(OR(F16=1,AND(G13>=Assumptions!$E$18,G7>=Assumptions!$E$19)),1,0) -> 0 | H16: =IF(OR(G16=1,AND(H13>=Assumptions!$E$18,H7>=Assumptions!$E$19)),1,0) -> 0 | I16: =IF(OR(H16=1,AND(I13>=Assumptions!$E$18,I7>=Assumptions!$E$19)),1,0) -> 0 | J16: =IF(OR(I16=1,AND(J13>=Assumptions!$E$18,J7>=Assumptions!$E$19)),1,0) -> 0 | K16: =IF(OR(J16=1,AND(K13>=Assumptions!$E$18,K7>=Assumptions!$E$19)),1,0) -> 0 | ... BK16: =IF(OR(BJ16=1,AND(BK13>=Assumptions!$E$18,BK7>=Assumptions!$E$19)),1,0) -> 1
A17: pro_unlocked | B17: Pro features GA | C17: 0 | D17: =IF(OR(C17=1,AND(D13>=Assumptions!$E$20,D7>=Assumptions!$E$21)),1,0) -> 0 | E17: =IF(OR(D17=1,AND(E13>=Assumptions!$E$20,E7>=Assumptions!$E$21)),1,0) -> 0 | F17: =IF(OR(E17=1,AND(F13>=Assumptions!$E$20,F7>=Assumptions!$E$21)),1,0) -> 0 | G17: =IF(OR(F17=1,AND(G13>=Assumptions!$E$20,G7>=Assumptions!$E$21)),1,0) -> 0 | H17: =IF(OR(G17=1,AND(H13>=Assumptions!$E$20,H7>=Assumptions!$E$21)),1,0) -> 0 | I17: =IF(OR(H17=1,AND(I13>=Assumptions!$E$20,I7>=Assumptions!$E$21)),1,0) -> 0 | J17: =IF(OR(I17=1,AND(J13>=Assumptions!$E$20,J7>=Assumptions!$E$21)),1,0) -> 0 | K17: =IF(OR(J17=1,AND(K13>=Assumptions!$E$20,K7>=Assumptions!$E$21)),1,0) -> 0 | ... BK17: =IF(OR(BJ17=1,AND(BK13>=Assumptions!$E$20,BK7>=Assumptions!$E$21)),1,0) -> 1
A18: bia_unlocked | B18: BIA campaigns available | C18: 0 | D18: =IF(OR(C18=1,D13>=Assumptions!$E$22),1,0) -> 0 | E18: =IF(OR(D18=1,E13>=Assumptions!$E$22),1,0) -> 0 | F18: =IF(OR(E18=1,F13>=Assumptions!$E$22),1,0) -> 0 | G18: =IF(OR(F18=1,G13>=Assumptions!$E$22),1,0) -> 0 | H18: =IF(OR(G18=1,H13>=Assumptions!$E$22),1,0) -> 0 | I18: =IF(OR(H18=1,I13>=Assumptions!$E$22),1,0) -> 0 | J18: =IF(OR(I18=1,J13>=Assumptions!$E$22),1,0) -> 0 | K18: =IF(OR(J18=1,K13>=Assumptions!$E$22),1,0) -> 0 | ... BK18: =IF(OR(BJ18=1,BK13>=Assumptions!$E$22),1,0) -> 1
A19: ads_unlocked | B19: Ads available | C19: 0 | D19: =IF(OR(C19=1,AND(D13>=Assumptions!$E$23,D7>=Assumptions!$E$24)),1,0) -> 0 | E19: =IF(OR(D19=1,AND(E13>=Assumptions!$E$23,E7>=Assumptions!$E$24)),1,0) -> 0 | F19: =IF(OR(E19=1,AND(F13>=Assumptions!$E$23,F7>=Assumptions!$E$24)),1,0) -> 0 | G19: =IF(OR(F19=1,AND(G13>=Assumptions!$E$23,G7>=Assumptions!$E$24)),1,0) -> 0 | H19: =IF(OR(G19=1,AND(H13>=Assumptions!$E$23,H7>=Assumptions!$E$24)),1,0) -> 0 | I19: =IF(OR(H19=1,AND(I13>=Assumptions!$E$23,I7>=Assumptions!$E$24)),1,0) -> 0 | J19: =IF(OR(I19=1,AND(J13>=Assumptions!$E$23,J7>=Assumptions!$E$24)),1,0) -> 0 | K19: =IF(OR(J19=1,AND(K13>=Assumptions!$E$23,K7>=Assumptions!$E$24)),1,0) -> 0 | ... BK19: =IF(OR(BJ19=1,AND(BK13>=Assumptions!$E$23,BK7>=Assumptions!$E$24)),1,0) -> 1
A20: ads_months | B20: Months since ads unlocked | C20: 0 | D20: =IF(D19=1,C20+1,0) -> 0 | E20: =IF(E19=1,D20+1,0) -> 0 | F20: =IF(F19=1,E20+1,0) -> 0 | G20: =IF(G19=1,F20+1,0) -> 0 | H20: =IF(H19=1,G20+1,0) -> 0 | I20: =IF(I19=1,H20+1,0) -> 0 | J20: =IF(J19=1,I20+1,0) -> 0 | K20: =IF(K19=1,J20+1,0) -> 0 | ... BK20: =IF(BK19=1,BJ20+1,0) -> 30
A21: ads_ramp | B21: Ad demand ramp | C21: 0 | D21: =MIN(1,D20/Assumptions!$E$77) -> 0 | E21: =MIN(1,E20/Assumptions!$E$77) -> 0 | F21: =MIN(1,F20/Assumptions!$E$77) -> 0 | G21: =MIN(1,G20/Assumptions!$E$77) -> 0 | H21: =MIN(1,H20/Assumptions!$E$77) -> 0 | I21: =MIN(1,I20/Assumptions!$E$77) -> 0 | J21: =MIN(1,J20/Assumptions!$E$77) -> 0 | K21: =MIN(1,K20/Assumptions!$E$77) -> 0 | ... BK21: =MIN(1,BK20/Assumptions!$E$77) -> 1
B22: Customers
A23: memberships | B23: Memberships (customer-shop pairs) | C23: 0 | D23: =C23+(D13*Assumptions!$E$13-C23)*Assumptions!$E$14 -> 0 | E23: =D23+(E13*Assumptions!$E$13-D23)*Assumptions!$E$14 -> 0 | F23: =E23+(F13*Assumptions!$E$13-E23)*Assumptions!$E$14 -> 0 | G23: =F23+(G13*Assumptions!$E$13-F23)*Assumptions!$E$14 -> 0 | H23: =G23+(H13*Assumptions!$E$13-G23)*Assumptions!$E$14 -> 126 | I23: =H23+(I13*Assumptions!$E$13-H23)*Assumptions!$E$14 -> 316.89 | J23: =I23+(J13*Assumptions!$E$13-I23)*Assumptions!$E$14 -> 513.04365 | K23: =J23+(K13*Assumptions!$E$13-J23)*Assumptions!$E$14 -> 812.33755 | ... BK23: =BJ23+(BK13*Assumptions!$E$13-BJ23)*Assumptions!$E$14 -> 57392.841
A24: active_customers | B24: Active customers (unique) | C24: 0 | D24: =D23/Assumptions!$E$15 -> 0 | E24: =E23/Assumptions!$E$15 -> 0 | F24: =F23/Assumptions!$E$15 -> 0 | G24: =G23/Assumptions!$E$15 -> 0 | H24: =H23/Assumptions!$E$15 -> 90 | I24: =I23/Assumptions!$E$15 -> 226.35 | J24: =J23/Assumptions!$E$15 -> 366.45975 | K24: =K23/Assumptions!$E$15 -> 580.2411 | ... BK24: =BK23/Assumptions!$E$15 -> 40994.887
A25: new_customers | B25: New / re-acquired customers | C25: 0 | D25: =MAX(0,D24-C24)+C24*Assumptions!$E$16 -> 0 | E25: =MAX(0,E24-D24)+D24*Assumptions!$E$16 -> 0 | F25: =MAX(0,F24-E24)+E24*Assumptions!$E$16 -> 0 | G25: =MAX(0,G24-F24)+F24*Assumptions!$E$16 -> 0 | H25: =MAX(0,H24-G24)+G24*Assumptions!$E$16 -> 90 | I25: =MAX(0,I24-H24)+H24*Assumptions!$E$16 -> 139.95 | J25: =MAX(0,J24-I24)+I24*Assumptions!$E$16 -> 149.16375 | K25: =MAX(0,K24-J24)+J24*Assumptions!$E$16 -> 228.43974 | ... BK25: =MAX(0,BK24-BJ24)+BJ24*Assumptions!$E$16 -> 2387.3187
B26: Paying merchants by vertical (repair/auto gated by Pro, others by Plus)
A27: paid_food_bev | B27: Paying — Cafes, restaurants, bakeries | C27: 0 | D27: =C27*(1-Assumptions!$E$41)+D16*((1-(1-Assumptions!$E$30)^(1/12))*Assumptions!$E$40)*MAX(0,D13*Assumptions!$E$25-C27) -> 0 | E27: =D27*(1-Assumptions!$E$41)+E16*((1-(1-Assumptions!$E$30)^(1/12))*Assumptions!$E$40)*MAX(0,E13*Assumptions!$E$25-D27) -> 0 | F27: =E27*(1-Assumptions!$E$41)+F16*((1-(1-Assumptions!$E$30)^(1/12))*Assumptions!$E$40)*MAX(0,F13*Assumptions!$E$25-E27) -> 0 | G27: =F27*(1-Assumptions!$E$41)+G16*((1-(1-Assumptions!$E$30)^(1/12))*Assumptions!$E$40)*MAX(0,G13*Assumptions!$E$25-F27) -> 0 | H27: =G27*(1-Assumptions!$E$41)+H16*((1-(1-Assumptions!$E$30)^(1/12))*Assumptions!$E$40)*MAX(0,H13*Assumptions!$E$25-G27) -> 0 | I27: =H27*(1-Assumptions!$E$41)+I16*((1-(1-Assumptions!$E$30)^(1/12))*Assumptions!$E$40)*MAX(0,I13*Assumptions!$E$25-H27) -> 0 | J27: =I27*(1-Assumptions!$E$41)+J16*((1-(1-Assumptions!$E$30)^(1/12))*Assumptions!$E$40)*MAX(0,J13*Assumptions!$E$25-I27) -> 0 | K27: =J27*(1-Assumptions!$E$41)+K16*((1-(1-Assumptions!$E$30)^(1/12))*Assumptions!$E$40)*MAX(0,K13*Assumptions!$E$25-J27) -> 0 | ... BK27: =BJ27*(1-Assumptions!$E$41)+BK16*((1-(1-Assumptions!$E$30)^(1/12))*Assumptions!$E$40)*MAX(0,BK13*Assumptions!$E$25-BJ27) -> 66.858522
A28: paid_retail | B28: Paying — Independent retail | C28: 0 | D28: =C28*(1-Assumptions!$E$41)+D16*((1-(1-Assumptions!$E$31)^(1/12))*Assumptions!$E$40)*MAX(0,D13*Assumptions!$E$26-C28) -> 0 | E28: =D28*(1-Assumptions!$E$41)+E16*((1-(1-Assumptions!$E$31)^(1/12))*Assumptions!$E$40)*MAX(0,E13*Assumptions!$E$26-D28) -> 0 | F28: =E28*(1-Assumptions!$E$41)+F16*((1-(1-Assumptions!$E$31)^(1/12))*Assumptions!$E$40)*MAX(0,F13*Assumptions!$E$26-E28) -> 0 | G28: =F28*(1-Assumptions!$E$41)+G16*((1-(1-Assumptions!$E$31)^(1/12))*Assumptions!$E$40)*MAX(0,G13*Assumptions!$E$26-F28) -> 0 | H28: =G28*(1-Assumptions!$E$41)+H16*((1-(1-Assumptions!$E$31)^(1/12))*Assumptions!$E$40)*MAX(0,H13*Assumptions!$E$26-G28) -> 0 | I28: =H28*(1-Assumptions!$E$41)+I16*((1-(1-Assumptions!$E$31)^(1/12))*Assumptions!$E$40)*MAX(0,I13*Assumptions!$E$26-H28) -> 0 | J28: =I28*(1-Assumptions!$E$41)+J16*((1-(1-Assumptions!$E$31)^(1/12))*Assumptions!$E$40)*MAX(0,J13*Assumptions!$E$26-I28) -> 0 | K28: =J28*(1-Assumptions!$E$41)+K16*((1-(1-Assumptions!$E$31)^(1/12))*Assumptions!$E$40)*MAX(0,K13*Assumptions!$E$26-J28) -> 0 | ... BK28: =BJ28*(1-Assumptions!$E$41)+BK16*((1-(1-Assumptions!$E$31)^(1/12))*Assumptions!$E$40)*MAX(0,BK13*Assumptions!$E$26-BJ28) -> 29.938683
A29: paid_repair_auto | B29: Paying — Repair, auto, alterations, print | C29: 0 | D29: =C29*(1-Assumptions!$E$41)+D17*((1-(1-Assumptions!$E$32)^(1/12))*Assumptions!$E$40)*MAX(0,D13*Assumptions!$E$27-C29) -> 0 | E29: =D29*(1-Assumptions!$E$41)+E17*((1-(1-Assumptions!$E$32)^(1/12))*Assumptions!$E$40)*MAX(0,E13*Assumptions!$E$27-D29) -> 0 | F29: =E29*(1-Assumptions!$E$41)+F17*((1-(1-Assumptions!$E$32)^(1/12))*Assumptions!$E$40)*MAX(0,F13*Assumptions!$E$27-E29) -> 0 | G29: =F29*(1-Assumptions!$E$41)+G17*((1-(1-Assumptions!$E$32)^(1/12))*Assumptions!$E$40)*MAX(0,G13*Assumptions!$E$27-F29) -> 0 | H29: =G29*(1-Assumptions!$E$41)+H17*((1-(1-Assumptions!$E$32)^(1/12))*Assumptions!$E$40)*MAX(0,H13*Assumptions!$E$27-G29) -> 0 | I29: =H29*(1-Assumptions!$E$41)+I17*((1-(1-Assumptions!$E$32)^(1/12))*Assumptions!$E$40)*MAX(0,I13*Assumptions!$E$27-H29) -> 0 | J29: =I29*(1-Assumptions!$E$41)+J17*((1-(1-Assumptions!$E$32)^(1/12))*Assumptions!$E$40)*MAX(0,J13*Assumptions!$E$27-I29) -> 0 | K29: =J29*(1-Assumptions!$E$41)+K17*((1-(1-Assumptions!$E$32)^(1/12))*Assumptions!$E$40)*MAX(0,K13*Assumptions!$E$27-J29) -> 0 | ... BK29: =BJ29*(1-Assumptions!$E$41)+BK17*((1-(1-Assumptions!$E$32)^(1/12))*Assumptions!$E$40)*MAX(0,BK13*Assumptions!$E$27-BJ29) -> 68.824206
A30: paid_personal_services | B30: Paying — Salons, barbers, fitness, pets | C30: 0 | D30: =C30*(1-Assumptions!$E$41)+D16*((1-(1-Assumptions!$E$33)^(1/12))*Assumptions!$E$40)*MAX(0,D13*Assumptions!$E$28-C30) -> 0 | E30: =D30*(1-Assumptions!$E$41)+E16*((1-(1-Assumptions!$E$33)^(1/12))*Assumptions!$E$40)*MAX(0,E13*Assumptions!$E$28-D30) -> 0 | F30: =E30*(1-Assumptions!$E$41)+F16*((1-(1-Assumptions!$E$33)^(1/12))*Assumptions!$E$40)*MAX(0,F13*Assumptions!$E$28-E30) -> 0 | G30: =F30*(1-Assumptions!$E$41)+G16*((1-(1-Assumptions!$E$33)^(1/12))*Assumptions!$E$40)*MAX(0,G13*Assumptions!$E$28-F30) -> 0 | H30: =G30*(1-Assumptions!$E$41)+H16*((1-(1-Assumptions!$E$33)^(1/12))*Assumptions!$E$40)*MAX(0,H13*Assumptions!$E$28-G30) -> 0 | I30: =H30*(1-Assumptions!$E$41)+I16*((1-(1-Assumptions!$E$33)^(1/12))*Assumptions!$E$40)*MAX(0,I13*Assumptions!$E$28-H30) -> 0 | J30: =I30*(1-Assumptions!$E$41)+J16*((1-(1-Assumptions!$E$33)^(1/12))*Assumptions!$E$40)*MAX(0,J13*Assumptions!$E$28-I30) -> 0 | K30: =J30*(1-Assumptions!$E$41)+K16*((1-(1-Assumptions!$E$33)^(1/12))*Assumptions!$E$40)*MAX(0,K13*Assumptions!$E$28-J30) -> 0 | ... BK30: =BJ30*(1-Assumptions!$E$41)+BK16*((1-(1-Assumptions!$E$33)^(1/12))*Assumptions!$E$40)*MAX(0,BK13*Assumptions!$E$28-BJ30) -> 17.668848
A31: paid_pharmacy | B31: Paying — Independent pharmacies (front store only) | C31: 0 | D31: =C31*(1-Assumptions!$E$41)+D16*((1-(1-Assumptions!$E$34)^(1/12))*Assumptions!$E$40)*MAX(0,D13*Assumptions!$E$29-C31) -> 0 | E31: =D31*(1-Assumptions!$E$41)+E16*((1-(1-Assumptions!$E$34)^(1/12))*Assumptions!$E$40)*MAX(0,E13*Assumptions!$E$29-D31) -> 0 | F31: =E31*(1-Assumptions!$E$41)+F16*((1-(1-Assumptions!$E$34)^(1/12))*Assumptions!$E$40)*MAX(0,F13*Assumptions!$E$29-E31) -> 0 | G31: =F31*(1-Assumptions!$E$41)+G16*((1-(1-Assumptions!$E$34)^(1/12))*Assumptions!$E$40)*MAX(0,G13*Assumptions!$E$29-F31) -> 0 | H31: =G31*(1-Assumptions!$E$41)+H16*((1-(1-Assumptions!$E$34)^(1/12))*Assumptions!$E$40)*MAX(0,H13*Assumptions!$E$29-G31) -> 0 | I31: =H31*(1-Assumptions!$E$41)+I16*((1-(1-Assumptions!$E$34)^(1/12))*Assumptions!$E$40)*MAX(0,I13*Assumptions!$E$29-H31) -> 0 | J31: =I31*(1-Assumptions!$E$41)+J16*((1-(1-Assumptions!$E$34)^(1/12))*Assumptions!$E$40)*MAX(0,J13*Assumptions!$E$29-I31) -> 0 | K31: =J31*(1-Assumptions!$E$41)+K16*((1-(1-Assumptions!$E$34)^(1/12))*Assumptions!$E$40)*MAX(0,K13*Assumptions!$E$29-J31) -> 0 | ... BK31: =BJ31*(1-Assumptions!$E$41)+BK16*((1-(1-Assumptions!$E$34)^(1/12))*Assumptions!$E$40)*MAX(0,BK13*Assumptions!$E$29-BJ31) -> 4.1499079
A32: paid_total | B32: Paying merchants (total) | C32: 0 | D32: =D27+D28+D29+D30+D31 -> 0 | E32: =E27+E28+E29+E30+E31 -> 0 | F32: =F27+F28+F29+F30+F31 -> 0 | G32: =G27+G28+G29+G30+G31 -> 0 | H32: =H27+H28+H29+H30+H31 -> 0 | I32: =I27+I28+I29+I30+I31 -> 0 | J32: =J27+J28+J29+J30+J31 -> 0 | K32: =K27+K28+K29+K30+K31 -> 0 | ... BK32: =BK27+BK28+BK29+BK30+BK31 -> 187.44017
A33: plus_merchants | B33: Plus merchants | D33: =D27*(1-Assumptions!$E$35)+D28*(1-Assumptions!$E$36)+D29*(1-Assumptions!$E$37)+D30*(1-Assumptions!$E$38)+D31*(1-Assumptions!$E$39) -> 0 | E33: =E27*(1-Assumptions!$E$35)+E28*(1-Assumptions!$E$36)+E29*(1-Assumptions!$E$37)+E30*(1-Assumptions!$E$38)+E31*(1-Assumptions!$E$39) -> 0 | F33: =F27*(1-Assumptions!$E$35)+F28*(1-Assumptions!$E$36)+F29*(1-Assumptions!$E$37)+F30*(1-Assumptions!$E$38)+F31*(1-Assumptions!$E$39) -> 0 | G33: =G27*(1-Assumptions!$E$35)+G28*(1-Assumptions!$E$36)+G29*(1-Assumptions!$E$37)+G30*(1-Assumptions!$E$38)+G31*(1-Assumptions!$E$39) -> 0 | H33: =H27*(1-Assumptions!$E$35)+H28*(1-Assumptions!$E$36)+H29*(1-Assumptions!$E$37)+H30*(1-Assumptions!$E$38)+H31*(1-Assumptions!$E$39) -> 0 | I33: =I27*(1-Assumptions!$E$35)+I28*(1-Assumptions!$E$36)+I29*(1-Assumptions!$E$37)+I30*(1-Assumptions!$E$38)+I31*(1-Assumptions!$E$39) -> 0 | J33: =J27*(1-Assumptions!$E$35)+J28*(1-Assumptions!$E$36)+J29*(1-Assumptions!$E$37)+J30*(1-Assumptions!$E$38)+J31*(1-Assumptions!$E$39) -> 0 | K33: =K27*(1-Assumptions!$E$35)+K28*(1-Assumptions!$E$36)+K29*(1-Assumptions!$E$37)+K30*(1-Assumptions!$E$38)+K31*(1-Assumptions!$E$39) -> 0 | ... BK33: =BK27*(1-Assumptions!$E$35)+BK28*(1-Assumptions!$E$36)+BK29*(1-Assumptions!$E$37)+BK30*(1-Assumptions!$E$38)+BK31*(1-Assumptions!$E$39) -> 118.79908
A34: pro_merchants | B34: Pro merchants | D34: =D27*Assumptions!$E$35+D28*Assumptions!$E$36+D29*Assumptions!$E$37+D30*Assumptions!$E$38+D31*Assumptions!$E$39 -> 0 | E34: =E27*Assumptions!$E$35+E28*Assumptions!$E$36+E29*Assumptions!$E$37+E30*Assumptions!$E$38+E31*Assumptions!$E$39 -> 0 | F34: =F27*Assumptions!$E$35+F28*Assumptions!$E$36+F29*Assumptions!$E$37+F30*Assumptions!$E$38+F31*Assumptions!$E$39 -> 0 | G34: =G27*Assumptions!$E$35+G28*Assumptions!$E$36+G29*Assumptions!$E$37+G30*Assumptions!$E$38+G31*Assumptions!$E$39 -> 0 | H34: =H27*Assumptions!$E$35+H28*Assumptions!$E$36+H29*Assumptions!$E$37+H30*Assumptions!$E$38+H31*Assumptions!$E$39 -> 0 | I34: =I27*Assumptions!$E$35+I28*Assumptions!$E$36+I29*Assumptions!$E$37+I30*Assumptions!$E$38+I31*Assumptions!$E$39 -> 0 | J34: =J27*Assumptions!$E$35+J28*Assumptions!$E$36+J29*Assumptions!$E$37+J30*Assumptions!$E$38+J31*Assumptions!$E$39 -> 0 | K34: =K27*Assumptions!$E$35+K28*Assumptions!$E$36+K29*Assumptions!$E$37+K30*Assumptions!$E$38+K31*Assumptions!$E$39 -> 0 | ... BK34: =BK27*Assumptions!$E$35+BK28*Assumptions!$E$36+BK29*Assumptions!$E$37+BK30*Assumptions!$E$38+BK31*Assumptions!$E$39 -> 68.64109
A35: new_conversions | B35: New paid conversions | D35: =MAX(0,D32-C32*(1-Assumptions!$E$41)) -> 0 | E35: =MAX(0,E32-D32*(1-Assumptions!$E$41)) -> 0 | F35: =MAX(0,F32-E32*(1-Assumptions!$E$41)) -> 0 | G35: =MAX(0,G32-F32*(1-Assumptions!$E$41)) -> 0 | H35: =MAX(0,H32-G32*(1-Assumptions!$E$41)) -> 0 | I35: =MAX(0,I32-H32*(1-Assumptions!$E$41)) -> 0 | J35: =MAX(0,J32-I32*(1-Assumptions!$E$41)) -> 0 | K35: =MAX(0,K32-J32*(1-Assumptions!$E$41)) -> 0 | ... BK35: =MAX(0,BK32-BJ32*(1-Assumptions!$E$41)) -> 10.815706
B36: Revenue (CAD)
A37: rev_plus | B37: Plus subscriptions | D37: =D33*Assumptions!$E$42 -> 0 | E37: =E33*Assumptions!$E$42 -> 0 | F37: =F33*Assumptions!$E$42 -> 0 | G37: =G33*Assumptions!$E$42 -> 0 | H37: =H33*Assumptions!$E$42 -> 0 | I37: =I33*Assumptions!$E$42 -> 0 | J37: =J33*Assumptions!$E$42 -> 0 | K37: =K33*Assumptions!$E$42 -> 0 | ... BK37: =BK33*Assumptions!$E$42 -> 4633.164
A38: rev_pro | B38: Pro subscriptions | D38: =D34*Assumptions!$E$43 -> 0 | E38: =E34*Assumptions!$E$43 -> 0 | F38: =F34*Assumptions!$E$43 -> 0 | G38: =G34*Assumptions!$E$43 -> 0 | H38: =H34*Assumptions!$E$43 -> 0 | I38: =I34*Assumptions!$E$43 -> 0 | J38: =J34*Assumptions!$E$43 -> 0 | K38: =K34*Assumptions!$E$43 -> 0 | ... BK38: =BK34*Assumptions!$E$43 -> 5422.6461
A39: gmv_in_app | B39: In-app payment volume (GMV) | D39: =(D33*Assumptions!$E$46+D34*Assumptions!$E$47)*Assumptions!$E$45 -> 0 | E39: =(E33*Assumptions!$E$46+E34*Assumptions!$E$47)*Assumptions!$E$45 -> 0 | F39: =(F33*Assumptions!$E$46+F34*Assumptions!$E$47)*Assumptions!$E$45 -> 0 | G39: =(G33*Assumptions!$E$46+G34*Assumptions!$E$47)*Assumptions!$E$45 -> 0 | H39: =(H33*Assumptions!$E$46+H34*Assumptions!$E$47)*Assumptions!$E$45 -> 0 | I39: =(I33*Assumptions!$E$46+I34*Assumptions!$E$47)*Assumptions!$E$45 -> 0 | J39: =(J33*Assumptions!$E$46+J34*Assumptions!$E$47)*Assumptions!$E$45 -> 0 | K39: =(K33*Assumptions!$E$46+K34*Assumptions!$E$47)*Assumptions!$E$45 -> 0 | ... BK39: =(BK33*Assumptions!$E$46+BK34*Assumptions!$E$47)*Assumptions!$E$45 -> 425306.54
A40: rev_payments | B40: Platform fee on payments (0.75%) | D40: =D39*Assumptions!$E$44 -> 0 | E40: =E39*Assumptions!$E$44 -> 0 | F40: =F39*Assumptions!$E$44 -> 0 | G40: =G39*Assumptions!$E$44 -> 0 | H40: =H39*Assumptions!$E$44 -> 0 | I40: =I39*Assumptions!$E$44 -> 0 | J40: =J39*Assumptions!$E$44 -> 0 | K40: =K39*Assumptions!$E$44 -> 0 | ... BK40: =BK39*Assumptions!$E$44 -> 3189.799
A41: rev_ads_impressions | B41: Sponsored listings/promos (CPM) | D41: =D24*Assumptions!$E$17*Assumptions!$E$68*Assumptions!$E$69*Assumptions!$E$70*Assumptions!$E$71/1000*D21 -> 0 | E41: =E24*Assumptions!$E$17*Assumptions!$E$68*Assumptions!$E$69*Assumptions!$E$70*Assumptions!$E$71/1000*E21 -> 0 | F41: =F24*Assumptions!$E$17*Assumptions!$E$68*Assumptions!$E$69*Assumptions!$E$70*Assumptions!$E$71/1000*F21 -> 0 | G41: =G24*Assumptions!$E$17*Assumptions!$E$68*Assumptions!$E$69*Assumptions!$E$70*Assumptions!$E$71/1000*G21 -> 0 | H41: =H24*Assumptions!$E$17*Assumptions!$E$68*Assumptions!$E$69*Assumptions!$E$70*Assumptions!$E$71/1000*H21 -> 0 | I41: =I24*Assumptions!$E$17*Assumptions!$E$68*Assumptions!$E$69*Assumptions!$E$70*Assumptions!$E$71/1000*I21 -> 0 | J41: =J24*Assumptions!$E$17*Assumptions!$E$68*Assumptions!$E$69*Assumptions!$E$70*Assumptions!$E$71/1000*J21 -> 0 | K41: =K24*Assumptions!$E$17*Assumptions!$E$68*Assumptions!$E$69*Assumptions!$E$70*Assumptions!$E$71/1000*K21 -> 0 | ... BK41: =BK24*Assumptions!$E$17*Assumptions!$E$68*Assumptions!$E$69*Assumptions!$E$70*Assumptions!$E$71/1000*BK21 -> 413.22846
A42: rev_map_pins | B42: Featured map pins | D42: =D13*Assumptions!$E$72*Assumptions!$E$73*D21 -> 0 | E42: =E13*Assumptions!$E$72*Assumptions!$E$73*E21 -> 0 | F42: =F13*Assumptions!$E$72*Assumptions!$E$73*F21 -> 0 | G42: =G13*Assumptions!$E$72*Assumptions!$E$73*G21 -> 0 | H42: =H13*Assumptions!$E$72*Assumptions!$E$73*H21 -> 0 | I42: =I13*Assumptions!$E$72*Assumptions!$E$73*I21 -> 0 | J42: =J13*Assumptions!$E$72*Assumptions!$E$73*J21 -> 0 | K42: =K13*Assumptions!$E$72*Assumptions!$E$73*K21 -> 0 | ... BK42: =BK13*Assumptions!$E$72*Assumptions!$E$73*BK21 -> 1782.5215
A43: rev_push_boosts | B43: Nearby push boosts | D43: =D13*Assumptions!$E$74*Assumptions!$E$75*Assumptions!$E$76*D21 -> 0 | E43: =E13*Assumptions!$E$74*Assumptions!$E$75*Assumptions!$E$76*E21 -> 0 | F43: =F13*Assumptions!$E$74*Assumptions!$E$75*Assumptions!$E$76*F21 -> 0 | G43: =G13*Assumptions!$E$74*Assumptions!$E$75*Assumptions!$E$76*G21 -> 0 | H43: =H13*Assumptions!$E$74*Assumptions!$E$75*Assumptions!$E$76*H21 -> 0 | I43: =I13*Assumptions!$E$74*Assumptions!$E$75*Assumptions!$E$76*I21 -> 0 | J43: =J13*Assumptions!$E$74*Assumptions!$E$75*Assumptions!$E$76*J21 -> 0 | K43: =K13*Assumptions!$E$74*Assumptions!$E$75*Assumptions!$E$76*K21 -> 0 | ... BK43: =BK13*Assumptions!$E$74*Assumptions!$E$75*Assumptions!$E$76*BK21 -> 1584.4636
A44: bia_campaigns | B44: BIA campaigns sold (expected) | D44: =D10*Assumptions!$E$80/12*D18 -> 0 | E44: =E10*Assumptions!$E$80/12*E18 -> 0 | F44: =F10*Assumptions!$E$80/12*F18 -> 0 | G44: =G10*Assumptions!$E$80/12*G18 -> 0 | H44: =H10*Assumptions!$E$80/12*H18 -> 0 | I44: =I10*Assumptions!$E$80/12*I18 -> 0 | J44: =J10*Assumptions!$E$80/12*J18 -> 0 | K44: =K10*Assumptions!$E$80/12*K18 -> 0 | ... BK44: =BK10*Assumptions!$E$80/12*BK18 -> 4.4166667
A45: rev_bia | B45: BIA neighbourhood campaigns | D45: =D44*Assumptions!$E$81 -> 0 | E45: =E44*Assumptions!$E$81 -> 0 | F45: =F44*Assumptions!$E$81 -> 0 | G45: =G44*Assumptions!$E$81 -> 0 | H45: =H44*Assumptions!$E$81 -> 0 | I45: =I44*Assumptions!$E$81 -> 0 | J45: =J44*Assumptions!$E$81 -> 0 | K45: =K44*Assumptions!$E$81 -> 0 | ... BK45: =BK44*Assumptions!$E$81 -> 9937.5
A46: rev_total | B46: Total revenue | D46: =D37+D38+D40+D41+D42+D43+D45 -> 0 | E46: =E37+E38+E40+E41+E42+E43+E45 -> 0 | F46: =F37+F38+F40+F41+F42+F43+F45 -> 0 | G46: =G37+G38+G40+G41+G42+G43+G45 -> 0 | H46: =H37+H38+H40+H41+H42+H43+H45 -> 0 | I46: =I37+I38+I40+I41+I42+I43+I45 -> 0 | J46: =J37+J38+J40+J41+J42+J43+J45 -> 0 | K46: =K37+K38+K40+K41+K42+K43+K45 -> 0 | ... BK46: =BK37+BK38+BK40+BK41+BK42+BK43+BK45 -> 26963.323
A47: mrr_subscriptions | B47: Subscription MRR | D47: =D37+D38 -> 0 | E47: =E37+E38 -> 0 | F47: =F37+F38 -> 0 | G47: =G37+G38 -> 0 | H47: =H37+H38 -> 0 | I47: =I37+I38 -> 0 | J47: =J37+J38 -> 0 | K47: =K37+K38 -> 0 | ... BK47: =BK37+BK38 -> 10055.81
B48: Variable costs (CAD)
A49: cost_free_merchants | B49: Free-tier merchant cost (infra + support) | D49: =D12*(Assumptions!$E$60+Assumptions!$E$63/60*Assumptions!$E$62) -> 0 | E49: =E12*(Assumptions!$E$60+Assumptions!$E$63/60*Assumptions!$E$62) -> 0 | F49: =F12*(Assumptions!$E$60+Assumptions!$E$63/60*Assumptions!$E$62) -> 0 | G49: =G12*(Assumptions!$E$60+Assumptions!$E$63/60*Assumptions!$E$62) -> 0 | H49: =H12*(Assumptions!$E$60+Assumptions!$E$63/60*Assumptions!$E$62) -> 24.666667 | I49: =I12*(Assumptions!$E$60+Assumptions!$E$63/60*Assumptions!$E$62) -> 46.003333 | J49: =J12*(Assumptions!$E$60+Assumptions!$E$63/60*Assumptions!$E$62) -> 60.113283 | K49: =K12*(Assumptions!$E$60+Assumptions!$E$63/60*Assumptions!$E$62) -> 93.744917 | ... BK49: =BK12*(Assumptions!$E$60+Assumptions!$E$63/60*Assumptions!$E$62) -> 4071.1911
A50: cost_paid_support | B50: Extra support, paying merchants | D50: =D32*Assumptions!$E$64/60*Assumptions!$E$62 -> 0 | E50: =E32*Assumptions!$E$64/60*Assumptions!$E$62 -> 0 | F50: =F32*Assumptions!$E$64/60*Assumptions!$E$62 -> 0 | G50: =G32*Assumptions!$E$64/60*Assumptions!$E$62 -> 0 | H50: =H32*Assumptions!$E$64/60*Assumptions!$E$62 -> 0 | I50: =I32*Assumptions!$E$64/60*Assumptions!$E$62 -> 0 | J50: =J32*Assumptions!$E$64/60*Assumptions!$E$62 -> 0 | K50: =K32*Assumptions!$E$64/60*Assumptions!$E$62 -> 0 | ... BK50: =BK32*Assumptions!$E$64/60*Assumptions!$E$62 -> 1171.501
A51: cost_customer_infra | B51: Customer infra | D51: =D24*Assumptions!$E$61 -> 0 | E51: =E24*Assumptions!$E$61 -> 0 | F51: =F24*Assumptions!$E$61 -> 0 | G51: =G24*Assumptions!$E$61 -> 0 | H51: =H24*Assumptions!$E$61 -> 0.9 | I51: =I24*Assumptions!$E$61 -> 2.2635 | J51: =J24*Assumptions!$E$61 -> 3.6645975 | K51: =K24*Assumptions!$E$61 -> 5.802411 | ... BK51: =BK24*Assumptions!$E$61 -> 409.94887
A52: cost_sms | B52: SMS (Twilio) | D52: =(D33*Assumptions!$E$56+D34*Assumptions!$E$57+D25*Assumptions!$E$58+D24*Assumptions!$E$59)*Assumptions!$E$55 -> 0 | E52: =(E33*Assumptions!$E$56+E34*Assumptions!$E$57+E25*Assumptions!$E$58+E24*Assumptions!$E$59)*Assumptions!$E$55 -> 0 | F52: =(F33*Assumptions!$E$56+F34*Assumptions!$E$57+F25*Assumptions!$E$58+F24*Assumptions!$E$59)*Assumptions!$E$55 -> 0 | G52: =(G33*Assumptions!$E$56+G34*Assumptions!$E$57+G25*Assumptions!$E$58+G24*Assumptions!$E$59)*Assumptions!$E$55 -> 0 | H52: =(H33*Assumptions!$E$56+H34*Assumptions!$E$57+H25*Assumptions!$E$58+H24*Assumptions!$E$59)*Assumptions!$E$55 -> 3.564 | I52: =(I33*Assumptions!$E$56+I34*Assumptions!$E$57+I25*Assumptions!$E$58+I24*Assumptions!$E$59)*Assumptions!$E$55 -> 6.11226 | J52: =(J33*Assumptions!$E$56+J34*Assumptions!$E$57+J25*Assumptions!$E$58+J24*Assumptions!$E$59)*Assumptions!$E$55 -> 7.3410381 | K52: =(K33*Assumptions!$E$56+K34*Assumptions!$E$57+K25*Assumptions!$E$58+K24*Assumptions!$E$59)*Assumptions!$E$55 -> 11.368103 | ... BK52: =(BK33*Assumptions!$E$56+BK34*Assumptions!$E$57+BK25*Assumptions!$E$58+BK24*Assumptions!$E$59)*Assumptions!$E$55 -> 2492.5153
A53: cost_payments | B53: Stripe Connect platform costs | D53: =D39*Assumptions!$E$51+D32*Assumptions!$E$45*Assumptions!$E$52 -> 0 | E53: =E39*Assumptions!$E$51+E32*Assumptions!$E$45*Assumptions!$E$52 -> 0 | F53: =F39*Assumptions!$E$51+F32*Assumptions!$E$45*Assumptions!$E$52 -> 0 | G53: =G39*Assumptions!$E$51+G32*Assumptions!$E$45*Assumptions!$E$52 -> 0 | H53: =H39*Assumptions!$E$51+H32*Assumptions!$E$45*Assumptions!$E$52 -> 0 | I53: =I39*Assumptions!$E$51+I32*Assumptions!$E$45*Assumptions!$E$52 -> 0 | J53: =J39*Assumptions!$E$51+J32*Assumptions!$E$45*Assumptions!$E$52 -> 0 | K53: =K39*Assumptions!$E$51+K32*Assumptions!$E$45*Assumptions!$E$52 -> 0 | ... BK53: =BK39*Assumptions!$E$51+BK32*Assumptions!$E$45*Assumptions!$E$52 -> 1288.1945
A54: cost_billing | B54: Subscription billing fees | D54: =(D37+D38)*Assumptions!$E$53+D32*Assumptions!$E$54 -> 0 | E54: =(E37+E38)*Assumptions!$E$53+E32*Assumptions!$E$54 -> 0 | F54: =(F37+F38)*Assumptions!$E$53+F32*Assumptions!$E$54 -> 0 | G54: =(G37+G38)*Assumptions!$E$53+G32*Assumptions!$E$54 -> 0 | H54: =(H37+H38)*Assumptions!$E$53+H32*Assumptions!$E$54 -> 0 | I54: =(I37+I38)*Assumptions!$E$53+I32*Assumptions!$E$54 -> 0 | J54: =(J37+J38)*Assumptions!$E$53+J32*Assumptions!$E$54 -> 0 | K54: =(K37+K38)*Assumptions!$E$53+K32*Assumptions!$E$54 -> 0 | ... BK54: =(BK37+BK38)*Assumptions!$E$53+BK32*Assumptions!$E$54 -> 398.12959
A55: cost_network_perks | B55: Platform-funded network perks | D55: =D25*Assumptions!$E$65*Assumptions!$E$66*Assumptions!$E$67 -> 0 | E55: =E25*Assumptions!$E$65*Assumptions!$E$66*Assumptions!$E$67 -> 0 | F55: =F25*Assumptions!$E$65*Assumptions!$E$66*Assumptions!$E$67 -> 0 | G55: =G25*Assumptions!$E$65*Assumptions!$E$66*Assumptions!$E$67 -> 0 | H55: =H25*Assumptions!$E$65*Assumptions!$E$66*Assumptions!$E$67 -> 24.3 | I55: =I25*Assumptions!$E$65*Assumptions!$E$66*Assumptions!$E$67 -> 37.7865 | J55: =J25*Assumptions!$E$65*Assumptions!$E$66*Assumptions!$E$67 -> 40.274212 | K55: =K25*Assumptions!$E$65*Assumptions!$E$66*Assumptions!$E$67 -> 61.678731 | ... BK55: =BK25*Assumptions!$E$65*Assumptions!$E$66*Assumptions!$E$67 -> 644.57606
A56: cost_ads_ops | B56: Ad operations | D56: =(D41+D42+D43)*Assumptions!$E$78 -> 0 | E56: =(E41+E42+E43)*Assumptions!$E$78 -> 0 | F56: =(F41+F42+F43)*Assumptions!$E$78 -> 0 | G56: =(G41+G42+G43)*Assumptions!$E$78 -> 0 | H56: =(H41+H42+H43)*Assumptions!$E$78 -> 0 | I56: =(I41+I42+I43)*Assumptions!$E$78 -> 0 | J56: =(J41+J42+J43)*Assumptions!$E$78 -> 0 | K56: =(K41+K42+K43)*Assumptions!$E$78 -> 0 | ... BK56: =(BK41+BK42+BK43)*Assumptions!$E$78 -> 378.02135
A57: cost_bia | B57: BIA campaign delivery | D57: =D45*Assumptions!$E$82 -> 0 | E57: =E45*Assumptions!$E$82 -> 0 | F57: =F45*Assumptions!$E$82 -> 0 | G57: =G45*Assumptions!$E$82 -> 0 | H57: =H45*Assumptions!$E$82 -> 0 | I57: =I45*Assumptions!$E$82 -> 0 | J57: =J45*Assumptions!$E$82 -> 0 | K57: =K45*Assumptions!$E$82 -> 0 | ... BK57: =BK45*Assumptions!$E$82 -> 2981.25
A58: variable_total | B58: Total variable costs | D58: =D49+D50+D51+D52+D53+D54+D55+D56+D57 -> 0 | E58: =E49+E50+E51+E52+E53+E54+E55+E56+E57 -> 0 | F58: =F49+F50+F51+F52+F53+F54+F55+F56+F57 -> 0 | G58: =G49+G50+G51+G52+G53+G54+G55+G56+G57 -> 0 | H58: =H49+H50+H51+H52+H53+H54+H55+H56+H57 -> 53.430667 | I58: =I49+I50+I51+I52+I53+I54+I55+I56+I57 -> 92.165593 | J58: =J49+J50+J51+J52+J53+J54+J55+J56+J57 -> 111.39313 | K58: =K49+K50+K51+K52+K53+K54+K55+K56+K57 -> 172.59416 | ... BK58: =BK49+BK50+BK51+BK52+BK53+BK54+BK55+BK56+BK57 -> 13835.328
A59: gross_profit | B59: Gross profit | D59: =D46-D58 -> 0 | E59: =E46-E58 -> 0 | F59: =F46-F58 -> 0 | G59: =G46-G58 -> 0 | H59: =H46-H58 -> -53.430667 | I59: =I46-I58 -> -92.165593 | J59: =J46-J58 -> -111.39313 | K59: =K46-K58 -> -172.59416 | ... BK59: =BK46-BK58 -> 13127.995
B60: Merchant acquisition (CAC) spend (CAD)
A61: rep_wage | B61: Rep hourly wage (indexed each Oct 1) | D61: =Assumptions!$E$83*(1+Assumptions!$E$84)^INT(D7/12) -> 17.95 | E61: =Assumptions!$E$83*(1+Assumptions!$E$84)^INT(E7/12) -> 17.95 | F61: =Assumptions!$E$83*(1+Assumptions!$E$84)^INT(F7/12) -> 17.95 | G61: =Assumptions!$E$83*(1+Assumptions!$E$84)^INT(G7/12) -> 17.95 | H61: =Assumptions!$E$83*(1+Assumptions!$E$84)^INT(H7/12) -> 17.95 | I61: =Assumptions!$E$83*(1+Assumptions!$E$84)^INT(I7/12) -> 17.95 | J61: =Assumptions!$E$83*(1+Assumptions!$E$84)^INT(J7/12) -> 17.95 | K61: =Assumptions!$E$83*(1+Assumptions!$E$84)^INT(K7/12) -> 17.95 | ... BK61: =Assumptions!$E$83*(1+Assumptions!$E$84)^INT(BK7/12) -> 20.308777
A62: cac_rep_wages | B62: Rep wages incl. payroll burden | D62: =D11*Assumptions!$E$86*D61*(1+Assumptions!$E$85)*Assumptions!$E$91 -> 0 | E62: =E11*Assumptions!$E$86*E61*(1+Assumptions!$E$85)*Assumptions!$E$91 -> 0 | F62: =F11*Assumptions!$E$86*F61*(1+Assumptions!$E$85)*Assumptions!$E$91 -> 0 | G62: =G11*Assumptions!$E$86*G61*(1+Assumptions!$E$85)*Assumptions!$E$91 -> 0 | H62: =H11*Assumptions!$E$86*H61*(1+Assumptions!$E$85)*Assumptions!$E$91 -> 405.67 | I62: =I11*Assumptions!$E$86*I61*(1+Assumptions!$E$85)*Assumptions!$E$91 -> 356.9896 | J62: =J11*Assumptions!$E$86*J61*(1+Assumptions!$E$85)*Assumptions!$E$91 -> 243.402 | K62: =K11*Assumptions!$E$86*K61*(1+Assumptions!$E$85)*Assumptions!$E$91 -> 567.938 | ... BK62: =BK11*Assumptions!$E$86*BK61*(1+Assumptions!$E$85)*Assumptions!$E$91 -> 2460.1241
A63: cac_activation_bonus | B63: Activation bonuses incl. burden | D63: =D14*Assumptions!$E$87*(1+Assumptions!$E$85)*Assumptions!$E$91 -> 0 | E63: =E14*Assumptions!$E$87*(1+Assumptions!$E$85)*Assumptions!$E$91 -> 0 | F63: =F14*Assumptions!$E$87*(1+Assumptions!$E$85)*Assumptions!$E$91 -> 0 | G63: =G14*Assumptions!$E$87*(1+Assumptions!$E$85)*Assumptions!$E$91 -> 0 | H63: =H14*Assumptions!$E$87*(1+Assumptions!$E$85)*Assumptions!$E$91 -> 135.6 | I63: =I14*Assumptions!$E$87*(1+Assumptions!$E$85)*Assumptions!$E$91 -> 119.328 | J63: =J14*Assumptions!$E$87*(1+Assumptions!$E$85)*Assumptions!$E$91 -> 81.36 | K63: =K14*Assumptions!$E$87*(1+Assumptions!$E$85)*Assumptions!$E$91 -> 189.84 | ... BK63: =BK14*Assumptions!$E$87*(1+Assumptions!$E$85)*Assumptions!$E$91 -> 726.816
A64: cac_kits | B64: Counter kits | D64: =D11*Assumptions!$E$88*Assumptions!$E$91 -> 0 | E64: =E11*Assumptions!$E$88*Assumptions!$E$91 -> 0 | F64: =F11*Assumptions!$E$88*Assumptions!$E$91 -> 0 | G64: =G11*Assumptions!$E$88*Assumptions!$E$91 -> 0 | H64: =H11*Assumptions!$E$88*Assumptions!$E$91 -> 120 | I64: =I11*Assumptions!$E$88*Assumptions!$E$91 -> 105.6 | J64: =J11*Assumptions!$E$88*Assumptions!$E$91 -> 72 | K64: =K11*Assumptions!$E$88*Assumptions!$E$91 -> 168 | ... BK64: =BK11*Assumptions!$E$88*Assumptions!$E$91 -> 643.2
A65: cac_strip_launch | B65: Strip launch events | D65: =D8*Assumptions!$E$89*Assumptions!$E$91 -> 0 | E65: =E8*Assumptions!$E$89*Assumptions!$E$91 -> 0 | F65: =F8*Assumptions!$E$89*Assumptions!$E$91 -> 0 | G65: =G8*Assumptions!$E$89*Assumptions!$E$91 -> 0 | H65: =H8*Assumptions!$E$89*Assumptions!$E$91 -> 750 | I65: =I8*Assumptions!$E$89*Assumptions!$E$91 -> 0 | J65: =J8*Assumptions!$E$89*Assumptions!$E$91 -> 0 | K65: =K8*Assumptions!$E$89*Assumptions!$E$91 -> 750 | ... BK65: =BK8*Assumptions!$E$89*Assumptions!$E$91 -> 750
A66: cac_upsell | B66: Paid upsell cost | D66: =D35*Assumptions!$E$90*Assumptions!$E$91 -> 0 | E66: =E35*Assumptions!$E$90*Assumptions!$E$91 -> 0 | F66: =F35*Assumptions!$E$90*Assumptions!$E$91 -> 0 | G66: =G35*Assumptions!$E$90*Assumptions!$E$91 -> 0 | H66: =H35*Assumptions!$E$90*Assumptions!$E$91 -> 0 | I66: =I35*Assumptions!$E$90*Assumptions!$E$91 -> 0 | J66: =J35*Assumptions!$E$90*Assumptions!$E$91 -> 0 | K66: =K35*Assumptions!$E$90*Assumptions!$E$91 -> 0 | ... BK66: =BK35*Assumptions!$E$90*Assumptions!$E$91 -> 540.78532
A67: cac_total | B67: Total acquisition spend | D67: =D62+D63+D64+D65+D66 -> 0 | E67: =E62+E63+E64+E65+E66 -> 0 | F67: =F62+F63+F64+F65+F66 -> 0 | G67: =G62+G63+G64+G65+G66 -> 0 | H67: =H62+H63+H64+H65+H66 -> 1411.27 | I67: =I62+I63+I64+I65+I66 -> 581.9176 | J67: =J62+J63+J64+J65+J66 -> 396.762 | K67: =K62+K63+K64+K65+K66 -> 1675.778 | ... BK67: =BK62+BK63+BK64+BK65+BK66 -> 5120.9254
B68: Fixed operating costs (CAD)
A69: opex_fixed_overhead | B69: Fixed overhead | D69: =Assumptions!$E$108 -> 1465 | E69: =Assumptions!$E$108 -> 1465 | F69: =Assumptions!$E$108 -> 1465 | G69: =Assumptions!$E$108 -> 1465 | H69: =Assumptions!$E$108 -> 1465 | I69: =Assumptions!$E$108 -> 1465 | J69: =Assumptions!$E$108 -> 1465 | K69: =Assumptions!$E$108 -> 1465 | ... BK69: =Assumptions!$E$108 -> 1465
